Workbook

Sheet README
A1: MCED District Account Assistant — Practice Performance Tracker
A2: Practice scoring rule (NOT an official MCED scheme): 1 mark per correct answer, 0 for wrong/unanswered, no negative marking (change only if you deliberately configure another rule).
A4: HOW TO USE (tutor only — this workbook contains the answer key):
A5: 1. Candidate solves the question-only paper without the answer key; tutor records the answers.
A6: 2. Sheet "Attempts": add one row per attempt. Fill the yellow cells: Attempt ID (e.g. A001), Candidate, Date, Paper No (1-11), then the candidate's responses A/B/C/D in Q1..Q30 (leave blank = unanswered).
A7: 3. Green cells calculate automatically: attempted / correct / incorrect / unanswered / score / %.
A8: 4. Sheet "Topic_Accuracy": topic-wise accuracy per attempt, weakest subtopic and recommended remedial lesson.
A9: 5. Sheet "Error_Log": for each wrong answer, choose an error category (Conceptual / Calculation / Terminology / Careless).
A10: 6. Teach the recommended lesson (Remediation Notes), give a short remedial quiz, then record the retest as a new Attempt and link both IDs in sheet "Retest".
A11: 7. Sheet "Baseline_40": enter the candidate's 40 baseline answers for section-wise baseline analysis.
A13: Do NOT label the candidate weak/strong from total score alone; use topic-wise accuracy (suggested guide, not an official cutoff): <50% re-teach, 50-74% practice, >=75% relatively secure. Use topic % only when the subtopic has at least 3 questions.
A14: Rows 2..200 of Attempts are pre-formulated. Copy a row down if you need more.

Sheet Papers
A1: Paper No | B1: Title | C1: Questions | D1: Minutes | E1: Sub1 | F1: Sub2 | G1: Sub3 | H1: Sub4 | I1: Sub5 | J1: Sub6 | K1: Les1 | L1: Les2 | M1: Les3 | N1: Les4 | O1: Les5 | P1: Les6
A2: 1 | B2: Baseline Test Analysis and Remediation | C2: 25 | D2: 35 | E2: A Bookkeeping & Basic Accounting | F2: B Taxation | G2: C Budget & Financial Discipline | H2: D Banking | I2: E Computer & Modern Tools | J2: F Current Affairs / General Awareness | K2: Papers 2–5 (Accounting) | L2: Paper 6 (Taxation) | M2: Paper 7 (Budget) | N2: Paper 8 (Banking) | O2: Paper 9 (Computer/Excel) | P2: Paper 10 (Current Affairs)
A3: 2 | B3: Accounting Fundamentals and Accounting Equation | C3: 23 | D3: 30 | E3: Book-keeping, Accounting आणि Users | F3: Accounts चे प्रकार (Classification) | G3: Accounting Concepts | H3: Accounting Equation | I3: Transactions चा Equation वर परिणाम | K3: Lesson 2.1 Book-keeping vs Accounting | L3: Lesson 2.2 Assets-Liabilities-Capital-Income-Expense | M3: Lesson 2.3 Basic Accounting Concepts | N3: Lesson 2.4 A = L + C सूत्र | O3: Lesson 2.5 Transaction analysis (equation drill)
A4: 3 | B4: Debit, Credit and Journal Entries | C4: 24 | D4: 35 | E4: Golden Rules (Personal/Real/Nominal) | F4: Debit-Credit चा परिणाम | G4: Basic Journal Entries (cash) | H4: Credit व्यवहार, Returns, Discount | I4: Adjustment/Special Entries | J4: Journal Format आणि Terminology | K4: Lesson 3.1 Three Golden Rules | L4: Lesson 3.2 Dr/Cr rule table | M4: Lesson 3.3 Cash transaction journal drill | N4: Lesson 3.4 Credit, Returns, Discount entries | O4: Lesson 3.5 Drawings, Outstanding, Prepaid, Bad debts | P4: Lesson 3.6 Journal format
A5: 4 | B5: Ledger, Cash Book and Trial Balance | C5: 24 | D5: 35 | E5: Ledger posting आणि balancing | F5: Cash Book (single/three column, contra) | G5: Petty Cash / Imprest | H5: Trial Balance आणि errors | I5: Subsidiary Books (Purchases/Sales/Returns) | K5: Lesson 4.1 Ledger T-account आणि balancing | L5: Lesson 4.2 Cash Book प्रकार | M5: Lesson 4.3 Imprest system | N5: Lesson 4.4 Trial Balance व errors | O5: Lesson 4.5 Subsidiary books
A6: 5 | B6: Bank Reconciliation, Depreciation and Final Accounts | C6: 24 | D6: 40 | E6: Bank Reconciliation Statement (BRS) | F6: Depreciation (SLM / WDV) | G6: Trading Account | H6: Profit & Loss Account | I6: Balance Sheet | J6: Adjustments (Outstanding, Prepaid, Bad debts) | K6: Lesson 5.1 BRS step-by-step | L6: Lesson 5.2 Depreciation methods | M6: Lesson 5.3 Trading A/c व Gross Profit | N6: Lesson 5.4 P&L A/c व Net Profit | O6: Lesson 5.5 Balance Sheet मांडणी | P6: Lesson 5.6 Year-end adjustments
A7: 6 | B7: Taxation: GST, Input Tax Credit, TDS and Income Tax Basics | C7: 24 | D7: 35 | E7: GST रचना आणि दर | F7: GST गणना आणि ITC | G7: GST documents/returns | H7: TDS | I7: Income Tax basics | K7: Lesson 6.1 GST structure (CGST/SGST/IGST/rates) | L7: Lesson 6.2 GST calculation आणि ITC set-off | M7: Lesson 6.3 GSTIN, invoice, returns | N7: Lesson 6.4 TDS concept आणि गणना | O7: Lesson 6.5 Income tax basics
A8: 7 | B8: Budget and Financial Discipline | C8: 22 | D8: 30 | E8: Budget basics | F8: Capital vs Revenue (expenditure/receipts) | G8: Budget variance आणि utilisation | H8: Government Budget concepts (deficits, Articles) | I8: Financial discipline आणि internal control | K8: Lesson 7.1 Budget म्हणजे काय | L8: Lesson 7.2 Capital vs Revenue | M8: Lesson 7.3 Variance व grant utilisation | N8: Lesson 7.4 Deficits व Constitution चे Articles | O8: Lesson 7.5 Vouchers, controls, segregation of duties
A9: 8 | B9: Banking and Digital Payment Systems | C9: 22 | D9: 30 | E9: RBI आणि Banking structure | F9: Bank accounts आणि KYC | G9: Cheque आणि Negotiable instruments | H9: NEFT/RTGS/IMPS/UPI | I9: Digital safety आणि fraud | J9: Interest आणि bank calculations | K9: Lesson 8.1 RBI functions, Repo, CRR | L9: Lesson 8.2 Account types, KYC | M9: Lesson 8.3 Cheque basics | N9: Lesson 8.4 NEFT vs RTGS vs IMPS vs UPI | O9: Lesson 8.5 Digital safety | P9: Lesson 8.6 Interest calculation
A10: 9 | B10: Computer Knowledge, Excel and Modern Office Tools | C10: 22 | D10: 30 | E10: Computer basics (hardware/software) | F10: Windows, files आणि shortcuts | G10: Word, Email आणि PDF | H10: Excel basics आणि functions | I10: Excel application (SUMIF, VLOOKUP, %) | J10: Internet, cloud, cyber safety आणि modern tools | K10: Lesson 9.1 Hardware-Software-Memory | L10: Lesson 9.2 Windows आणि shortcuts | M10: Lesson 9.3 Word/Email | N10: Lesson 9.4 Excel functions | O10: Lesson 9.5 Excel लेखा उदाहरणे | P10: Lesson 9.6 Cloud आणि सुरक्षा
A11: 10 | B11: Current Affairs and General Awareness | C11: 22 | D11: 30 | E11: स्थिर General Knowledge (संविधान, संस्था) | F11: Union Budget 2026-27 | G11: Maharashtra Budget 2026-27 आणि राज्य | H11: Taxation/Banking updates | I11: Census 2027 आणि इतर घडामोडी | K11: Lesson 10.1 Static GK (Articles, संस्था, तारखा) | L11: Lesson 10.2 Union Budget 2026-27 आकडे | M11: Lesson 10.3 Maharashtra Budget 2026-27 | N11: Lesson 10.4 GST 2.0, Income-tax Act 2025, RBI | O11: Lesson 10.5 Census 2027
A12: 11 | B12: Comprehensive Mixed Mock Test | C12: 30 | D12: 40 | E12: A Bookkeeping & Accounting | F12: B Taxation | G12: C Budget & Financial Discipline | H12: D Banking | I12: E Computer & Excel | J12: F Current Affairs / General Awareness | K12: Papers 2–5 | L12: Paper 6 | M12: Paper 7 | N12: Paper 8 | O12: Paper 9 | P12: Paper 10

Sheet Key
A1: Paper | B1: Q | C1: Answer | D1: Subtopic# | E1: Subtopic | F1: Level | G1: ID(P*100+Q)
A2: 1 | B2: 1 | C2: B | D2: 1 | E2: A Bookkeeping & Basic Accounting | F2: Foundational | G2: 101
A3: 1 | B3: 2 | C3: A | D3: 1 | E3: A Bookkeeping & Basic Accounting | F3: Foundational | G3: 102
A4: 1 | B4: 3 | C4: D | D4: 2 | E4: B Taxation | F4: Foundational | G4: 103
A5: 1 | B5: 4 | C5: C | D5: 3 | E5: C Budget & Financial Discipline | F5: Foundational | G5: 104
A6: 1 | B6: 5 | C6: B | D6: 4 | E6: D Banking | F6: Foundational | G6: 105
A7: 1 | B7: 6 | C7: D | D7: 5 | E7: E Computer & Modern Tools | F7: Foundational | G7: 106
A8: 1 | B8: 7 | C8: A | D8: 5 | E8: E Computer & Modern Tools | F8: Foundational | G8: 107
A9: 1 | B9: 8 | C9: C | D9: 6 | E9: F Current Affairs / General Awareness | F9: Foundational | G9: 108
A10: 1 | B10: 9 | C10: C | D10: 1 | E10: A Bookkeeping & Basic Accounting | F10: Intermediate | G10: 109
A11: 1 | B11: 10 | C11: A | D11: 1 | E11: A Bookkeeping & Basic Accounting | F11: Intermediate | G11: 110
A12: 1 | B12: 11 | C12: D | D12: 1 | E12: A Bookkeeping & Basic Accounting | F12: Intermediate | G12: 111
A13: 1 | B13: 12 | C13: B | D13: 2 | E13: B Taxation | F13: Intermediate | G13: 112
... A263: 11 | B263: 30 | C263: A | D263: 6 | E263: F Current Affairs / General Awareness | F263: Application | G263: 1130

Sheet SubMap
A1: Paper | B1: Q1 | C1: Q2 | D1: Q3 | E1: Q4 | F1: Q5 | G1: Q6 | H1: Q7 | I1: Q8 | J1: Q9 | K1: Q10 | L1: Q11 | M1: Q12 | N1: Q13 | O1: Q14 | P1: Q15 | Q1: Q16 | R1: Q17 | S1: Q18 | T1: Q19 | U1: Q20 | V1: Q21 | W1: Q22 | X1: Q23 | Y1: Q24 | Z1: Q25 | AA1: Q26 | AB1: Q27 | AC1: Q28 | AD1: Q29 | AE1: Q30
A2: 1 | B2: 1 | C2: 1 | D2: 2 | E2: 3 | F2: 4 | G2: 5 | H2: 5 | I2: 6 | J2: 1 | K2: 1 | L2: 1 | M2: 2 | N2: 2 | O2: 3 | P2: 4 | Q2: 4 | R2: 5 | S2: 6 | T2: 1 | U2: 1 | V2: 2 | W2: 3 | X2: 4 | Y2: 5 | Z2: 6
A3: 2 | B3: 1 | C3: 1 | D3: 2 | E3: 2 | F3: 2 | G3: 2 | H3: 4 | I3: 3 | J3: 3 | K3: 3 | L3: 3 | M3: 5 | N3: 4 | O3: 4 | P3: 4 | Q3: 5 | R3: 5 | S3: 5 | T3: 2 | U3: 5 | V3: 4 | W3: 4 | X3: 5
A4: 3 | B4: 1 | C4: 1 | D4: 1 | E4: 2 | F4: 2 | G4: 2 | H4: 6 | I4: 6 | J4: 3 | K4: 3 | L4: 4 | M4: 4 | N4: 4 | O4: 4 | P4: 5 | Q4: 5 | R4: 5 | S4: 3 | T4: 4 | U4: 2 | V4: 3 | W4: 5 | X4: 4 | Y4: 4
A5: 4 | B5: 1 | C5: 1 | D5: 1 | E5: 2 | F5: 2 | G5: 4 | H5: 4 | I5: 5 | J5: 1 | K5: 1 | L5: 2 | M5: 2 | N5: 2 | O5: 3 | P5: 4 | Q5: 4 | R5: 5 | S5: 4 | T5: 4 | U5: 2 | V5: 1 | W5: 5 | X5: 3 | Y5: 4
A6: 5 | B6: 1 | C6: 1 | D6: 2 | E6: 2 | F6: 3 | G6: 4 | H6: 5 | I6: 3 | J6: 1 | K6: 1 | L6: 2 | M6: 2 | N6: 3 | O6: 4 | P6: 6 | Q6: 6 | R6: 5 | S6: 6 | T6: 2 | U6: 1 | V6: 4 | W6: 5 | X6: 3 | Y6: 2
A7: 6 | B7: 1 | C7: 1 | D7: 1 | E7: 1 | F7: 2 | G7: 3 | H7: 4 | I7: 5 | J7: 2 | K7: 2 | L7: 2 | M7: 2 | N7: 3 | O7: 2 | P7: 4 | Q7: 4 | R7: 5 | S7: 2 | T7: 2 | U7: 4 | V7: 1 | W7: 2 | X7: 5 | Y7: 5
A8: 7 | B8: 1 | C8: 4 | D8: 2 | E8: 2 | F8: 4 | G8: 5 | H8: 5 | I8: 3 | J8: 3 | K8: 4 | L8: 4 | M8: 4 | N8: 2 | O8: 4 | P8: 5 | Q8: 1 | R8: 3 | S8: 3 | T8: 2 | U8: 5 | V8: 4 | W8: 4
A9: 8 | B9: 1 | C9: 1 | D9: 2 | E9: 2 | F9: 3 | G9: 4 | H9: 4 | I9: 5 | J9: 4 | K9: 3 | L9: 1 | M9: 1 | N9: 4 | O9: 4 | P9: 2 | Q9: 3 | R9: 6 | S9: 6 | T9: 6 | U9: 4 | V9: 5 | W9: 6
A10: 9 | B10: 1 | C10: 1 | D10: 2 | E10: 2 | F10: 3 | G10: 3 | H10: 4 | I10: 4 | J10: 4 | K10: 4 | L10: 5 | M10: 5 | N10: 4 | O10: 6 | P10: 6 | Q10: 2 | R10: 5 | S10: 5 | T10: 4 | U10: 5 | V10: 6 | W10: 6
A11: 10 | B11: 2 | C11: 1 | D11: 1 | E11: 4 | F11: 1 | G11: 1 | H11: 1 | I11: 4 | J11: 2 | K11: 2 | L11: 2 | M11: 2 | N11: 3 | O11: 3 | P11: 5 | Q11: 5 | R11: 3 | S11: 3 | T11: 2 | U11: 4 | V11: 4 | W11: 5
A12: 11 | B12: 1 | C12: 1 | D12: 1 | E12: 2 | F12: 3 | G12: 4 | H12: 4 | I12: 5 | J12: 5 | K12: 6 | L12: 1 | M12: 1 | N12: 1 | O12: 1 | P12: 2 | Q12: 2 | R12: 3 | S12: 3 | T12: 4 | U12: 4 | V12: 5 | W12: 6 | X12: 1 | Y12: 1 | Z12: 1 | AA12: 2 | AB12: 3 | AC12: 4 | AD12: 5 | AE12: 6

Sheet Attempts
A1: Attempt ID | B1: Candidate | C1: Date | D1: Paper No | E1: Topic | F1: Total Qs | G1: Attempted | H1: Correct | I1: Incorrect | J1: Unanswered | K1: Score | L1: % | M1: Q1 | N1: Q2 | O1: Q3 | P1: Q4 | Q1: Q5 | R1: Q6 | S1: Q7 | T1: Q8 | U1: Q9 | V1: Q10 | W1: Q11 | X1: Q12 | Y1: Q13 | Z1: Q14 | AA1: Q15 | AB1: Q16 | AC1: Q17 | AD1: Q18 | AE1: Q19 | AF1: Q20 | AG1: Q21 | AH1: Q22 | AI1: Q23 | AJ1: Q24 | AK1: Q25 | AL1: Q26 | AM1: Q27 | AN1: Q28 | AO1: Q29 | AP1: Q30 | AQ1: → flags | AR1: f1 | AS1: f2 | AT1: f3 | AU1: f4 | AV1: f5 | AW1: f6 | AX1: f7 | AY1: f8 | AZ1: f9 | BA1: f10 | BB1: f11 | BC1: f12 | BD1: f13 | BE1: f14 | BF1: f15 | BG1: f16 | BH1: f17 | BI1: f18 | BJ1: f19 | BK1: f20 | BL1: f21 | BM1: f22 | BN1: f23 | BO1: f24 | BP1: f25 | BQ1: f26 | BR1: f27 | BS1: f28 | BT1: f29 | BU1: f30
E2: =IF($D2="","",IFERROR(INDEX(Papers!$B$2:$B$12,MATCH($D2,Papers!$A$2:$A$12,0)),"?")) | F2: =IF($D2="","",IFERROR(INDEX(Papers!$C$2:$C$12,MATCH($D2,Papers!$A$2:$A$12,0)),0)) | G2: =IF($D2="","",COUNTIF(M2:AP2,"?*")) | H2: =IF($D2="","",SUM(AR2:BU2)) | I2: =IF($D2="","",G2-H2) | J2: =IF($D2="","",F2-G2) | K2: =IF($D2="","",H2) | L2: =IF($D2="","",IF(F2=0,"",ROUND(H2/F2*100,1))) | AR2: =IF(OR($D2="",M2="",1>$F2),0,IF(UPPER(TRIM(M2))=IFERROR(INDEX(Key!$C$2:$C$263,MATCH($D2*100+1,Key!$G$2:$G$263,0)),"#"),1,0)) | AS2: =IF(OR($D2="",N2="",2>$F2),0,IF(UPPER(TRIM(N2))=IFERROR(INDEX(Key!$C$2:$C$263,MATCH($D2*100+2,Key!$G$2:$G$263,0)),"#"),1,0)) | AT2: =IF(OR($D2="",O2="",3>$F2),0,IF(UPPER(TRIM(O2))=IFERROR(INDEX(Key!$C$2:$C$263,MATCH($D2*100+3,Key!$G$2:$G$263,0)),"#"),1,0)) | AU2: =IF(OR($D2="",P2="",4>$F2),0,IF(UPPER(TRIM(P2))=IFERROR(INDEX(Key!$C$2:$C$263,MATCH($D2*100+4,Key!$G$2:$G$263,0)),"#"),1,0)) | AV2: =IF(OR($D2="",Q2="",5>$F2),0,IF(UPPER(TRIM(Q2))=IFERROR(INDEX(Key!$C$2:$C$263,MATCH($D2*100+5,Key!$G$2:$G$263,0)),"#"),1,0)) | AW2: =IF(OR($D2="",R2="",6>$F2),0,IF(UPPER(TRIM(R2))=IFERROR(INDEX(Key!$C$2:$C$263,MATCH($D2*100+6,Key!$G$2:$G$263,0)),"#"),1,0)) | AX2: =IF(OR($D2="",S2="",7>$F2),0,IF(UPPER(TRIM(S2))=IFERROR(INDEX(Key!$C$2:$C$263,MATCH($D2*100+7,Key!$G$2:$G$263,0)),"#"),1,0)) | AY2: =IF(OR($D2="",T2="",8>$F2),0,IF(UPPER(TRIM(T2))=IFERROR(INDEX(Key!$C$2:$C$263,MATCH($D2*100+8,Key!$G$2:$G$263,0)),"#"),1,0)) | AZ2: =IF(OR($D2="",U2="",9>$F2),0,IF(UPPER(TRIM(U2))=IFERROR(INDEX(Key!$C$2:$C$263,MATCH($D2*100+9,Key!$G$2:$G$263,0)),"#"),1,0)) | BA2: =IF(OR($D2="",V2="",10>$F2),0,IF(UPPER(TRIM(V2))=IFERROR(INDEX(Key!$C$2:$C$263,MATCH($D2*100+10,Key!$G$2:$G$263,0)),"#"),1,0)) | BB2: =IF(OR($D2="",W2="",11>$F2),0,IF(UPPER(TRIM(W2))=IFERROR(INDEX(Key!$C$2:$C$263,MATCH($D2*100+11,Key!$G$2:$G$263,0)),"#"),1,0)) | BC2: =IF(OR($D2="",X2="",12>$F2),0,IF(UPPER(TRIM(X2))=IFERROR(INDEX(Key!$C$2:$C$263,MATCH($D2*100+12,Key!$G$2:$G$263,0)),"#"),1,0)) | BD2: =IF(OR($D2="",Y2="",13>$F2),0,IF(UPPER(TRIM(Y2))=IFERROR(INDEX(Key!$C$2:$C$263,MATCH($D2*100+13,Key!$G$2:$G$263,0)),"#"),1,0)) | BE2: =IF(OR($D2="",Z2="",14>$F2),0,IF(UPPER(TRIM(Z2))=IFERROR(INDEX(Key!$C$2:$C$263,MATCH($D2*100+14,Key!$G$2:$G$263,0)),"#"),1,0)) | BF2: =IF(OR($D2="",AA2="",15>$F2),0,IF(UPPER(TRIM(AA2))=IFERROR(INDEX(Key!$C$2:$C$263,MATCH($D2*100+15,Key!$G$2:$G$263,0)),"#"),1,0)) | BG2: =IF(OR($D2="",AB2="",16>$F2),0,IF(UPPER(TRIM(AB2))=IFERROR(INDEX(Key!$C$2:$C$263,MATCH($D2*100+16,Key!$G$2:$G$263,0)),"#"),1,0)) | BH2: =IF(OR($D2="",AC2="",17>$F2),0,IF(UPPER(TRIM(AC2))=IFERROR(INDEX(Key!$C$2:$C$263,MATCH($D2*100+17,Key!$G$2:$G$263,0)),"#"),1,0)) | BI2: =IF(OR($D2="",AD2="",18>$F2),0,IF(UPPER(TRIM(AD2))=IFERROR(INDEX(Key!$C$2:$C$263,MATCH($D2*100+18,Key!$G$2:$G$263,0)),"#"),1,0)) | BJ2: =IF(OR($D2="",AE2="",19>$F2),0,IF(UPPER(TRIM(AE2))=IFERROR(INDEX(Key!$C$2:$C$263,MATCH($D2*100+19,Key!$G$2:$G$263,0)),"#"),1,0)) | BK2: =IF(OR($D2="",AF2="",20>$F2),0,IF(UPPER(TRIM(AF2))=IFERROR(INDEX(Key!$C$2:$C$263,MATCH($D2*100+20,Key!$G$2:$G$263,0)),"#"),1,0)) | BL2: =IF(OR($D2="",AG2="",21>$F2),0,IF(UPPER(TRIM(AG2))=IFERROR(INDEX(Key!$C$2:$C$263,MATCH($D2*100+21,Key!$G$2:$G$263,0)),"#"),1,0)) | BM2: =IF(OR($D2="",AH2="",22>$F2),0,IF(UPPER(TRIM(AH2))=IFERROR(INDEX(Key!$C$2:$C$263,MATCH($D2*100+22,Key!$G$2:$G$263,0)),"#"),1,0)) | BN2: =IF(OR($D2="",AI2="",23>$F2),0,IF(UPPER(TRIM(AI2))=IFERROR(INDEX(Key!$C$2:$C$263,MATCH($D2*100+23,Key!$G$2:$G$263,0)),"#"),1,0)) | BO2: =IF(OR($D2="",AJ2="",24>$F2),0,IF(UPPER(TRIM(AJ2))=IFERROR(INDEX(Key!$C$2:$C$263,MATCH($D2*100+24,Key!$G$2:$G$263,0)),"#"),1,0)) | BP2: =IF(OR($D2="",AK2="",25>$F2),0,IF(UPPER(TRIM(AK2))=IFERROR(INDEX(Key!$C$2:$C$263,MATCH($D2*100+25,Key!$G$2:$G$263,0)),"#"),1,0)) | BQ2: =IF(OR($D2="",AL2="",26>$F2),0,IF(UPPER(TRIM(AL2))=IFERROR(INDEX(Key!$C$2:$C$263,MATCH($D2*100+26,Key!$G$2:$G$263,0)),"#"),1,0)) | BR2: =IF(OR($D2="",AM2="",27>$F2),0,IF(UPPER(TRIM(AM2))=IFERROR(INDEX(Key!$C$2:$C$263,MATCH($D2*100+27,Key!$G$2:$G$263,0)),"#"),1,0)) | BS2: =IF(OR($D2="",AN2="",28>$F2),0,IF(UPPER(TRIM(AN2))=IFERROR(INDEX(Key!$C$2:$C$263,MATCH($D2*100+28,Key!$G$2:$G$263,0)),"#"),1,0)) | BT2: =IF(OR($D2="",AO2="",29>$F2),0,IF(UPPER(TRIM(AO2))=IFERROR(INDEX(Key!$C$2:$C$263,MATCH($D2*100+29,Key!$G$2:$G$263,0)),"#"),1,0)) | BU2: =IF(OR($D2="",AP2="",30>$F2),0,IF(UPPER(TRIM(AP2))=IFERROR(INDEX(Key!$C$2:$C$263,MATCH($D2*100+30,Key!$G$2:$G$263,0)),"#"),1,0))
E3: =IF($D3="","",IFERROR(INDEX(Papers!$B$2:$B$12,MATCH($D3,Papers!$A$2:$A$12,0)),"?")) | F3: =IF($D3="","",IFERROR(INDEX(Papers!$C$2:$C$12,MATCH($D3,Papers!$A$2:$A$12,0)),0)) | G3: =IF($D3="","",COUNTIF(M3:AP3,"?*")) | H3: =IF($D3="","",SUM(AR3:BU3)) | I3: =IF($D3="","",G3-H3) | J3: =IF($D3="","",F3-G3) | K3: =IF($D3="","",H3) | L3: =IF($D3="","",IF(F3=0,"",ROUND(H3/F3*100,1))) | AR3: =IF(OR($D3="",M3="",1>$F3),0,IF(UPPER(TRIM(M3))=IFERROR(INDEX(Key!$C$2:$C$263,MATCH($D3*100+1,Key!$G$2:$G$263,0)),"#"),1,0)) | AS3: =IF(OR($D3="",N3="",2>$F3),0,IF(UPPER(TRIM(N3))=IFERROR(INDEX(Key!$C$2:$C$263,MATCH($D3*100+2,Key!$G$2:$G$263,0)),"#"),1,0)) | AT3: =IF(OR($D3="",O3="",3>$F3),0,IF(UPPER(TRIM(O3))=IFERROR(INDEX(Key!$C$2:$C$263,MATCH($D3*100+3,Key!$G$2:$G$263,0)),"#"),1,0)) | AU3: =IF(OR($D3="",P3="",4>$F3),0,IF(UPPER(TRIM(P3))=IFERROR(INDEX(Key!$C$2:$C$263,MATCH($D3*100+4,Key!$G$2:$G$263,0)),"#"),1,0)) | AV3: =IF(OR($D3="",Q3="",5>$F3),0,IF(UPPER(TRIM(Q3))=IFERROR(INDEX(Key!$C$2:$C$263,MATCH($D3*100+5,Key!$G$2:$G$263,0)),"#"),1,0)) | AW3: =IF(OR($D3="",R3="",6>$F3),0,IF(UPPER(TRIM(R3))=IFERROR(INDEX(Key!$C$2:$C$263,MATCH($D3*100+6,Key!$G$2:$G$263,0)),"#"),1,0)) | AX3: =IF(OR($D3="",S3="",7>$F3),0,IF(UPPER(TRIM(S3))=IFERROR(INDEX(Key!$C$2:$C$263,MATCH($D3*100+7,Key!$G$2:$G$263,0)),"#"),1,0)) | AY3: =IF(OR($D3="",T3="",8>$F3),0,IF(UPPER(TRIM(T3))=IFERROR(INDEX(Key!$C$2:$C$263,MATCH($D3*100+8,Key!$G$2:$G$263,0)),"#"),1,0)) | AZ3: =IF(OR($D3="",U3="",9>$F3),0,IF(UPPER(TRIM(U3))=IFERROR(INDEX(Key!$C$2:$C$263,MATCH($D3*100+9,Key!$G$2:$G$263,0)),"#"),1,0)) | BA3: =IF(OR($D3="",V3="",10>$F3),0,IF(UPPER(TRIM(V3))=IFERROR(INDEX(Key!$C$2:$C$263,MATCH($D3*100+10,Key!$G$2:$G$263,0)),"#"),1,0)) | BB3: =IF(OR($D3="",W3="",11>$F3),0,IF(UPPER(TRIM(W3))=IFERROR(INDEX(Key!$C$2:$C$263,MATCH($D3*100+11,Key!$G$2:$G$263,0)),"#"),1,0)) | BC3: =IF(OR($D3="",X3="",12>$F3),0,IF(UPPER(TRIM(X3))=IFERROR(INDEX(Key!$C$2:$C$263,MATCH($D3*100+12,Key!$G$2:$G$263,0)),"#"),1,0)) | BD3: =IF(OR($D3="",Y3="",13>$F3),0,IF(UPPER(TRIM(Y3))=IFERROR(INDEX(Key!$C$2:$C$263,MATCH($D3*100+13,Key!$G$2:$G$263,0)),"#"),1,0)) | BE3: =IF(OR($D3="",Z3="",14>$F3),0,IF(UPPER(TRIM(Z3))=IFERROR(INDEX(Key!$C$2:$C$263,MATCH($D3*100+14,Key!$G$2:$G$263,0)),"#"),1,0)) | BF3: =IF(OR($D3="",AA3="",15>$F3),0,IF(UPPER(TRIM(AA3))=IFERROR(INDEX(Key!$C$2:$C$263,MATCH($D3*100+15,Key!$G$2:$G$263,0)),"#"),1,0)) | BG3: =IF(OR($D3="",AB3="",16>$F3),0,IF(UPPER(TRIM(AB3))=IFERROR(INDEX(Key!$C$2:$C$263,MATCH($D3*100+16,Key!$G$2:$G$263,0)),"#"),1,0)) | BH3: =IF(OR($D3="",AC3="",17>$F3),0,IF(UPPER(TRIM(AC3))=IFERROR(INDEX(Key!$C$2:$C$263,MATCH($D3*100+17,Key!$G$2:$G$263,0)),"#"),1,0)) | BI3: =IF(OR($D3="",AD3="",18>$F3),0,IF(UPPER(TRIM(AD3))=IFERROR(INDEX(Key!$C$2:$C$263,MATCH($D3*100+18,Key!$G$2:$G$263,0)),"#"),1,0)) | BJ3: =IF(OR($D3="",AE3="",19>$F3),0,IF(UPPER(TRIM(AE3))=IFERROR(INDEX(Key!$C$2:$C$263,MATCH($D3*100+19,Key!$G$2:$G$263,0)),"#"),1,0)) | BK3: =IF(OR($D3="",AF3="",20>$F3),0,IF(UPPER(TRIM(AF3))=IFERROR(INDEX(Key!$C$2:$C$263,MATCH($D3*100+20,Key!$G$2:$G$263,0)),"#"),1,0)) | BL3: =IF(OR($D3="",AG3="",21>$F3),0,IF(UPPER(TRIM(AG3))=IFERROR(INDEX(Key!$C$2:$C$263,MATCH($D3*100+21,Key!$G$2:$G$263,0)),"#"),1,0)) | BM3: =IF(OR($D3="",AH3="",22>$F3),0,IF(UPPER(TRIM(AH3))=IFERROR(INDEX(Key!$C$2:$C$263,MATCH($D3*100+22,Key!$G$2:$G$263,0)),"#"),1,0)) | BN3: =IF(OR($D3="",AI3="",23>$F3),0,IF(UPPER(TRIM(AI3))=IFERROR(INDEX(Key!$C$2:$C$263,MATCH($D3*100+23,Key!$G$2:$G$263,0)),"#"),1,0)) | BO3: =IF(OR($D3="",AJ3="",24>$F3),0,IF(UPPER(TRIM(AJ3))=IFERROR(INDEX(Key!$C$2:$C$263,MATCH($D3*100+24,Key!$G$2:$G$263,0)),"#"),1,0)) | BP3: =IF(OR($D3="",AK3="",25>$F3),0,IF(UPPER(TRIM(AK3))=IFERROR(INDEX(Key!$C$2:$C$263,MATCH($D3*100+25,Key!$G$2:$G$263,0)),"#"),1,0)) | BQ3: =IF(OR($D3="",AL3="",26>$F3),0,IF(UPPER(TRIM(AL3))=IFERROR(INDEX(Key!$C$2:$C$263,MATCH($D3*100+26,Key!$G$2:$G$263,0)),"#"),1,0)) | BR3: =IF(OR($D3="",AM3="",27>$F3),0,IF(UPPER(TRIM(AM3))=IFERROR(INDEX(Key!$C$2:$C$263,MATCH($D3*100+27,Key!$G$2:$G$263,0)),"#"),1,0)) | BS3: =IF(OR($D3="",AN3="",28>$F3),0,IF(UPPER(TRIM(AN3))=IFERROR(INDEX(Key!$C$2:$C$263,MATCH($D3*100+28,Key!$G$2:$G$263,0)),"#"),1,0)) | BT3: =IF(OR($D3="",AO3="",29>$F3),0,IF(UPPER(TRIM(AO3))=IFERROR(INDEX(Key!$C$2:$C$263,MATCH($D3*100+29,Key!$G$2:$G$263,0)),"#"),1,0)) | BU3: =IF(OR($D3="",AP3="",30>$F3),0,IF(UPPER(TRIM(AP3))=IFERROR(INDEX(Key!$C$2:$C$263,MATCH($D3*100+30,Key!$G$2:$G$263,0)),"#"),1,0))
E4: =IF($D4="","",IFERROR(INDEX(Papers!$B$2:$B$12,MATCH($D4,Papers!$A$2:$A$12,0)),"?")) | F4: =IF($D4="","",IFERROR(INDEX(Papers!$C$2:$C$12,MATCH($D4,Papers!$A$2:$A$12,0)),0)) | G4: =IF($D4="","",COUNTIF(M4:AP4,"?*")) | H4: =IF($D4="","",SUM(AR4:BU4)) | I4: =IF($D4="","",G4-H4) | J4: =IF($D4="","",F4-G4) | K4: =IF($D4="","",H4) | L4: =IF($D4="","",IF(F4=0,"",ROUND(H4/F4*100,1))) | AR4: =IF(OR($D4="",M4="",1>$F4),0,IF(UPPER(TRIM(M4))=IFERROR(INDEX(Key!$C$2:$C$263,MATCH($D4*100+1,Key!$G$2:$G$263,0)),"#"),1,0)) | AS4: =IF(OR($D4="",N4="",2>$F4),0,IF(UPPER(TRIM(N4))=IFERROR(INDEX(Key!$C$2:$C$263,MATCH($D4*100+2,Key!$G$2:$G$263,0)),"#"),1,0)) | AT4: =IF(OR($D4="",O4="",3>$F4),0,IF(UPPER(TRIM(O4))=IFERROR(INDEX(Key!$C$2:$C$263,MATCH($D4*100+3,Key!$G$2:$G$263,0)),"#"),1,0)) | AU4: =IF(OR($D4="",P4="",4>$F4),0,IF(UPPER(TRIM(P4))=IFERROR(INDEX(Key!$C$2:$C$263,MATCH($D4*100+4,Key!$G$2:$G$263,0)),"#"),1,0)) | AV4: =IF(OR($D4="",Q4="",5>$F4),0,IF(UPPER(TRIM(Q4))=IFERROR(INDEX(Key!$C$2:$C$263,MATCH($D4*100+5,Key!$G$2:$G$263,0)),"#"),1,0)) | AW4: =IF(OR($D4="",R4="",6>$F4),0,IF(UPPER(TRIM(R4))=IFERROR(INDEX(Key!$C$2:$C$263,MATCH($D4*100+6,Key!$G$2:$G$263,0)),"#"),1,0)) | AX4: =IF(OR($D4="",S4="",7>$F4),0,IF(UPPER(TRIM(S4))=IFERROR(INDEX(Key!$C$2:$C$263,MATCH($D4*100+7,Key!$G$2:$G$263,0)),"#"),1,0)) | AY4: =IF(OR($D4="",T4="",8>$F4),0,IF(UPPER(TRIM(T4))=IFERROR(INDEX(Key!$C$2:$C$263,MATCH($D4*100+8,Key!$G$2:$G$263,0)),"#"),1,0)) | AZ4: =IF(OR($D4="",U4="",9>$F4),0,IF(UPPER(TRIM(U4))=IFERROR(INDEX(Key!$C$2:$C$263,MATCH($D4*100+9,Key!$G$2:$G$263,0)),"#"),1,0)) | BA4: =IF(OR($D4="",V4="",10>$F4),0,IF(UPPER(TRIM(V4))=IFERROR(INDEX(Key!$C$2:$C$263,MATCH($D4*100+10,Key!$G$2:$G$263,0)),"#"),1,0)) | BB4: =IF(OR($D4="",W4="",11>$F4),0,IF(UPPER(TRIM(W4))=IFERROR(INDEX(Key!$C$2:$C$263,MATCH($D4*100+11,Key!$G$2:$G$263,0)),"#"),1,0)) | BC4: =IF(OR($D4="",X4="",12>$F4),0,IF(UPPER(TRIM(X4))=IFERROR(INDEX(Key!$C$2:$C$263,MATCH($D4*100+12,Key!$G$2:$G$263,0)),"#"),1,0)) | BD4: =IF(OR($D4="",Y4="",13>$F4),0,IF(UPPER(TRIM(Y4))=IFERROR(INDEX(Key!$C$2:$C$263,MATCH($D4*100+13,Key!$G$2:$G$263,0)),"#"),1,0)) | BE4: =IF(OR($D4="",Z4="",14>$F4),0,IF(UPPER(TRIM(Z4))=IFERROR(INDEX(Key!$C$2:$C$263,MATCH($D4*100+14,Key!$G$2:$G$263,0)),"#"),1,0)) | BF4: =IF(OR($D4="",AA4="",15>$F4),0,IF(UPPER(TRIM(AA4))=IFERROR(INDEX(Key!$C$2:$C$263,MATCH($D4*100+15,Key!$G$2:$G$263,0)),"#"),1,0)) | BG4: =IF(OR($D4="",AB4="",16>$F4),0,IF(UPPER(TRIM(AB4))=IFERROR(INDEX(Key!$C$2:$C$263,MATCH($D4*100+16,Key!$G$2:$G$263,0)),"#"),1,0)) | BH4: =IF(OR($D4="",AC4="",17>$F4),0,IF(UPPER(TRIM(AC4))=IFERROR(INDEX(Key!$C$2:$C$263,MATCH($D4*100+17,Key!$G$2:$G$263,0)),"#"),1,0)) | BI4: =IF(OR($D4="",AD4="",18>$F4),0,IF(UPPER(TRIM(AD4))=IFERROR(INDEX(Key!$C$2:$C$263,MATCH($D4*100+18,Key!$G$2:$G$263,0)),"#"),1,0)) | BJ4: =IF(OR($D4="",AE4="",19>$F4),0,IF(UPPER(TRIM(AE4))=IFERROR(INDEX(Key!$C$2:$C$263,MATCH($D4*100+19,Key!$G$2:$G$263,0)),"#"),1,0)) | BK4: =IF(OR($D4="",AF4="",20>$F4),0,IF(UPPER(TRIM(AF4))=IFERROR(INDEX(Key!$C$2:$C$263,MATCH($D4*100+20,Key!$G$2:$G$263,0)),"#"),1,0)) | BL4: =IF(OR($D4="",AG4="",21>$F4),0,IF(UPPER(TRIM(AG4))=IFERROR(INDEX(Key!$C$2:$C$263,MATCH($D4*100+21,Key!$G$2:$G$263,0)),"#"),1,0)) | BM4: =IF(OR($D4="",AH4="",22>$F4),0,IF(UPPER(TRIM(AH4))=IFERROR(INDEX(Key!$C$2:$C$263,MATCH($D4*100+22,Key!$G$2:$G$263,0)),"#"),1,0)) | BN4: =IF(OR($D4="",AI4="",23>$F4),0,IF(UPPER(TRIM(AI4))=IFERROR(INDEX(Key!$C$2:$C$263,MATCH($D4*100+23,Key!$G$2:$G$263,0)),"#"),1,0)) | BO4: =IF(OR($D4="",AJ4="",24>$F4),0,IF(UPPER(TRIM(AJ4))=IFERROR(INDEX(Key!$C$2:$C$263,MATCH($D4*100+24,Key!$G$2:$G$263,0)),"#"),1,0)) | BP4: =IF(OR($D4="",AK4="",25>$F4),0,IF(UPPER(TRIM(AK4))=IFERROR(INDEX(Key!$C$2:$C$263,MATCH($D4*100+25,Key!$G$2:$G$263,0)),"#"),1,0)) | BQ4: =IF(OR($D4="",AL4="",26>$F4),0,IF(UPPER(TRIM(AL4))=IFERROR(INDEX(Key!$C$2:$C$263,MATCH($D4*100+26,Key!$G$2:$G$263,0)),"#"),1,0)) | BR4: =IF(OR($D4="",AM4="",27>$F4),0,IF(UPPER(TRIM(AM4))=IFERROR(INDEX(Key!$C$2:$C$263,MATCH($D4*100+27,Key!$G$2:$G$263,0)),"#"),1,0)) | BS4: =IF(OR($D4="",AN4="",28>$F4),0,IF(UPPER(TRIM(AN4))=IFERROR(INDEX(Key!$C$2:$C$263,MATCH($D4*100+28,Key!$G$2:$G$263,0)),"#"),1,0)) | BT4: =IF(OR($D4="",AO4="",29>$F4),0,IF(UPPER(TRIM(AO4))=IFERROR(INDEX(Key!$C$2:$C$263,MATCH($D4*100+29,Key!$G$2:$G$263,0)),"#"),1,0)) | BU4: =IF(OR($D4="",AP4="",30>$F4),0,IF(UPPER(TRIM(AP4))=IFERROR(INDEX(Key!$C$2:$C$263,MATCH($D4*100+30,Key!$G$2:$G$263,0)),"#"),1,0))
E5: =IF($D5="","",IFERROR(INDEX(Papers!$B$2:$B$12,MATCH($D5,Papers!$A$2:$A$12,0)),"?")) | F5: =IF($D5="","",IFERROR(INDEX(Papers!$C$2:$C$12,MATCH($D5,Papers!$A$2:$A$12,0)),0)) | G5: =IF($D5="","",COUNTIF(M5:AP5,"?*")) | H5: =IF($D5="","",SUM(AR5:BU5)) | I5: =IF($D5="","",G5-H5) | J5: =IF($D5="","",F5-G5) | K5: =IF($D5="","",H5) | L5: =IF($D5="","",IF(F5=0,"",ROUND(H5/F5*100,1))) | AR5: =IF(OR($D5="",M5="",1>$F5),0,IF(UPPER(TRIM(M5))=IFERROR(INDEX(Key!$C$2:$C$263,MATCH($D5*100+1,Key!$G$2:$G$263,0)),"#"),1,0)) | AS5: =IF(OR($D5="",N5="",2>$F5),0,IF(UPPER(TRIM(N5))=IFERROR(INDEX(Key!$C$2:$C$263,MATCH($D5*100+2,Key!$G$2:$G$263,0)),"#"),1,0)) | AT5: =IF(OR($D5="",O5="",3>$F5),0,IF(UPPER(TRIM(O5))=IFERROR(INDEX(Key!$C$2:$C$263,MATCH($D5*100+3,Key!$G$2:$G$263,0)),"#"),1,0)) | AU5: =IF(OR($D5="",P5="",4>$F5),0,IF(UPPER(TRIM(P5))=IFERROR(INDEX(Key!$C$2:$C$263,MATCH($D5*100+4,Key!$G$2:$G$263,0)),"#"),1,0)) | AV5: =IF(OR($D5="",Q5="",5>$F5),0,IF(UPPER(TRIM(Q5))=IFERROR(INDEX(Key!$C$2:$C$263,MATCH($D5*100+5,Key!$G$2:$G$263,0)),"#"),1,0)) | AW5: =IF(OR($D5="",R5="",6>$F5),0,IF(UPPER(TRIM(R5))=IFERROR(INDEX(Key!$C$2:$C$263,MATCH($D5*100+6,Key!$G$2:$G$263,0)),"#"),1,0)) | AX5: =IF(OR($D5="",S5="",7>$F5),0,IF(UPPER(TRIM(S5))=IFERROR(INDEX(Key!$C$2:$C$263,MATCH($D5*100+7,Key!$G$2:$G$263,0)),"#"),1,0)) | AY5: =IF(OR($D5="",T5="",8>$F5),0,IF(UPPER(TRIM(T5))=IFERROR(INDEX(Key!$C$2:$C$263,MATCH($D5*100+8,Key!$G$2:$G$263,0)),"#"),1,0)) | AZ5: =IF(OR($D5="",U5="",9>$F5),0,IF(UPPER(TRIM(U5))=IFERROR(INDEX(Key!$C$2:$C$263,MATCH($D5*100+9,Key!$G$2:$G$263,0)),"#"),1,0)) | BA5: =IF(OR($D5="",V5="",10>$F5),0,IF(UPPER(TRIM(V5))=IFERROR(INDEX(Key!$C$2:$C$263,MATCH($D5*100+10,Key!$G$2:$G$263,0)),"#"),1,0)) | BB5: =IF(OR($D5="",W5="",11>$F5),0,IF(UPPER(TRIM(W5))=IFERROR(INDEX(Key!$C$2:$C$263,MATCH($D5*100+11,Key!$G$2:$G$263,0)),"#"),1,0)) | BC5: =IF(OR($D5="",X5="",12>$F5),0,IF(UPPER(TRIM(X5))=IFERROR(INDEX(Key!$C$2:$C$263,MATCH($D5*100+12,Key!$G$2:$G$263,0)),"#"),1,0)) | BD5: =IF(OR($D5="",Y5="",13>$F5),0,IF(UPPER(TRIM(Y5))=IFERROR(INDEX(Key!$C$2:$C$263,MATCH($D5*100+13,Key!$G$2:$G$263,0)),"#"),1,0)) | BE5: =IF(OR($D5="",Z5="",14>$F5),0,IF(UPPER(TRIM(Z5))=IFERROR(INDEX(Key!$C$2:$C$263,MATCH($D5*100+14,Key!$G$2:$G$263,0)),"#"),1,0)) | BF5: =IF(OR($D5="",AA5="",15>$F5),0,IF(UPPER(TRIM(AA5))=IFERROR(INDEX(Key!$C$2:$C$263,MATCH($D5*100+15,Key!$G$2:$G$263,0)),"#"),1,0)) | BG5: =IF(OR($D5="",AB5="",16>$F5),0,IF(UPPER(TRIM(AB5))=IFERROR(INDEX(Key!$C$2:$C$263,MATCH($D5*100+16,Key!$G$2:$G$263,0)),"#"),1,0)) | BH5: =IF(OR($D5="",AC5="",17>$F5),0,IF(UPPER(TRIM(AC5))=IFERROR(INDEX(Key!$C$2:$C$263,MATCH($D5*100+17,Key!$G$2:$G$263,0)),"#"),1,0)) | BI5: =IF(OR($D5="",AD5="",18>$F5),0,IF(UPPER(TRIM(AD5))=IFERROR(INDEX(Key!$C$2:$C$263,MATCH($D5*100+18,Key!$G$2:$G$263,0)),"#"),1,0)) | BJ5: =IF(OR($D5="",AE5="",19>$F5),0,IF(UPPER(TRIM(AE5))=IFERROR(INDEX(Key!$C$2:$C$263,MATCH($D5*100+19,Key!$G$2:$G$263,0)),"#"),1,0)) | BK5: =IF(OR($D5="",AF5="",20>$F5),0,IF(UPPER(TRIM(AF5))=IFERROR(INDEX(Key!$C$2:$C$263,MATCH($D5*100+20,Key!$G$2:$G$263,0)),"#"),1,0)) | BL5: =IF(OR($D5="",AG5="",21>$F5),0,IF(UPPER(TRIM(AG5))=IFERROR(INDEX(Key!$C$2:$C$263,MATCH($D5*100+21,Key!$G$2:$G$263,0)),"#"),1,0)) | BM5: =IF(OR($D5="",AH5="",22>$F5),0,IF(UPPER(TRIM(AH5))=IFERROR(INDEX(Key!$C$2:$C$263,MATCH($D5*100+22,Key!$G$2:$G$263,0)),"#"),1,0)) | BN5: =IF(OR($D5="",AI5="",23>$F5),0,IF(UPPER(TRIM(AI5))=IFERROR(INDEX(Key!$C$2:$C$263,MATCH($D5*100+23,Key!$G$2:$G$263,0)),"#"),1,0)) | BO5: =IF(OR($D5="",AJ5="",24>$F5),0,IF(UPPER(TRIM(AJ5))=IFERROR(INDEX(Key!$C$2:$C$263,MATCH($D5*100+24,Key!$G$2:$G$263,0)),"#"),1,0)) | BP5: =IF(OR($D5="",AK5="",25>$F5),0,IF(UPPER(TRIM(AK5))=IFERROR(INDEX(Key!$C$2:$C$263,MATCH($D5*100+25,Key!$G$2:$G$263,0)),"#"),1,0)) | BQ5: =IF(OR($D5="",AL5="",26>$F5),0,IF(UPPER(TRIM(AL5))=IFERROR(INDEX(Key!$C$2:$C$263,MATCH($D5*100+26,Key!$G$2:$G$263,0)),"#"),1,0)) | BR5: =IF(OR($D5="",AM5="",27>$F5),0,IF(UPPER(TRIM(AM5))=IFERROR(INDEX(Key!$C$2:$C$263,MATCH($D5*100+27,Key!$G$2:$G$263,0)),"#"),1,0)) | BS5: =IF(OR($D5="",AN5="",28>$F5),0,IF(UPPER(TRIM(AN5))=IFERROR(INDEX(Key!$C$2:$C$263,MATCH($D5*100+28,Key!$G$2:$G$263,0)),"#"),1,0)) | BT5: =IF(OR($D5="",AO5="",29>$F5),0,IF(UPPER(TRIM(AO5))=IFERROR(INDEX(Key!$C$2:$C$263,MATCH($D5*100+29,Key!$G$2:$G$263,0)),"#"),1,0)) | BU5: =IF(OR($D5="",AP5="",30>$F5),0,IF(UPPER(TRIM(AP5))=IFERROR(INDEX(Key!$C$2:$C$263,MATCH($D5*100+30,Key!$G$2:$G$263,0)),"#"),1,0))
E6: =IF($D6="","",IFERROR(INDEX(Papers!$B$2:$B$12,MATCH($D6,Papers!$A$2:$A$12,0)),"?")) | F6: =IF($D6="","",IFERROR(INDEX(Papers!$C$2:$C$12,MATCH($D6,Papers!$A$2:$A$12,0)),0)) | G6: =IF($D6="","",COUNTIF(M6:AP6,"?*")) | H6: =IF($D6="","",SUM(AR6:BU6)) | I6: =IF($D6="","",G6-H6) | J6: =IF($D6="","",F6-G6) | K6: =IF($D6="","",H6) | L6: =IF($D6="","",IF(F6=0,"",ROUND(H6/F6*100,1))) | AR6: =IF(OR($D6="",M6="",1>$F6),0,IF(UPPER(TRIM(M6))=IFERROR(INDEX(Key!$C$2:$C$263,MATCH($D6*100+1,Key!$G$2:$G$263,0)),"#"),1,0)) | AS6: =IF(OR($D6="",N6="",2>$F6),0,IF(UPPER(TRIM(N6))=IFERROR(INDEX(Key!$C$2:$C$263,MATCH($D6*100+2,Key!$G$2:$G$263,0)),"#"),1,0)) | AT6: =IF(OR($D6="",O6="",3>$F6),0,IF(UPPER(TRIM(O6))=IFERROR(INDEX(Key!$C$2:$C$263,MATCH($D6*100+3,Key!$G$2:$G$263,0)),"#"),1,0)) | AU6: =IF(OR($D6="",P6="",4>$F6),0,IF(UPPER(TRIM(P6))=IFERROR(INDEX(Key!$C$2:$C$263,MATCH($D6*100+4,Key!$G$2:$G$263,0)),"#"),1,0)) | AV6: =IF(OR($D6="",Q6="",5>$F6),0,IF(UPPER(TRIM(Q6))=IFERROR(INDEX(Key!$C$2:$C$263,MATCH($D6*100+5,Key!$G$2:$G$263,0)),"#"),1,0)) | AW6: =IF(OR($D6="",R6="",6>$F6),0,IF(UPPER(TRIM(R6))=IFERROR(INDEX(Key!$C$2:$C$263,MATCH($D6*100+6,Key!$G$2:$G$263,0)),"#"),1,0)) | AX6: =IF(OR($D6="",S6="",7>$F6),0,IF(UPPER(TRIM(S6))=IFERROR(INDEX(Key!$C$2:$C$263,MATCH($D6*100+7,Key!$G$2:$G$263,0)),"#"),1,0)) | AY6: =IF(OR($D6="",T6="",8>$F6),0,IF(UPPER(TRIM(T6))=IFERROR(INDEX(Key!$C$2:$C$263,MATCH($D6*100+8,Key!$G$2:$G$263,0)),"#"),1,0)) | AZ6: =IF(OR($D6="",U6="",9>$F6),0,IF(UPPER(TRIM(U6))=IFERROR(INDEX(Key!$C$2:$C$263,MATCH($D6*100+9,Key!$G$2:$G$263,0)),"#"),1,0)) | BA6: =IF(OR($D6="",V6="",10>$F6),0,IF(UPPER(TRIM(V6))=IFERROR(INDEX(Key!$C$2:$C$263,MATCH($D6*100+10,Key!$G$2:$G$263,0)),"#"),1,0)) | BB6: =IF(OR($D6="",W6="",11>$F6),0,IF(UPPER(TRIM(W6))=IFERROR(INDEX(Key!$C$2:$C$263,MATCH($D6*100+11,Key!$G$2:$G$263,0)),"#"),1,0)) | BC6: =IF(OR($D6="",X6="",12>$F6),0,IF(UPPER(TRIM(X6))=IFERROR(INDEX(Key!$C$2:$C$263,MATCH($D6*100+12,Key!$G$2:$G$263,0)),"#"),1,0)) | BD6: =IF(OR($D6="",Y6="",13>$F6),0,IF(UPPER(TRIM(Y6))=IFERROR(INDEX(Key!$C$2:$C$263,MATCH($D6*100+13,Key!$G$2:$G$263,0)),"#"),1,0)) | BE6: =IF(OR($D6="",Z6="",14>$F6),0,IF(UPPER(TRIM(Z6))=IFERROR(INDEX(Key!$C$2:$C$263,MATCH($D6*100+14,Key!$G$2:$G$263,0)),"#"),1,0)) | BF6: =IF(OR($D6="",AA6="",15>$F6),0,IF(UPPER(TRIM(AA6))=IFERROR(INDEX(Key!$C$2:$C$263,MATCH($D6*100+15,Key!$G$2:$G$263,0)),"#"),1,0)) | BG6: =IF(OR($D6="",AB6="",16>$F6),0,IF(UPPER(TRIM(AB6))=IFERROR(INDEX(Key!$C$2:$C$263,MATCH($D6*100+16,Key!$G$2:$G$263,0)),"#"),1,0)) | BH6: =IF(OR($D6="",AC6="",17>$F6),0,IF(UPPER(TRIM(AC6))=IFERROR(INDEX(Key!$C$2:$C$263,MATCH($D6*100+17,Key!$G$2:$G$263,0)),"#"),1,0)) | BI6: =IF(OR($D6="",AD6="",18>$F6),0,IF(UPPER(TRIM(AD6))=IFERROR(INDEX(Key!$C$2:$C$263,MATCH($D6*100+18,Key!$G$2:$G$263,0)),"#"),1,0)) | BJ6: =IF(OR($D6="",AE6="",19>$F6),0,IF(UPPER(TRIM(AE6))=IFERROR(INDEX(Key!$C$2:$C$263,MATCH($D6*100+19,Key!$G$2:$G$263,0)),"#"),1,0)) | BK6: =IF(OR($D6="",AF6="",20>$F6),0,IF(UPPER(TRIM(AF6))=IFERROR(INDEX(Key!$C$2:$C$263,MATCH($D6*100+20,Key!$G$2:$G$263,0)),"#"),1,0)) | BL6: =IF(OR($D6="",AG6="",21>$F6),0,IF(UPPER(TRIM(AG6))=IFERROR(INDEX(Key!$C$2:$C$263,MATCH($D6*100+21,Key!$G$2:$G$263,0)),"#"),1,0)) | BM6: =IF(OR($D6="",AH6="",22>$F6),0,IF(UPPER(TRIM(AH6))=IFERROR(INDEX(Key!$C$2:$C$263,MATCH($D6*100+22,Key!$G$2:$G$263,0)),"#"),1,0)) | BN6: =IF(OR($D6="",AI6="",23>$F6),0,IF(UPPER(TRIM(AI6))=IFERROR(INDEX(Key!$C$2:$C$263,MATCH($D6*100+23,Key!$G$2:$G$263,0)),"#"),1,0)) | BO6: =IF(OR($D6="",AJ6="",24>$F6),0,IF(UPPER(TRIM(AJ6))=IFERROR(INDEX(Key!$C$2:$C$263,MATCH($D6*100+24,Key!$G$2:$G$263,0)),"#"),1,0)) | BP6: =IF(OR($D6="",AK6="",25>$F6),0,IF(UPPER(TRIM(AK6))=IFERROR(INDEX(Key!$C$2:$C$263,MATCH($D6*100+25,Key!$G$2:$G$263,0)),"#"),1,0)) | BQ6: =IF(OR($D6="",AL6="",26>$F6),0,IF(UPPER(TRIM(AL6))=IFERROR(INDEX(Key!$C$2:$C$263,MATCH($D6*100+26,Key!$G$2:$G$263,0)),"#"),1,0)) | BR6: =IF(OR($D6="",AM6="",27>$F6),0,IF(UPPER(TRIM(AM6))=IFERROR(INDEX(Key!$C$2:$C$263,MATCH($D6*100+27,Key!$G$2:$G$263,0)),"#"),1,0)) | BS6: =IF(OR($D6="",AN6="",28>$F6),0,IF(UPPER(TRIM(AN6))=IFERROR(INDEX(Key!$C$2:$C$263,MATCH($D6*100+28,Key!$G$2:$G$263,0)),"#"),1,0)) | BT6: =IF(OR($D6="",AO6="",29>$F6),0,IF(UPPER(TRIM(AO6))=IFERROR(INDEX(Key!$C$2:$C$263,MATCH($D6*100+29,Key!$G$2:$G$263,0)),"#"),1,0)) | BU6: =IF(OR($D6="",AP6="",30>$F6),0,IF(UPPER(TRIM(AP6))=IFERROR(INDEX(Key!$C$2:$C$263,MATCH($D6*100+30,Key!$G$2:$G$263,0)),"#"),1,0))
E7: =IF($D7="","",IFERROR(INDEX(Papers!$B$2:$B$12,MATCH($D7,Papers!$A$2:$A$12,0)),"?")) | F7: =IF($D7="","",IFERROR(INDEX(Papers!$C$2:$C$12,MATCH($D7,Papers!$A$2:$A$12,0)),0)) | G7: =IF($D7="","",COUNTIF(M7:AP7,"?*")) | H7: =IF($D7="","",SUM(AR7:BU7)) | I7: =IF($D7="","",G7-H7) | J7: =IF($D7="","",F7-G7) | K7: =IF($D7="","",H7) | L7: =IF($D7="","",IF(F7=0,"",ROUND(H7/F7*100,1))) | AR7: =IF(OR($D7="",M7="",1>$F7),0,IF(UPPER(TRIM(M7))=IFERROR(INDEX(Key!$C$2:$C$263,MATCH($D7*100+1,Key!$G$2:$G$263,0)),"#"),1,0)) | AS7: =IF(OR($D7="",N7="",2>$F7),0,IF(UPPER(TRIM(N7))=IFERROR(INDEX(Key!$C$2:$C$263,MATCH($D7*100+2,Key!$G$2:$G$263,0)),"#"),1,0)) | AT7: =IF(OR($D7="",O7="",3>$F7),0,IF(UPPER(TRIM(O7))=IFERROR(INDEX(Key!$C$2:$C$263,MATCH($D7*100+3,Key!$G$2:$G$263,0)),"#"),1,0)) | AU7: =IF(OR($D7="",P7="",4>$F7),0,IF(UPPER(TRIM(P7))=IFERROR(INDEX(Key!$C$2:$C$263,MATCH($D7*100+4,Key!$G$2:$G$263,0)),"#"),1,0)) | AV7: =IF(OR($D7="",Q7="",5>$F7),0,IF(UPPER(TRIM(Q7))=IFERROR(INDEX(Key!$C$2:$C$263,MATCH($D7*100+5,Key!$G$2:$G$263,0)),"#"),1,0)) | AW7: =IF(OR($D7="",R7="",6>$F7),0,IF(UPPER(TRIM(R7))=IFERROR(INDEX(Key!$C$2:$C$263,MATCH($D7*100+6,Key!$G$2:$G$263,0)),"#"),1,0)) | AX7: =IF(OR($D7="",S7="",7>$F7),0,IF(UPPER(TRIM(S7))=IFERROR(INDEX(Key!$C$2:$C$263,MATCH($D7*100+7,Key!$G$2:$G$263,0)),"#"),1,0)) | AY7: =IF(OR($D7="",T7="",8>$F7),0,IF(UPPER(TRIM(T7))=IFERROR(INDEX(Key!$C$2:$C$263,MATCH($D7*100+8,Key!$G$2:$G$263,0)),"#"),1,0)) | AZ7: =IF(OR($D7="",U7="",9>$F7),0,IF(UPPER(TRIM(U7))=IFERROR(INDEX(Key!$C$2:$C$263,MATCH($D7*100+9,Key!$G$2:$G$263,0)),"#"),1,0)) | BA7: =IF(OR($D7="",V7="",10>$F7),0,IF(UPPER(TRIM(V7))=IFERROR(INDEX(Key!$C$2:$C$263,MATCH($D7*100+10,Key!$G$2:$G$263,0)),"#"),1,0)) | BB7: =IF(OR($D7="",W7="",11>$F7),0,IF(UPPER(TRIM(W7))=IFERROR(INDEX(Key!$C$2:$C$263,MATCH($D7*100+11,Key!$G$2:$G$263,0)),"#"),1,0)) | BC7: =IF(OR($D7="",X7="",12>$F7),0,IF(UPPER(TRIM(X7))=IFERROR(INDEX(Key!$C$2:$C$263,MATCH($D7*100+12,Key!$G$2:$G$263,0)),"#"),1,0)) | BD7: =IF(OR($D7="",Y7="",13>$F7),0,IF(UPPER(TRIM(Y7))=IFERROR(INDEX(Key!$C$2:$C$263,MATCH($D7*100+13,Key!$G$2:$G$263,0)),"#"),1,0)) | BE7: =IF(OR($D7="",Z7="",14>$F7),0,IF(UPPER(TRIM(Z7))=IFERROR(INDEX(Key!$C$2:$C$263,MATCH($D7*100+14,Key!$G$2:$G$263,0)),"#"),1,0)) | BF7: =IF(OR($D7="",AA7="",15>$F7),0,IF(UPPER(TRIM(AA7))=IFERROR(INDEX(Key!$C$2:$C$263,MATCH($D7*100+15,Key!$G$2:$G$263,0)),"#"),1,0)) | BG7: =IF(OR($D7="",AB7="",16>$F7),0,IF(UPPER(TRIM(AB7))=IFERROR(INDEX(Key!$C$2:$C$263,MATCH($D7*100+16,Key!$G$2:$G$263,0)),"#"),1,0)) | BH7: =IF(OR($D7="",AC7="",17>$F7),0,IF(UPPER(TRIM(AC7))=IFERROR(INDEX(Key!$C$2:$C$263,MATCH($D7*100+17,Key!$G$2:$G$263,0)),"#"),1,0)) | BI7: =IF(OR($D7="",AD7="",18>$F7),0,IF(UPPER(TRIM(AD7))=IFERROR(INDEX(Key!$C$2:$C$263,MATCH($D7*100+18,Key!$G$2:$G$263,0)),"#"),1,0)) | BJ7: =IF(OR($D7="",AE7="",19>$F7),0,IF(UPPER(TRIM(AE7))=IFERROR(INDEX(Key!$C$2:$C$263,MATCH($D7*100+19,Key!$G$2:$G$263,0)),"#"),1,0)) | BK7: =IF(OR($D7="",AF7="",20>$F7),0,IF(UPPER(TRIM(AF7))=IFERROR(INDEX(Key!$C$2:$C$263,MATCH($D7*100+20,Key!$G$2:$G$263,0)),"#"),1,0)) | BL7: =IF(OR($D7="",AG7="",21>$F7),0,IF(UPPER(TRIM(AG7))=IFERROR(INDEX(Key!$C$2:$C$263,MATCH($D7*100+21,Key!$G$2:$G$263,0)),"#"),1,0)) | BM7: =IF(OR($D7="",AH7="",22>$F7),0,IF(UPPER(TRIM(AH7))=IFERROR(INDEX(Key!$C$2:$C$263,MATCH($D7*100+22,Key!$G$2:$G$263,0)),"#"),1,0)) | BN7: =IF(OR($D7="",AI7="",23>$F7),0,IF(UPPER(TRIM(AI7))=IFERROR(INDEX(Key!$C$2:$C$263,MATCH($D7*100+23,Key!$G$2:$G$263,0)),"#"),1,0)) | BO7: =IF(OR($D7="",AJ7="",24>$F7),0,IF(UPPER(TRIM(AJ7))=IFERROR(INDEX(Key!$C$2:$C$263,MATCH($D7*100+24,Key!$G$2:$G$263,0)),"#"),1,0)) | BP7: =IF(OR($D7="",AK7="",25>$F7),0,IF(UPPER(TRIM(AK7))=IFERROR(INDEX(Key!$C$2:$C$263,MATCH($D7*100+25,Key!$G$2:$G$263,0)),"#"),1,0)) | BQ7: =IF(OR($D7="",AL7="",26>$F7),0,IF(UPPER(TRIM(AL7))=IFERROR(INDEX(Key!$C$2:$C$263,MATCH($D7*100+26,Key!$G$2:$G$263,0)),"#"),1,0)) | BR7: =IF(OR($D7="",AM7="",27>$F7),0,IF(UPPER(TRIM(AM7))=IFERROR(INDEX(Key!$C$2:$C$263,MATCH($D7*100+27,Key!$G$2:$G$263,0)),"#"),1,0)) | BS7: =IF(OR($D7="",AN7="",28>$F7),0,IF(UPPER(TRIM(AN7))=IFERROR(INDEX(Key!$C$2:$C$263,MATCH($D7*100+28,Key!$G$2:$G$263,0)),"#"),1,0)) | BT7: =IF(OR($D7="",AO7="",29>$F7),0,IF(UPPER(TRIM(AO7))=IFERROR(INDEX(Key!$C$2:$C$263,MATCH($D7*100+29,Key!$G$2:$G$263,0)),"#"),1,0)) | BU7: =IF(OR($D7="",AP7="",30>$F7),0,IF(UPPER(TRIM(AP7))=IFERROR(INDEX(Key!$C$2:$C$263,MATCH($D7*100+30,Key!$G$2:$G$263,0)),"#"),1,0))
E8: =IF($D8="","",IFERROR(INDEX(Papers!$B$2:$B$12,MATCH($D8,Papers!$A$2:$A$12,0)),"?")) | F8: =IF($D8="","",IFERROR(INDEX(Papers!$C$2:$C$12,MATCH($D8,Papers!$A$2:$A$12,0)),0)) | G8: =IF($D8="","",COUNTIF(M8:AP8,"?*")) | H8: =IF($D8="","",SUM(AR8:BU8)) | I8: =IF($D8="","",G8-H8) | J8: =IF($D8="","",F8-G8) | K8: =IF($D8="","",H8) | L8: =IF($D8="","",IF(F8=0,"",ROUND(H8/F8*100,1))) | AR8: =IF(OR($D8="",M8="",1>$F8),0,IF(UPPER(TRIM(M8))=IFERROR(INDEX(Key!$C$2:$C$263,MATCH($D8*100+1,Key!$G$2:$G$263,0)),"#"),1,0)) | AS8: =IF(OR($D8="",N8="",2>$F8),0,IF(UPPER(TRIM(N8))=IFERROR(INDEX(Key!$C$2:$C$263,MATCH($D8*100+2,Key!$G$2:$G$263,0)),"#"),1,0)) | AT8: =IF(OR($D8="",O8="",3>$F8),0,IF(UPPER(TRIM(O8))=IFERROR(INDEX(Key!$C$2:$C$263,MATCH($D8*100+3,Key!$G$2:$G$263,0)),"#"),1,0)) | AU8: =IF(OR($D8="",P8="",4>$F8),0,IF(UPPER(TRIM(P8))=IFERROR(INDEX(Key!$C$2:$C$263,MATCH($D8*100+4,Key!$G$2:$G$263,0)),"#"),1,0)) | AV8: =IF(OR($D8="",Q8="",5>$F8),0,IF(UPPER(TRIM(Q8))=IFERROR(INDEX(Key!$C$2:$C$263,MATCH($D8*100+5,Key!$G$2:$G$263,0)),"#"),1,0)) | AW8: =IF(OR($D8="",R8="",6>$F8),0,IF(UPPER(TRIM(R8))=IFERROR(INDEX(Key!$C$2:$C$263,MATCH($D8*100+6,Key!$G$2:$G$263,0)),"#"),1,0)) | AX8: =IF(OR($D8="",S8="",7>$F8),0,IF(UPPER(TRIM(S8))=IFERROR(INDEX(Key!$C$2:$C$263,MATCH($D8*100+7,Key!$G$2:$G$263,0)),"#"),1,0)) | AY8: =IF(OR($D8="",T8="",8>$F8),0,IF(UPPER(TRIM(T8))=IFERROR(INDEX(Key!$C$2:$C$263,MATCH($D8*100+8,Key!$G$2:$G$263,0)),"#"),1,0)) | AZ8: =IF(OR($D8="",U8="",9>$F8),0,IF(UPPER(TRIM(U8))=IFERROR(INDEX(Key!$C$2:$C$263,MATCH($D8*100+9,Key!$G$2:$G$263,0)),"#"),1,0)) | BA8: =IF(OR($D8="",V8="",10>$F8),0,IF(UPPER(TRIM(V8))=IFERROR(INDEX(Key!$C$2:$C$263,MATCH($D8*100+10,Key!$G$2:$G$263,0)),"#"),1,0)) | BB8: =IF(OR($D8="",W8="",11>$F8),0,IF(UPPER(TRIM(W8))=IFERROR(INDEX(Key!$C$2:$C$263,MATCH($D8*100+11,Key!$G$2:$G$263,0)),"#"),1,0)) | BC8: =IF(OR($D8="",X8="",12>$F8),0,IF(UPPER(TRIM(X8))=IFERROR(INDEX(Key!$C$2:$C$263,MATCH($D8*100+12,Key!$G$2:$G$263,0)),"#"),1,0)) | BD8: =IF(OR($D8="",Y8="",13>$F8),0,IF(UPPER(TRIM(Y8))=IFERROR(INDEX(Key!$C$2:$C$263,MATCH($D8*100+13,Key!$G$2:$G$263,0)),"#"),1,0)) | BE8: =IF(OR($D8="",Z8="",14>$F8),0,IF(UPPER(TRIM(Z8))=IFERROR(INDEX(Key!$C$2:$C$263,MATCH($D8*100+14,Key!$G$2:$G$263,0)),"#"),1,0)) | BF8: =IF(OR($D8="",AA8="",15>$F8),0,IF(UPPER(TRIM(AA8))=IFERROR(INDEX(Key!$C$2:$C$263,MATCH($D8*100+15,Key!$G$2:$G$263,0)),"#"),1,0)) | BG8: =IF(OR($D8="",AB8="",16>$F8),0,IF(UPPER(TRIM(AB8))=IFERROR(INDEX(Key!$C$2:$C$263,MATCH($D8*100+16,Key!$G$2:$G$263,0)),"#"),1,0)) | BH8: =IF(OR($D8="",AC8="",17>$F8),0,IF(UPPER(TRIM(AC8))=IFERROR(INDEX(Key!$C$2:$C$263,MATCH($D8*100+17,Key!$G$2:$G$263,0)),"#"),1,0)) | BI8: =IF(OR($D8="",AD8="",18>$F8),0,IF(UPPER(TRIM(AD8))=IFERROR(INDEX(Key!$C$2:$C$263,MATCH($D8*100+18,Key!$G$2:$G$263,0)),"#"),1,0)) | BJ8: =IF(OR($D8="",AE8="",19>$F8),0,IF(UPPER(TRIM(AE8))=IFERROR(INDEX(Key!$C$2:$C$263,MATCH($D8*100+19,Key!$G$2:$G$263,0)),"#"),1,0)) | BK8: =IF(OR($D8="",AF8="",20>$F8),0,IF(UPPER(TRIM(AF8))=IFERROR(INDEX(Key!$C$2:$C$263,MATCH($D8*100+20,Key!$G$2:$G$263,0)),"#"),1,0)) | BL8: =IF(OR($D8="",AG8="",21>$F8),0,IF(UPPER(TRIM(AG8))=IFERROR(INDEX(Key!$C$2:$C$263,MATCH($D8*100+21,Key!$G$2:$G$263,0)),"#"),1,0)) | BM8: =IF(OR($D8="",AH8="",22>$F8),0,IF(UPPER(TRIM(AH8))=IFERROR(INDEX(Key!$C$2:$C$263,MATCH($D8*100+22,Key!$G$2:$G$263,0)),"#"),1,0)) | BN8: =IF(OR($D8="",AI8="",23>$F8),0,IF(UPPER(TRIM(AI8))=IFERROR(INDEX(Key!$C$2:$C$263,MATCH($D8*100+23,Key!$G$2:$G$263,0)),"#"),1,0)) | BO8: =IF(OR($D8="",AJ8="",24>$F8),0,IF(UPPER(TRIM(AJ8))=IFERROR(INDEX(Key!$C$2:$C$263,MATCH($D8*100+24,Key!$G$2:$G$263,0)),"#"),1,0)) | BP8: =IF(OR($D8="",AK8="",25>$F8),0,IF(UPPER(TRIM(AK8))=IFERROR(INDEX(Key!$C$2:$C$263,MATCH($D8*100+25,Key!$G$2:$G$263,0)),"#"),1,0)) | BQ8: =IF(OR($D8="",AL8="",26>$F8),0,IF(UPPER(TRIM(AL8))=IFERROR(INDEX(Key!$C$2:$C$263,MATCH($D8*100+26,Key!$G$2:$G$263,0)),"#"),1,0)) | BR8: =IF(OR($D8="",AM8="",27>$F8),0,IF(UPPER(TRIM(AM8))=IFERROR(INDEX(Key!$C$2:$C$263,MATCH($D8*100+27,Key!$G$2:$G$263,0)),"#"),1,0)) | BS8: =IF(OR($D8="",AN8="",28>$F8),0,IF(UPPER(TRIM(AN8))=IFERROR(INDEX(Key!$C$2:$C$263,MATCH($D8*100+28,Key!$G$2:$G$263,0)),"#"),1,0)) | BT8: =IF(OR($D8="",AO8="",29>$F8),0,IF(UPPER(TRIM(AO8))=IFERROR(INDEX(Key!$C$2:$C$263,MATCH($D8*100+29,Key!$G$2:$G$263,0)),"#"),1,0)) | BU8: =IF(OR($D8="",AP8="",30>$F8),0,IF(UPPER(TRIM(AP8))=IFERROR(INDEX(Key!$C$2:$C$263,MATCH($D8*100+30,Key!$G$2:$G$263,0)),"#"),1,0))
E9: =IF($D9="","",IFERROR(INDEX(Papers!$B$2:$B$12,MATCH($D9,Papers!$A$2:$A$12,0)),"?")) | F9: =IF($D9="","",IFERROR(INDEX(Papers!$C$2:$C$12,MATCH($D9,Papers!$A$2:$A$12,0)),0)) | G9: =IF($D9="","",COUNTIF(M9:AP9,"?*")) | H9: =IF($D9="","",SUM(AR9:BU9)) | I9: =IF($D9="","",G9-H9) | J9: =IF($D9="","",F9-G9) | K9: =IF($D9="","",H9) | L9: =IF($D9="","",IF(F9=0,"",ROUND(H9/F9*100,1))) | AR9: =IF(OR($D9="",M9="",1>$F9),0,IF(UPPER(TRIM(M9))=IFERROR(INDEX(Key!$C$2:$C$263,MATCH($D9*100+1,Key!$G$2:$G$263,0)),"#"),1,0)) | AS9: =IF(OR($D9="",N9="",2>$F9),0,IF(UPPER(TRIM(N9))=IFERROR(INDEX(Key!$C$2:$C$263,MATCH($D9*100+2,Key!$G$2:$G$263,0)),"#"),1,0)) | AT9: =IF(OR($D9="",O9="",3>$F9),0,IF(UPPER(TRIM(O9))=IFERROR(INDEX(Key!$C$2:$C$263,MATCH($D9*100+3,Key!$G$2:$G$263,0)),"#"),1,0)) | AU9: =IF(OR($D9="",P9="",4>$F9),0,IF(UPPER(TRIM(P9))=IFERROR(INDEX(Key!$C$2:$C$263,MATCH($D9*100+4,Key!$G$2:$G$263,0)),"#"),1,0)) | AV9: =IF(OR($D9="",Q9="",5>$F9),0,IF(UPPER(TRIM(Q9))=IFERROR(INDEX(Key!$C$2:$C$263,MATCH($D9*100+5,Key!$G$2:$G$263,0)),"#"),1,0)) | AW9: =IF(OR($D9="",R9="",6>$F9),0,IF(UPPER(TRIM(R9))=IFERROR(INDEX(Key!$C$2:$C$263,MATCH($D9*100+6,Key!$G$2:$G$263,0)),"#"),1,0)) | AX9: =IF(OR($D9="",S9="",7>$F9),0,IF(UPPER(TRIM(S9))=IFERROR(INDEX(Key!$C$2:$C$263,MATCH($D9*100+7,Key!$G$2:$G$263,0)),"#"),1,0)) | AY9: =IF(OR($D9="",T9="",8>$F9),0,IF(UPPER(TRIM(T9))=IFERROR(INDEX(Key!$C$2:$C$263,MATCH($D9*100+8,Key!$G$2:$G$263,0)),"#"),1,0)) | AZ9: =IF(OR($D9="",U9="",9>$F9),0,IF(UPPER(TRIM(U9))=IFERROR(INDEX(Key!$C$2:$C$263,MATCH($D9*100+9,Key!$G$2:$G$263,0)),"#"),1,0)) | BA9: =IF(OR($D9="",V9="",10>$F9),0,IF(UPPER(TRIM(V9))=IFERROR(INDEX(Key!$C$2:$C$263,MATCH($D9*100+10,Key!$G$2:$G$263,0)),"#"),1,0)) | BB9: =IF(OR($D9="",W9="",11>$F9),0,IF(UPPER(TRIM(W9))=IFERROR(INDEX(Key!$C$2:$C$263,MATCH($D9*100+11,Key!$G$2:$G$263,0)),"#"),1,0)) | BC9: =IF(OR($D9="",X9="",12>$F9),0,IF(UPPER(TRIM(X9))=IFERROR(INDEX(Key!$C$2:$C$263,MATCH($D9*100+12,Key!$G$2:$G$263,0)),"#"),1,0)) | BD9: =IF(OR($D9="",Y9="",13>$F9),0,IF(UPPER(TRIM(Y9))=IFERROR(INDEX(Key!$C$2:$C$263,MATCH($D9*100+13,Key!$G$2:$G$263,0)),"#"),1,0)) | BE9: =IF(OR($D9="",Z9="",14>$F9),0,IF(UPPER(TRIM(Z9))=IFERROR(INDEX(Key!$C$2:$C$263,MATCH($D9*100+14,Key!$G$2:$G$263,0)),"#"),1,0)) | BF9: =IF(OR($D9="",AA9="",15>$F9),0,IF(UPPER(TRIM(AA9))=IFERROR(INDEX(Key!$C$2:$C$263,MATCH($D9*100+15,Key!$G$2:$G$263,0)),"#"),1,0)) | BG9: =IF(OR($D9="",AB9="",16>$F9),0,IF(UPPER(TRIM(AB9))=IFERROR(INDEX(Key!$C$2:$C$263,MATCH($D9*100+16,Key!$G$2:$G$263,0)),"#"),1,0)) | BH9: =IF(OR($D9="",AC9="",17>$F9),0,IF(UPPER(TRIM(AC9))=IFERROR(INDEX(Key!$C$2:$C$263,MATCH($D9*100+17,Key!$G$2:$G$263,0)),"#"),1,0)) | BI9: =IF(OR($D9="",AD9="",18>$F9),0,IF(UPPER(TRIM(AD9))=IFERROR(INDEX(Key!$C$2:$C$263,MATCH($D9*100+18,Key!$G$2:$G$263,0)),"#"),1,0)) | BJ9: =IF(OR($D9="",AE9="",19>$F9),0,IF(UPPER(TRIM(AE9))=IFERROR(INDEX(Key!$C$2:$C$263,MATCH($D9*100+19,Key!$G$2:$G$263,0)),"#"),1,0)) | BK9: =IF(OR($D9="",AF9="",20>$F9),0,IF(UPPER(TRIM(AF9))=IFERROR(INDEX(Key!$C$2:$C$263,MATCH($D9*100+20,Key!$G$2:$G$263,0)),"#"),1,0)) | BL9: =IF(OR($D9="",AG9="",21>$F9),0,IF(UPPER(TRIM(AG9))=IFERROR(INDEX(Key!$C$2:$C$263,MATCH($D9*100+21,Key!$G$2:$G$263,0)),"#"),1,0)) | BM9: =IF(OR($D9="",AH9="",22>$F9),0,IF(UPPER(TRIM(AH9))=IFERROR(INDEX(Key!$C$2:$C$263,MATCH($D9*100+22,Key!$G$2:$G$263,0)),"#"),1,0)) | BN9: =IF(OR($D9="",AI9="",23>$F9),0,IF(UPPER(TRIM(AI9))=IFERROR(INDEX(Key!$C$2:$C$263,MATCH($D9*100+23,Key!$G$2:$G$263,0)),"#"),1,0)) | BO9: =IF(OR($D9="",AJ9="",24>$F9),0,IF(UPPER(TRIM(AJ9))=IFERROR(INDEX(Key!$C$2:$C$263,MATCH($D9*100+24,Key!$G$2:$G$263,0)),"#"),1,0)) | BP9: =IF(OR($D9="",AK9="",25>$F9),0,IF(UPPER(TRIM(AK9))=IFERROR(INDEX(Key!$C$2:$C$263,MATCH($D9*100+25,Key!$G$2:$G$263,0)),"#"),1,0)) | BQ9: =IF(OR($D9="",AL9="",26>$F9),0,IF(UPPER(TRIM(AL9))=IFERROR(INDEX(Key!$C$2:$C$263,MATCH($D9*100+26,Key!$G$2:$G$263,0)),"#"),1,0)) | BR9: =IF(OR($D9="",AM9="",27>$F9),0,IF(UPPER(TRIM(AM9))=IFERROR(INDEX(Key!$C$2:$C$263,MATCH($D9*100+27,Key!$G$2:$G$263,0)),"#"),1,0)) | BS9: =IF(OR($D9="",AN9="",28>$F9),0,IF(UPPER(TRIM(AN9))=IFERROR(INDEX(Key!$C$2:$C$263,MATCH($D9*100+28,Key!$G$2:$G$263,0)),"#"),1,0)) | BT9: =IF(OR($D9="",AO9="",29>$F9),0,IF(UPPER(TRIM(AO9))=IFERROR(INDEX(Key!$C$2:$C$263,MATCH($D9*100+29,Key!$G$2:$G$263,0)),"#"),1,0)) | BU9: =IF(OR($D9="",AP9="",30>$F9),0,IF(UPPER(TRIM(AP9))=IFERROR(INDEX(Key!$C$2:$C$263,MATCH($D9*100+30,Key!$G$2:$G$263,0)),"#"),1,0))
E10: =IF($D10="","",IFERROR(INDEX(Papers!$B$2:$B$12,MATCH($D10,Papers!$A$2:$A$12,0)),"?")) | F10: =IF($D10="","",IFERROR(INDEX(Papers!$C$2:$C$12,MATCH($D10,Papers!$A$2:$A$12,0)),0)) | G10: =IF($D10="","",COUNTIF(M10:AP10,"?*")) | H10: =IF($D10="","",SUM(AR10:BU10)) | I10: =IF($D10="","",G10-H10) | J10: =IF($D10="","",F10-G10) | K10: =IF($D10="","",H10) | L10: =IF($D10="","",IF(F10=0,"",ROUND(H10/F10*100,1))) | AR10: =IF(OR($D10="",M10="",1>$F10),0,IF(UPPER(TRIM(M10))=IFERROR(INDEX(Key!$C$2:$C$263,MATCH($D10*100+1,Key!$G$2:$G$263,0)),"#"),1,0)) | AS10: =IF(OR($D10="",N10="",2>$F10),0,IF(UPPER(TRIM(N10))=IFERROR(INDEX(Key!$C$2:$C$263,MATCH($D10*100+2,Key!$G$2:$G$263,0)),"#"),1,0)) | AT10: =IF(OR($D10="",O10="",3>$F10),0,IF(UPPER(TRIM(O10))=IFERROR(INDEX(Key!$C$2:$C$263,MATCH($D10*100+3,Key!$G$2:$G$263,0)),"#"),1,0)) | AU10: =IF(OR($D10="",P10="",4>$F10),0,IF(UPPER(TRIM(P10))=IFERROR(INDEX(Key!$C$2:$C$263,MATCH($D10*100+4,Key!$G$2:$G$263,0)),"#"),1,0)) | AV10: =IF(OR($D10="",Q10="",5>$F10),0,IF(UPPER(TRIM(Q10))=IFERROR(INDEX(Key!$C$2:$C$263,MATCH($D10*100+5,Key!$G$2:$G$263,0)),"#"),1,0)) | AW10: =IF(OR($D10="",R10="",6>$F10),0,IF(UPPER(TRIM(R10))=IFERROR(INDEX(Key!$C$2:$C$263,MATCH($D10*100+6,Key!$G$2:$G$263,0)),"#"),1,0)) | AX10: =IF(OR($D10="",S10="",7>$F10),0,IF(UPPER(TRIM(S10))=IFERROR(INDEX(Key!$C$2:$C$263,MATCH($D10*100+7,Key!$G$2:$G$263,0)),"#"),1,0)) | AY10: =IF(OR($D10="",T10="",8>$F10),0,IF(UPPER(TRIM(T10))=IFERROR(INDEX(Key!$C$2:$C$263,MATCH($D10*100+8,Key!$G$2:$G$263,0)),"#"),1,0)) | AZ10: =IF(OR($D10="",U10="",9>$F10),0,IF(UPPER(TRIM(U10))=IFERROR(INDEX(Key!$C$2:$C$263,MATCH($D10*100+9,Key!$G$2:$G$263,0)),"#"),1,0)) | BA10: =IF(OR($D10="",V10="",10>$F10),0,IF(UPPER(TRIM(V10))=IFERROR(INDEX(Key!$C$2:$C$263,MATCH($D10*100+10,Key!$G$2:$G$263,0)),"#"),1,0)) | BB10: =IF(OR($D10="",W10="",11>$F10),0,IF(UPPER(TRIM(W10))=IFERROR(INDEX(Key!$C$2:$C$263,MATCH($D10*100+11,Key!$G$2:$G$263,0)),"#"),1,0)) | BC10: =IF(OR($D10="",X10="",12>$F10),0,IF(UPPER(TRIM(X10))=IFERROR(INDEX(Key!$C$2:$C$263,MATCH($D10*100+12,Key!$G$2:$G$263,0)),"#"),1,0)) | BD10: =IF(OR($D10="",Y10="",13>$F10),0,IF(UPPER(TRIM(Y10))=IFERROR(INDEX(Key!$C$2:$C$263,MATCH($D10*100+13,Key!$G$2:$G$263,0)),"#"),1,0)) | BE10: =IF(OR($D10="",Z10="",14>$F10),0,IF(UPPER(TRIM(Z10))=IFERROR(INDEX(Key!$C$2:$C$263,MATCH($D10*100+14,Key!$G$2:$G$263,0)),"#"),1,0)) | BF10: =IF(OR($D10="",AA10="",15>$F10),0,IF(UPPER(TRIM(AA10))=IFERROR(INDEX(Key!$C$2:$C$263,MATCH($D10*100+15,Key!$G$2:$G$263,0)),"#"),1,0)) | BG10: =IF(OR($D10="",AB10="",16>$F10),0,IF(UPPER(TRIM(AB10))=IFERROR(INDEX(Key!$C$2:$C$263,MATCH($D10*100+16,Key!$G$2:$G$263,0)),"#"),1,0)) | BH10: =IF(OR($D10="",AC10="",17>$F10),0,IF(UPPER(TRIM(AC10))=IFERROR(INDEX(Key!$C$2:$C$263,MATCH($D10*100+17,Key!$G$2:$G$263,0)),"#"),1,0)) | BI10: =IF(OR($D10="",AD10="",18>$F10),0,IF(UPPER(TRIM(AD10))=IFERROR(INDEX(Key!$C$2:$C$263,MATCH($D10*100+18,Key!$G$2:$G$263,0)),"#"),1,0)) | BJ10: =IF(OR($D10="",AE10="",19>$F10),0,IF(UPPER(TRIM(AE10))=IFERROR(INDEX(Key!$C$2:$C$263,MATCH($D10*100+19,Key!$G$2:$G$263,0)),"#"),1,0)) | BK10: =IF(OR($D10="",AF10="",20>$F10),0,IF(UPPER(TRIM(AF10))=IFERROR(INDEX(Key!$C$2:$C$263,MATCH($D10*100+20,Key!$G$2:$G$263,0)),"#"),1,0)) | BL10: =IF(OR($D10="",AG10="",21>$F10),0,IF(UPPER(TRIM(AG10))=IFERROR(INDEX(Key!$C$2:$C$263,MATCH($D10*100+21,Key!$G$2:$G$263,0)),"#"),1,0)) | BM10: =IF(OR($D10="",AH10="",22>$F10),0,IF(UPPER(TRIM(AH10))=IFERROR(INDEX(Key!$C$2:$C$263,MATCH($D10*100+22,Key!$G$2:$G$263,0)),"#"),1,0)) | BN10: =IF(OR($D10="",AI10="",23>$F10),0,IF(UPPER(TRIM(AI10))=IFERROR(INDEX(Key!$C$2:$C$263,MATCH($D10*100+23,Key!$G$2:$G$263,0)),"#"),1,0)) | BO10: =IF(OR($D10="",AJ10="",24>$F10),0,IF(UPPER(TRIM(AJ10))=IFERROR(INDEX(Key!$C$2:$C$263,MATCH($D10*100+24,Key!$G$2:$G$263,0)),"#"),1,0)) | BP10: =IF(OR($D10="",AK10="",25>$F10),0,IF(UPPER(TRIM(AK10))=IFERROR(INDEX(Key!$C$2:$C$263,MATCH($D10*100+25,Key!$G$2:$G$263,0)),"#"),1,0)) | BQ10: =IF(OR($D10="",AL10="",26>$F10),0,IF(UPPER(TRIM(AL10))=IFERROR(INDEX(Key!$C$2:$C$263,MATCH($D10*100+26,Key!$G$2:$G$263,0)),"#"),1,0)) | BR10: =IF(OR($D10="",AM10="",27>$F10),0,IF(UPPER(TRIM(AM10))=IFERROR(INDEX(Key!$C$2:$C$263,MATCH($D10*100+27,Key!$G$2:$G$263,0)),"#"),1,0)) | BS10: =IF(OR($D10="",AN10="",28>$F10),0,IF(UPPER(TRIM(AN10))=IFERROR(INDEX(Key!$C$2:$C$263,MATCH($D10*100+28,Key!$G$2:$G$263,0)),"#"),1,0)) | BT10: =IF(OR($D10="",AO10="",29>$F10),0,IF(UPPER(TRIM(AO10))=IFERROR(INDEX(Key!$C$2:$C$263,MATCH($D10*100+29,Key!$G$2:$G$263,0)),"#"),1,0)) | BU10: =IF(OR($D10="",AP10="",30>$F10),0,IF(UPPER(TRIM(AP10))=IFERROR(INDEX(Key!$C$2:$C$263,MATCH($D10*100+30,Key!$G$2:$G$263,0)),"#"),1,0))
E11: =IF($D11="","",IFERROR(INDEX(Papers!$B$2:$B$12,MATCH($D11,Papers!$A$2:$A$12,0)),"?")) | F11: =IF($D11="","",IFERROR(INDEX(Papers!$C$2:$C$12,MATCH($D11,Papers!$A$2:$A$12,0)),0)) | G11: =IF($D11="","",COUNTIF(M11:AP11,"?*")) | H11: =IF($D11="","",SUM(AR11:BU11)) | I11: =IF($D11="","",G11-H11) | J11: =IF($D11="","",F11-G11) | K11: =IF($D11="","",H11) | L11: =IF($D11="","",IF(F11=0,"",ROUND(H11/F11*100,1))) | AR11: =IF(OR($D11="",M11="",1>$F11),0,IF(UPPER(TRIM(M11))=IFERROR(INDEX(Key!$C$2:$C$263,MATCH($D11*100+1,Key!$G$2:$G$263,0)),"#"),1,0)) | AS11: =IF(OR($D11="",N11="",2>$F11),0,IF(UPPER(TRIM(N11))=IFERROR(INDEX(Key!$C$2:$C$263,MATCH($D11*100+2,Key!$G$2:$G$263,0)),"#"),1,0)) | AT11: =IF(OR($D11="",O11="",3>$F11),0,IF(UPPER(TRIM(O11))=IFERROR(INDEX(Key!$C$2:$C$263,MATCH($D11*100+3,Key!$G$2:$G$263,0)),"#"),1,0)) | AU11: =IF(OR($D11="",P11="",4>$F11),0,IF(UPPER(TRIM(P11))=IFERROR(INDEX(Key!$C$2:$C$263,MATCH($D11*100+4,Key!$G$2:$G$263,0)),"#"),1,0)) | AV11: =IF(OR($D11="",Q11="",5>$F11),0,IF(UPPER(TRIM(Q11))=IFERROR(INDEX(Key!$C$2:$C$263,MATCH($D11*100+5,Key!$G$2:$G$263,0)),"#"),1,0)) | AW11: =IF(OR($D11="",R11="",6>$F11),0,IF(UPPER(TRIM(R11))=IFERROR(INDEX(Key!$C$2:$C$263,MATCH($D11*100+6,Key!$G$2:$G$263,0)),"#"),1,0)) | AX11: =IF(OR($D11="",S11="",7>$F11),0,IF(UPPER(TRIM(S11))=IFERROR(INDEX(Key!$C$2:$C$263,MATCH($D11*100+7,Key!$G$2:$G$263,0)),"#"),1,0)) | AY11: =IF(OR($D11="",T11="",8>$F11),0,IF(UPPER(TRIM(T11))=IFERROR(INDEX(Key!$C$2:$C$263,MATCH($D11*100+8,Key!$G$2:$G$263,0)),"#"),1,0)) | AZ11: =IF(OR($D11="",U11="",9>$F11),0,IF(UPPER(TRIM(U11))=IFERROR(INDEX(Key!$C$2:$C$263,MATCH($D11*100+9,Key!$G$2:$G$263,0)),"#"),1,0)) | BA11: =IF(OR($D11="",V11="",10>$F11),0,IF(UPPER(TRIM(V11))=IFERROR(INDEX(Key!$C$2:$C$263,MATCH($D11*100+10,Key!$G$2:$G$263,0)),"#"),1,0)) | BB11: =IF(OR($D11="",W11="",11>$F11),0,IF(UPPER(TRIM(W11))=IFERROR(INDEX(Key!$C$2:$C$263,MATCH($D11*100+11,Key!$G$2:$G$263,0)),"#"),1,0)) | BC11: =IF(OR($D11="",X11="",12>$F11),0,IF(UPPER(TRIM(X11))=IFERROR(INDEX(Key!$C$2:$C$263,MATCH($D11*100+12,Key!$G$2:$G$263,0)),"#"),1,0)) | BD11: =IF(OR($D11="",Y11="",13>$F11),0,IF(UPPER(TRIM(Y11))=IFERROR(INDEX(Key!$C$2:$C$263,MATCH($D11*100+13,Key!$G$2:$G$263,0)),"#"),1,0)) | BE11: =IF(OR($D11="",Z11="",14>$F11),0,IF(UPPER(TRIM(Z11))=IFERROR(INDEX(Key!$C$2:$C$263,MATCH($D11*100+14,Key!$G$2:$G$263,0)),"#"),1,0)) | BF11: =IF(OR($D11="",AA11="",15>$F11),0,IF(UPPER(TRIM(AA11))=IFERROR(INDEX(Key!$C$2:$C$263,MATCH($D11*100+15,Key!$G$2:$G$263,0)),"#"),1,0)) | BG11: =IF(OR($D11="",AB11="",16>$F11),0,IF(UPPER(TRIM(AB11))=IFERROR(INDEX(Key!$C$2:$C$263,MATCH($D11*100+16,Key!$G$2:$G$263,0)),"#"),1,0)) | BH11: =IF(OR($D11="",AC11="",17>$F11),0,IF(UPPER(TRIM(AC11))=IFERROR(INDEX(Key!$C$2:$C$263,MATCH($D11*100+17,Key!$G$2:$G$263,0)),"#"),1,0)) | BI11: =IF(OR($D11="",AD11="",18>$F11),0,IF(UPPER(TRIM(AD11))=IFERROR(INDEX(Key!$C$2:$C$263,MATCH($D11*100+18,Key!$G$2:$G$263,0)),"#"),1,0)) | BJ11: =IF(OR($D11="",AE11="",19>$F11),0,IF(UPPER(TRIM(AE11))=IFERROR(INDEX(Key!$C$2:$C$263,MATCH($D11*100+19,Key!$G$2:$G$263,0)),"#"),1,0)) | BK11: =IF(OR($D11="",AF11="",20>$F11),0,IF(UPPER(TRIM(AF11))=IFERROR(INDEX(Key!$C$2:$C$263,MATCH($D11*100+20,Key!$G$2:$G$263,0)),"#"),1,0)) | BL11: =IF(OR($D11="",AG11="",21>$F11),0,IF(UPPER(TRIM(AG11))=IFERROR(INDEX(Key!$C$2:$C$263,MATCH($D11*100+21,Key!$G$2:$G$263,0)),"#"),1,0)) | BM11: =IF(OR($D11="",AH11="",22>$F11),0,IF(UPPER(TRIM(AH11))=IFERROR(INDEX(Key!$C$2:$C$263,MATCH($D11*100+22,Key!$G$2:$G$263,0)),"#"),1,0)) | BN11: =IF(OR($D11="",AI11="",23>$F11),0,IF(UPPER(TRIM(AI11))=IFERROR(INDEX(Key!$C$2:$C$263,MATCH($D11*100+23,Key!$G$2:$G$263,0)),"#"),1,0)) | BO11: =IF(OR($D11="",AJ11="",24>$F11),0,IF(UPPER(TRIM(AJ11))=IFERROR(INDEX(Key!$C$2:$C$263,MATCH($D11*100+24,Key!$G$2:$G$263,0)),"#"),1,0)) | BP11: =IF(OR($D11="",AK11="",25>$F11),0,IF(UPPER(TRIM(AK11))=IFERROR(INDEX(Key!$C$2:$C$263,MATCH($D11*100+25,Key!$G$2:$G$263,0)),"#"),1,0)) | BQ11: =IF(OR($D11="",AL11="",26>$F11),0,IF(UPPER(TRIM(AL11))=IFERROR(INDEX(Key!$C$2:$C$263,MATCH($D11*100+26,Key!$G$2:$G$263,0)),"#"),1,0)) | BR11: =IF(OR($D11="",AM11="",27>$F11),0,IF(UPPER(TRIM(AM11))=IFERROR(INDEX(Key!$C$2:$C$263,MATCH($D11*100+27,Key!$G$2:$G$263,0)),"#"),1,0)) | BS11: =IF(OR($D11="",AN11="",28>$F11),0,IF(UPPER(TRIM(AN11))=IFERROR(INDEX(Key!$C$2:$C$263,MATCH($D11*100+28,Key!$G$2:$G$263,0)),"#"),1,0)) | BT11: =IF(OR($D11="",AO11="",29>$F11),0,IF(UPPER(TRIM(AO11))=IFERROR(INDEX(Key!$C$2:$C$263,MATCH($D11*100+29,Key!$G$2:$G$263,0)),"#"),1,0)) | BU11: =IF(OR($D11="",AP11="",30>$F11),0,IF(UPPER(TRIM(AP11))=IFERROR(INDEX(Key!$C$2:$C$263,MATCH($D11*100+30,Key!$G$2:$G$263,0)),"#"),1,0))
E12: =IF($D12="","",IFERROR(INDEX(Papers!$B$2:$B$12,MATCH($D12,Papers!$A$2:$A$12,0)),"?")) | F12: =IF($D12="","",IFERROR(INDEX(Papers!$C$2:$C$12,MATCH($D12,Papers!$A$2:$A$12,0)),0)) | G12: =IF($D12="","",COUNTIF(M12:AP12,"?*")) | H12: =IF($D12="","",SUM(AR12:BU12)) | I12: =IF($D12="","",G12-H12) | J12: =IF($D12="","",F12-G12) | K12: =IF($D12="","",H12) | L12: =IF($D12="","",IF(F12=0,"",ROUND(H12/F12*100,1))) | AR12: =IF(OR($D12="",M12="",1>$F12),0,IF(UPPER(TRIM(M12))=IFERROR(INDEX(Key!$C$2:$C$263,MATCH($D12*100+1,Key!$G$2:$G$263,0)),"#"),1,0)) | AS12: =IF(OR($D12="",N12="",2>$F12),0,IF(UPPER(TRIM(N12))=IFERROR(INDEX(Key!$C$2:$C$263,MATCH($D12*100+2,Key!$G$2:$G$263,0)),"#"),1,0)) | AT12: =IF(OR($D12="",O12="",3>$F12),0,IF(UPPER(TRIM(O12))=IFERROR(INDEX(Key!$C$2:$C$263,MATCH($D12*100+3,Key!$G$2:$G$263,0)),"#"),1,0)) | AU12: =IF(OR($D12="",P12="",4>$F12),0,IF(UPPER(TRIM(P12))=IFERROR(INDEX(Key!$C$2:$C$263,MATCH($D12*100+4,Key!$G$2:$G$263,0)),"#"),1,0)) | AV12: =IF(OR($D12="",Q12="",5>$F12),0,IF(UPPER(TRIM(Q12))=IFERROR(INDEX(Key!$C$2:$C$263,MATCH($D12*100+5,Key!$G$2:$G$263,0)),"#"),1,0)) | AW12: =IF(OR($D12="",R12="",6>$F12),0,IF(UPPER(TRIM(R12))=IFERROR(INDEX(Key!$C$2:$C$263,MATCH($D12*100+6,Key!$G$2:$G$263,0)),"#"),1,0)) | AX12: =IF(OR($D12="",S12="",7>$F12),0,IF(UPPER(TRIM(S12))=IFERROR(INDEX(Key!$C$2:$C$263,MATCH($D12*100+7,Key!$G$2:$G$263,0)),"#"),1,0)) | AY12: =IF(OR($D12="",T12="",8>$F12),0,IF(UPPER(TRIM(T12))=IFERROR(INDEX(Key!$C$2:$C$263,MATCH($D12*100+8,Key!$G$2:$G$263,0)),"#"),1,0)) | AZ12: =IF(OR($D12="",U12="",9>$F12),0,IF(UPPER(TRIM(U12))=IFERROR(INDEX(Key!$C$2:$C$263,MATCH($D12*100+9,Key!$G$2:$G$263,0)),"#"),1,0)) | BA12: =IF(OR($D12="",V12="",10>$F12),0,IF(UPPER(TRIM(V12))=IFERROR(INDEX(Key!$C$2:$C$263,MATCH($D12*100+10,Key!$G$2:$G$263,0)),"#"),1,0)) | BB12: =IF(OR($D12="",W12="",11>$F12),0,IF(UPPER(TRIM(W12))=IFERROR(INDEX(Key!$C$2:$C$263,MATCH($D12*100+11,Key!$G$2:$G$263,0)),"#"),1,0)) | BC12: =IF(OR($D12="",X12="",12>$F12),0,IF(UPPER(TRIM(X12))=IFERROR(INDEX(Key!$C$2:$C$263,MATCH($D12*100+12,Key!$G$2:$G$263,0)),"#"),1,0)) | BD12: =IF(OR($D12="",Y12="",13>$F12),0,IF(UPPER(TRIM(Y12))=IFERROR(INDEX(Key!$C$2:$C$263,MATCH($D12*100+13,Key!$G$2:$G$263,0)),"#"),1,0)) | BE12: =IF(OR($D12="",Z12="",14>$F12),0,IF(UPPER(TRIM(Z12))=IFERROR(INDEX(Key!$C$2:$C$263,MATCH($D12*100+14,Key!$G$2:$G$263,0)),"#"),1,0)) | BF12: =IF(OR($D12="",AA12="",15>$F12),0,IF(UPPER(TRIM(AA12))=IFERROR(INDEX(Key!$C$2:$C$263,MATCH($D12*100+15,Key!$G$2:$G$263,0)),"#"),1,0)) | BG12: =IF(OR($D12="",AB12="",16>$F12),0,IF(UPPER(TRIM(AB12))=IFERROR(INDEX(Key!$C$2:$C$263,MATCH($D12*100+16,Key!$G$2:$G$263,0)),"#"),1,0)) | BH12: =IF(OR($D12="",AC12="",17>$F12),0,IF(UPPER(TRIM(AC12))=IFERROR(INDEX(Key!$C$2:$C$263,MATCH($D12*100+17,Key!$G$2:$G$263,0)),"#"),1,0)) | BI12: =IF(OR($D12="",AD12="",18>$F12),0,IF(UPPER(TRIM(AD12))=IFERROR(INDEX(Key!$C$2:$C$263,MATCH($D12*100+18,Key!$G$2:$G$263,0)),"#"),1,0)) | BJ12: =IF(OR($D12="",AE12="",19>$F12),0,IF(UPPER(TRIM(AE12))=IFERROR(INDEX(Key!$C$2:$C$263,MATCH($D12*100+19,Key!$G$2:$G$263,0)),"#"),1,0)) | BK12: =IF(OR($D12="",AF12="",20>$F12),0,IF(UPPER(TRIM(AF12))=IFERROR(INDEX(Key!$C$2:$C$263,MATCH($D12*100+20,Key!$G$2:$G$263,0)),"#"),1,0)) | BL12: =IF(OR($D12="",AG12="",21>$F12),0,IF(UPPER(TRIM(AG12))=IFERROR(INDEX(Key!$C$2:$C$263,MATCH($D12*100+21,Key!$G$2:$G$263,0)),"#"),1,0)) | BM12: =IF(OR($D12="",AH12="",22>$F12),0,IF(UPPER(TRIM(AH12))=IFERROR(INDEX(Key!$C$2:$C$263,MATCH($D12*100+22,Key!$G$2:$G$263,0)),"#"),1,0)) | BN12: =IF(OR($D12="",AI12="",23>$F12),0,IF(UPPER(TRIM(AI12))=IFERROR(INDEX(Key!$C$2:$C$263,MATCH($D12*100+23,Key!$G$2:$G$263,0)),"#"),1,0)) | BO12: =IF(OR($D12="",AJ12="",24>$F12),0,IF(UPPER(TRIM(AJ12))=IFERROR(INDEX(Key!$C$2:$C$263,MATCH($D12*100+24,Key!$G$2:$G$263,0)),"#"),1,0)) | BP12: =IF(OR($D12="",AK12="",25>$F12),0,IF(UPPER(TRIM(AK12))=IFERROR(INDEX(Key!$C$2:$C$263,MATCH($D12*100+25,Key!$G$2:$G$263,0)),"#"),1,0)) | BQ12: =IF(OR($D12="",AL12="",26>$F12),0,IF(UPPER(TRIM(AL12))=IFERROR(INDEX(Key!$C$2:$C$263,MATCH($D12*100+26,Key!$G$2:$G$263,0)),"#"),1,0)) | BR12: =IF(OR($D12="",AM12="",27>$F12),0,IF(UPPER(TRIM(AM12))=IFERROR(INDEX(Key!$C$2:$C$263,MATCH($D12*100+27,Key!$G$2:$G$263,0)),"#"),1,0)) | BS12: =IF(OR($D12="",AN12="",28>$F12),0,IF(UPPER(TRIM(AN12))=IFERROR(INDEX(Key!$C$2:$C$263,MATCH($D12*100+28,Key!$G$2:$G$263,0)),"#"),1,0)) | BT12: =IF(OR($D12="",AO12="",29>$F12),0,IF(UPPER(TRIM(AO12))=IFERROR(INDEX(Key!$C$2:$C$263,MATCH($D12*100+29,Key!$G$2:$G$263,0)),"#"),1,0)) | BU12: =IF(OR($D12="",AP12="",30>$F12),0,IF(UPPER(TRIM(AP12))=IFERROR(INDEX(Key!$C$2:$C$263,MATCH($D12*100+30,Key!$G$2:$G$263,0)),"#"),1,0))
E13: =IF($D13="","",IFERROR(INDEX(Papers!$B$2:$B$12,MATCH($D13,Papers!$A$2:$A$12,0)),"?")) | F13: =IF($D13="","",IFERROR(INDEX(Papers!$C$2:$C$12,MATCH($D13,Papers!$A$2:$A$12,0)),0)) | G13: =IF($D13="","",COUNTIF(M13:AP13,"?*")) | H13: =IF($D13="","",SUM(AR13:BU13)) | I13: =IF($D13="","",G13-H13) | J13: =IF($D13="","",F13-G13) | K13: =IF($D13="","",H13) | L13: =IF($D13="","",IF(F13=0,"",ROUND(H13/F13*100,1))) | AR13: =IF(OR($D13="",M13="",1>$F13),0,IF(UPPER(TRIM(M13))=IFERROR(INDEX(Key!$C$2:$C$263,MATCH($D13*100+1,Key!$G$2:$G$263,0)),"#"),1,0)) | AS13: =IF(OR($D13="",N13="",2>$F13),0,IF(UPPER(TRIM(N13))=IFERROR(INDEX(Key!$C$2:$C$263,MATCH($D13*100+2,Key!$G$2:$G$263,0)),"#"),1,0)) | AT13: =IF(OR($D13="",O13="",3>$F13),0,IF(UPPER(TRIM(O13))=IFERROR(INDEX(Key!$C$2:$C$263,MATCH($D13*100+3,Key!$G$2:$G$263,0)),"#"),1,0)) | AU13: =IF(OR($D13="",P13="",4>$F13),0,IF(UPPER(TRIM(P13))=IFERROR(INDEX(Key!$C$2:$C$263,MATCH($D13*100+4,Key!$G$2:$G$263,0)),"#"),1,0)) | AV13: =IF(OR($D13="",Q13="",5>$F13),0,IF(UPPER(TRIM(Q13))=IFERROR(INDEX(Key!$C$2:$C$263,MATCH($D13*100+5,Key!$G$2:$G$263,0)),"#"),1,0)) | AW13: =IF(OR($D13="",R13="",6>$F13),0,IF(UPPER(TRIM(R13))=IFERROR(INDEX(Key!$C$2:$C$263,MATCH($D13*100+6,Key!$G$2:$G$263,0)),"#"),1,0)) | AX13: =IF(OR($D13="",S13="",7>$F13),0,IF(UPPER(TRIM(S13))=IFERROR(INDEX(Key!$C$2:$C$263,MATCH($D13*100+7,Key!$G$2:$G$263,0)),"#"),1,0)) | AY13: =IF(OR($D13="",T13="",8>$F13),0,IF(UPPER(TRIM(T13))=IFERROR(INDEX(Key!$C$2:$C$263,MATCH($D13*100+8,Key!$G$2:$G$263,0)),"#"),1,0)) | AZ13: =IF(OR($D13="",U13="",9>$F13),0,IF(UPPER(TRIM(U13))=IFERROR(INDEX(Key!$C$2:$C$263,MATCH($D13*100+9,Key!$G$2:$G$263,0)),"#"),1,0)) | BA13: =IF(OR($D13="",V13="",10>$F13),0,IF(UPPER(TRIM(V13))=IFERROR(INDEX(Key!$C$2:$C$263,MATCH($D13*100+10,Key!$G$2:$G$263,0)),"#"),1,0)) | BB13: =IF(OR($D13="",W13="",11>$F13),0,IF(UPPER(TRIM(W13))=IFERROR(INDEX(Key!$C$2:$C$263,MATCH($D13*100+11,Key!$G$2:$G$263,0)),"#"),1,0)) | BC13: =IF(OR($D13="",X13="",12>$F13),0,IF(UPPER(TRIM(X13))=IFERROR(INDEX(Key!$C$2:$C$263,MATCH($D13*100+12,Key!$G$2:$G$263,0)),"#"),1,0)) | BD13: =IF(OR($D13="",Y13="",13>$F13),0,IF(UPPER(TRIM(Y13))=IFERROR(INDEX(Key!$C$2:$C$263,MATCH($D13*100+13,Key!$G$2:$G$263,0)),"#"),1,0)) | BE13: =IF(OR($D13="",Z13="",14>$F13),0,IF(UPPER(TRIM(Z13))=IFERROR(INDEX(Key!$C$2:$C$263,MATCH($D13*100+14,Key!$G$2:$G$263,0)),"#"),1,0)) | BF13: =IF(OR($D13="",AA13="",15>$F13),0,IF(UPPER(TRIM(AA13))=IFERROR(INDEX(Key!$C$2:$C$263,MATCH($D13*100+15,Key!$G$2:$G$263,0)),"#"),1,0)) | BG13: =IF(OR($D13="",AB13="",16>$F13),0,IF(UPPER(TRIM(AB13))=IFERROR(INDEX(Key!$C$2:$C$263,MATCH($D13*100+16,Key!$G$2:$G$263,0)),"#"),1,0)) | BH13: =IF(OR($D13="",AC13="",17>$F13),0,IF(UPPER(TRIM(AC13))=IFERROR(INDEX(Key!$C$2:$C$263,MATCH($D13*100+17,Key!$G$2:$G$263,0)),"#"),1,0)) | BI13: =IF(OR($D13="",AD13="",18>$F13),0,IF(UPPER(TRIM(AD13))=IFERROR(INDEX(Key!$C$2:$C$263,MATCH($D13*100+18,Key!$G$2:$G$263,0)),"#"),1,0)) | BJ13: =IF(OR($D13="",AE13="",19>$F13),0,IF(UPPER(TRIM(AE13))=IFERROR(INDEX(Key!$C$2:$C$263,MATCH($D13*100+19,Key!$G$2:$G$263,0)),"#"),1,0)) | BK13: =IF(OR($D13="",AF13="",20>$F13),0,IF(UPPER(TRIM(AF13))=IFERROR(INDEX(Key!$C$2:$C$263,MATCH($D13*100+20,Key!$G$2:$G$263,0)),"#"),1,0)) | BL13: =IF(OR($D13="",AG13="",21>$F13),0,IF(UPPER(TRIM(AG13))=IFERROR(INDEX(Key!$C$2:$C$263,MATCH($D13*100+21,Key!$G$2:$G$263,0)),"#"),1,0)) | BM13: =IF(OR($D13="",AH13="",22>$F13),0,IF(UPPER(TRIM(AH13))=IFERROR(INDEX(Key!$C$2:$C$263,MATCH($D13*100+22,Key!$G$2:$G$263,0)),"#"),1,0)) | BN13: =IF(OR($D13="",AI13="",23>$F13),0,IF(UPPER(TRIM(AI13))=IFERROR(INDEX(Key!$C$2:$C$263,MATCH($D13*100+23,Key!$G$2:$G$263,0)),"#"),1,0)) | BO13: =IF(OR($D13="",AJ13="",24>$F13),0,IF(UPPER(TRIM(AJ13))=IFERROR(INDEX(Key!$C$2:$C$263,MATCH($D13*100+24,Key!$G$2:$G$263,0)),"#"),1,0)) | BP13: =IF(OR($D13="",AK13="",25>$F13),0,IF(UPPER(TRIM(AK13))=IFERROR(INDEX(Key!$C$2:$C$263,MATCH($D13*100+25,Key!$G$2:$G$263,0)),"#"),1,0)) | BQ13: =IF(OR($D13="",AL13="",26>$F13),0,IF(UPPER(TRIM(AL13))=IFERROR(INDEX(Key!$C$2:$C$263,MATCH($D13*100+26,Key!$G$2:$G$263,0)),"#"),1,0)) | BR13: =IF(OR($D13="",AM13="",27>$F13),0,IF(UPPER(TRIM(AM13))=IFERROR(INDEX(Key!$C$2:$C$263,MATCH($D13*100+27,Key!$G$2:$G$263,0)),"#"),1,0)) | BS13: =IF(OR($D13="",AN13="",28>$F13),0,IF(UPPER(TRIM(AN13))=IFERROR(INDEX(Key!$C$2:$C$263,MATCH($D13*100+28,Key!$G$2:$G$263,0)),"#"),1,0)) | BT13: =IF(OR($D13="",AO13="",29>$F13),0,IF(UPPER(TRIM(AO13))=IFERROR(INDEX(Key!$C$2:$C$263,MATCH($D13*100+29,Key!$G$2:$G$263,0)),"#"),1,0)) | BU13: =IF(OR($D13="",AP13="",30>$F13),0,IF(UPPER(TRIM(AP13))=IFERROR(INDEX(Key!$C$2:$C$263,MATCH($D13*100+30,Key!$G$2:$G$263,0)),"#"),1,0))
... E200: =IF($D200="","",IFERROR(INDEX(Papers!$B$2:$B$12,MATCH($D200,Papers!$A$2:$A$12,0)),"?")) | F200: =IF($D200="","",IFERROR(INDEX(Papers!$C$2:$C$12,MATCH($D200,Papers!$A$2:$A$12,0)),0)) | G200: =IF($D200="","",COUNTIF(M200:AP200,"?*")) | H200: =IF($D200="","",SUM(AR200:BU200)) | I200: =IF($D200="","",G200-H200) | J200: =IF($D200="","",F200-G200) | K200: =IF($D200="","",H200) | L200: =IF($D200="","",IF(F200=0,"",ROUND(H200/F200*100,1))) | AR200: =IF(OR($D200="",M200="",1>$F200),0,IF(UPPER(TRIM(M200))=IFERROR(INDEX(Key!$C$2:$C$263,MATCH($D200*100+1,Key!$G$2:$G$263,0)),"#"),1,0)) | AS200: =IF(OR($D200="",N200="",2>$F200),0,IF(UPPER(TRIM(N200))=IFERROR(INDEX(Key!$C$2:$C$263,MATCH($D200*100+2,Key!$G$2:$G$263,0)),"#"),1,0)) | AT200: =IF(OR($D200="",O200="",3>$F200),0,IF(UPPER(TRIM(O200))=IFERROR(INDEX(Key!$C$2:$C$263,MATCH($D200*100+3,Key!$G$2:$G$263,0)),"#"),1,0)) | AU200: =IF(OR($D200="",P200="",4>$F200),0,IF(UPPER(TRIM(P200))=IFERROR(INDEX(Key!$C$2:$C$263,MATCH($D200*100+4,Key!$G$2:$G$263,0)),"#"),1,0)) | AV200: =IF(OR($D200="",Q200="",5>$F200),0,IF(UPPER(TRIM(Q200))=IFERROR(INDEX(Key!$C$2:$C$263,MATCH($D200*100+5,Key!$G$2:$G$263,0)),"#"),1,0)) | AW200: =IF(OR($D200="",R200="",6>$F200),0,IF(UPPER(TRIM(R200))=IFERROR(INDEX(Key!$C$2:$C$263,MATCH($D200*100+6,Key!$G$2:$G$263,0)),"#"),1,0)) | AX200: =IF(OR($D200="",S200="",7>$F200),0,IF(UPPER(TRIM(S200))=IFERROR(INDEX(Key!$C$2:$C$263,MATCH($D200*100+7,Key!$G$2:$G$263,0)),"#"),1,0)) | AY200: =IF(OR($D200="",T200="",8>$F200),0,IF(UPPER(TRIM(T200))=IFERROR(INDEX(Key!$C$2:$C$263,MATCH($D200*100+8,Key!$G$2:$G$263,0)),"#"),1,0)) | AZ200: =IF(OR($D200="",U200="",9>$F200),0,IF(UPPER(TRIM(U200))=IFERROR(INDEX(Key!$C$2:$C$263,MATCH($D200*100+9,Key!$G$2:$G$263,0)),"#"),1,0)) | BA200: =IF(OR($D200="",V200="",10>$F200),0,IF(UPPER(TRIM(V200))=IFERROR(INDEX(Key!$C$2:$C$263,MATCH($D200*100+10,Key!$G$2:$G$263,0)),"#"),1,0)) | BB200: =IF(OR($D200="",W200="",11>$F200),0,IF(UPPER(TRIM(W200))=IFERROR(INDEX(Key!$C$2:$C$263,MATCH($D200*100+11,Key!$G$2:$G$263,0)),"#"),1,0)) | BC200: =IF(OR($D200="",X200="",12>$F200),0,IF(UPPER(TRIM(X200))=IFERROR(INDEX(Key!$C$2:$C$263,MATCH($D200*100+12,Key!$G$2:$G$263,0)),"#"),1,0)) | BD200: =IF(OR($D200="",Y200="",13>$F200),0,IF(UPPER(TRIM(Y200))=IFERROR(INDEX(Key!$C$2:$C$263,MATCH($D200*100+13,Key!$G$2:$G$263,0)),"#"),1,0)) | BE200: =IF(OR($D200="",Z200="",14>$F200),0,IF(UPPER(TRIM(Z200))=IFERROR(INDEX(Key!$C$2:$C$263,MATCH($D200*100+14,Key!$G$2:$G$263,0)),"#"),1,0)) | BF200: =IF(OR($D200="",AA200="",15>$F200),0,IF(UPPER(TRIM(AA200))=IFERROR(INDEX(Key!$C$2:$C$263,MATCH($D200*100+15,Key!$G$2:$G$263,0)),"#"),1,0)) | BG200: =IF(OR($D200="",AB200="",16>$F200),0,IF(UPPER(TRIM(AB200))=IFERROR(INDEX(Key!$C$2:$C$263,MATCH($D200*100+16,Key!$G$2:$G$263,0)),"#"),1,0)) | BH200: =IF(OR($D200="",AC200="",17>$F200),0,IF(UPPER(TRIM(AC200))=IFERROR(INDEX(Key!$C$2:$C$263,MATCH($D200*100+17,Key!$G$2:$G$263,0)),"#"),1,0)) | BI200: =IF(OR($D200="",AD200="",18>$F200),0,IF(UPPER(TRIM(AD200))=IFERROR(INDEX(Key!$C$2:$C$263,MATCH($D200*100+18,Key!$G$2:$G$263,0)),"#"),1,0)) | BJ200: =IF(OR($D200="",AE200="",19>$F200),0,IF(UPPER(TRIM(AE200))=IFERROR(INDEX(Key!$C$2:$C$263,MATCH($D200*100+19,Key!$G$2:$G$263,0)),"#"),1,0)) | BK200: =IF(OR($D200="",AF200="",20>$F200),0,IF(UPPER(TRIM(AF200))=IFERROR(INDEX(Key!$C$2:$C$263,MATCH($D200*100+20,Key!$G$2:$G$263,0)),"#"),1,0)) | BL200: =IF(OR($D200="",AG200="",21>$F200),0,IF(UPPER(TRIM(AG200))=IFERROR(INDEX(Key!$C$2:$C$263,MATCH($D200*100+21,Key!$G$2:$G$263,0)),"#"),1,0)) | BM200: =IF(OR($D200="",AH200="",22>$F200),0,IF(UPPER(TRIM(AH200))=IFERROR(INDEX(Key!$C$2:$C$263,MATCH($D200*100+22,Key!$G$2:$G$263,0)),"#"),1,0)) | BN200: =IF(OR($D200="",AI200="",23>$F200),0,IF(UPPER(TRIM(AI200))=IFERROR(INDEX(Key!$C$2:$C$263,MATCH($D200*100+23,Key!$G$2:$G$263,0)),"#"),1,0)) | BO200: =IF(OR($D200="",AJ200="",24>$F200),0,IF(UPPER(TRIM(AJ200))=IFERROR(INDEX(Key!$C$2:$C$263,MATCH($D200*100+24,Key!$G$2:$G$263,0)),"#"),1,0)) | BP200: =IF(OR($D200="",AK200="",25>$F200),0,IF(UPPER(TRIM(AK200))=IFERROR(INDEX(Key!$C$2:$C$263,MATCH($D200*100+25,Key!$G$2:$G$263,0)),"#"),1,0)) | BQ200: =IF(OR($D200="",AL200="",26>$F200),0,IF(UPPER(TRIM(AL200))=IFERROR(INDEX(Key!$C$2:$C$263,MATCH($D200*100+26,Key!$G$2:$G$263,0)),"#"),1,0)) | BR200: =IF(OR($D200="",AM200="",27>$F200),0,IF(UPPER(TRIM(AM200))=IFERROR(INDEX(Key!$C$2:$C$263,MATCH($D200*100+27,Key!$G$2:$G$263,0)),"#"),1,0)) | BS200: =IF(OR($D200="",AN200="",28>$F200),0,IF(UPPER(TRIM(AN200))=IFERROR(INDEX(Key!$C$2:$C$263,MATCH($D200*100+28,Key!$G$2:$G$263,0)),"#"),1,0)) | BT200: =IF(OR($D200="",AO200="",29>$F200),0,IF(UPPER(TRIM(AO200))=IFERROR(INDEX(Key!$C$2:$C$263,MATCH($D200*100+29,Key!$G$2:$G$263,0)),"#"),1,0)) | BU200: =IF(OR($D200="",AP200="",30>$F200),0,IF(UPPER(TRIM(AP200))=IFERROR(INDEX(Key!$C$2:$C$263,MATCH($D200*100+30,Key!$G$2:$G$263,0)),"#"),1,0))

Sheet Topic_Accuracy
A1: Attempt ID | B1: Candidate | C1: Paper | D1: S1 name | E1: S1 correct | F1: S1 total | G1: S1 % | H1: S2 name | I1: S2 correct | J1: S2 total | K1: S2 % | L1: S3 name | M1: S3 correct | N1: S3 total | O1: S3 % | P1: S4 name | Q1: S4 correct | R1: S4 total | S1: S4 % | T1: S5 name | U1: S5 correct | V1: S5 total | W1: S5 % | X1: S6 name | Y1: S6 correct | Z1: S6 total | AA1: S6 % | AB1: Weakest subtopic | AC1: Weakest % | AD1: Recommended remedial lesson | AE1: Guide (not official)
A2: =IF(Attempts!A2="","",Attempts!A2) | B2: =IF(Attempts!A2="","",Attempts!B2) | C2: =IF(Attempts!A2="","",Attempts!D2) | D2: =IF($A2="","",IFERROR(INDEX(Papers!$E$2:$E$12,MATCH($C2,Papers!$A$2:$A$12,0)),"")) | E2: =IF($A2="","",IFERROR(SUMPRODUCT((INDEX(SubMap!$B$2:$AE$12,MATCH($C2,SubMap!$A$2:$A$12,0),0)=1)*Attempts!$AR2:$BU2),0)) | F2: =IF($A2="","",IFERROR(COUNTIF(INDEX(SubMap!$B$2:$AE$12,MATCH($C2,SubMap!$A$2:$A$12,0),0),1),0)) | G2: =IF(OR($A2="",F2=0),"",ROUND(E2/F2*100,1)) | H2: =IF($A2="","",IFERROR(INDEX(Papers!$F$2:$F$12,MATCH($C2,Papers!$A$2:$A$12,0)),"")) | I2: =IF($A2="","",IFERROR(SUMPRODUCT((INDEX(SubMap!$B$2:$AE$12,MATCH($C2,SubMap!$A$2:$A$12,0),0)=2)*Attempts!$AR2:$BU2),0)) | J2: =IF($A2="","",IFERROR(COUNTIF(INDEX(SubMap!$B$2:$AE$12,MATCH($C2,SubMap!$A$2:$A$12,0),0),2),0)) | K2: =IF(OR($A2="",J2=0),"",ROUND(I2/J2*100,1)) | L2: =IF($A2="","",IFERROR(INDEX(Papers!$G$2:$G$12,MATCH($C2,Papers!$A$2:$A$12,0)),"")) | M2: =IF($A2="","",IFERROR(SUMPRODUCT((INDEX(SubMap!$B$2:$AE$12,MATCH($C2,SubMap!$A$2:$A$12,0),0)=3)*Attempts!$AR2:$BU2),0)) | N2: =IF($A2="","",IFERROR(COUNTIF(INDEX(SubMap!$B$2:$AE$12,MATCH($C2,SubMap!$A$2:$A$12,0),0),3),0)) | O2: =IF(OR($A2="",N2=0),"",ROUND(M2/N2*100,1)) | P2: =IF($A2="","",IFERROR(INDEX(Papers!$H$2:$H$12,MATCH($C2,Papers!$A$2:$A$12,0)),"")) | Q2: =IF($A2="","",IFERROR(SUMPRODUCT((INDEX(SubMap!$B$2:$AE$12,MATCH($C2,SubMap!$A$2:$A$12,0),0)=4)*Attempts!$AR2:$BU2),0)) | R2: =IF($A2="","",IFERROR(COUNTIF(INDEX(SubMap!$B$2:$AE$12,MATCH($C2,SubMap!$A$2:$A$12,0),0),4),0)) | S2: =IF(OR($A2="",R2=0),"",ROUND(Q2/R2*100,1)) | T2: =IF($A2="","",IFERROR(INDEX(Papers!$I$2:$I$12,MATCH($C2,Papers!$A$2:$A$12,0)),"")) | U2: =IF($A2="","",IFERROR(SUMPRODUCT((INDEX(SubMap!$B$2:$AE$12,MATCH($C2,SubMap!$A$2:$A$12,0),0)=5)*Attempts!$AR2:$BU2),0)) | V2: =IF($A2="","",IFERROR(COUNTIF(INDEX(SubMap!$B$2:$AE$12,MATCH($C2,SubMap!$A$2:$A$12,0),0),5),0)) | W2: =IF(OR($A2="",V2=0),"",ROUND(U2/V2*100,1)) | X2: =IF($A2="","",IFERROR(INDEX(Papers!$J$2:$J$12,MATCH($C2,Papers!$A$2:$A$12,0)),"")) | Y2: =IF($A2="","",IFERROR(SUMPRODUCT((INDEX(SubMap!$B$2:$AE$12,MATCH($C2,SubMap!$A$2:$A$12,0),0)=6)*Attempts!$AR2:$BU2),0)) | Z2: =IF($A2="","",IFERROR(COUNTIF(INDEX(SubMap!$B$2:$AE$12,MATCH($C2,SubMap!$A$2:$A$12,0),0),6),0)) | AA2: =IF(OR($A2="",Z2=0),"",ROUND(Y2/Z2*100,1)) | AB2: =IF($A2="","",IFERROR(INDEX(CHOOSE({1,2,3,4,5,6},D2,H2,L2,P2,T2,X2),MATCH(MIN(G2,K2,O2,S2,W2,AA2),CHOOSE({1,2,3,4,5,6},G2,K2,O2,S2,W2,AA2),0)),"")) | AC2: =IF($A2="","",IF(COUNT(G2,K2,O2,S2,W2,AA2)=0,"",MIN(G2,K2,O2,S2,W2,AA2))) | AD2: =IF($A2="","",IFERROR(INDEX(CHOOSE({1,2,3,4,5,6},IFERROR(INDEX(Papers!$K$2:$K$12,MATCH($C2,Papers!$A$2:$A$12,0)),""),IFERROR(INDEX(Papers!$L$2:$L$12,MATCH($C2,Papers!$A$2:$A$12,0)),""),IFERROR(INDEX(Papers!$M$2:$M$12,MATCH($C2,Papers!$A$2:$A$12,0)),""),IFERROR(INDEX(Papers!$N$2:$N$12,MATCH($C2,Papers!$A$2:$A$12,0)),""),IFERROR(INDEX(Papers!$O$2:$O$12,MATCH($C2,Papers!$A$2:$A$12,0)),""),IFERROR(INDEX(Papers!$P$2:$P$12,MATCH($C2,Papers!$A$2:$A$12,0)),"")),MATCH(MIN(G2,K2,O2,S2,W2,AA2),CHOOSE({1,2,3,4,5,6},G2,K2,O2,S2,W2,AA2),0)),"")) | AE2: =IF(AC2="","",IF(AC2<50,"Re-teach",IF(AC2<75,"Practice more","Relatively secure")))
A3: =IF(Attempts!A3="","",Attempts!A3) | B3: =IF(Attempts!A3="","",Attempts!B3) | C3: =IF(Attempts!A3="","",Attempts!D3) | D3: =IF($A3="","",IFERROR(INDEX(Papers!$E$2:$E$12,MATCH($C3,Papers!$A$2:$A$12,0)),"")) | E3: =IF($A3="","",IFERROR(SUMPRODUCT((INDEX(SubMap!$B$2:$AE$12,MATCH($C3,SubMap!$A$2:$A$12,0),0)=1)*Attempts!$AR3:$BU3),0)) | F3: =IF($A3="","",IFERROR(COUNTIF(INDEX(SubMap!$B$2:$AE$12,MATCH($C3,SubMap!$A$2:$A$12,0),0),1),0)) | G3: =IF(OR($A3="",F3=0),"",ROUND(E3/F3*100,1)) | H3: =IF($A3="","",IFERROR(INDEX(Papers!$F$2:$F$12,MATCH($C3,Papers!$A$2:$A$12,0)),"")) | I3: =IF($A3="","",IFERROR(SUMPRODUCT((INDEX(SubMap!$B$2:$AE$12,MATCH($C3,SubMap!$A$2:$A$12,0),0)=2)*Attempts!$AR3:$BU3),0)) | J3: =IF($A3="","",IFERROR(COUNTIF(INDEX(SubMap!$B$2:$AE$12,MATCH($C3,SubMap!$A$2:$A$12,0),0),2),0)) | K3: =IF(OR($A3="",J3=0),"",ROUND(I3/J3*100,1)) | L3: =IF($A3="","",IFERROR(INDEX(Papers!$G$2:$G$12,MATCH($C3,Papers!$A$2:$A$12,0)),"")) | M3: =IF($A3="","",IFERROR(SUMPRODUCT((INDEX(SubMap!$B$2:$AE$12,MATCH($C3,SubMap!$A$2:$A$12,0),0)=3)*Attempts!$AR3:$BU3),0)) | N3: =IF($A3="","",IFERROR(COUNTIF(INDEX(SubMap!$B$2:$AE$12,MATCH($C3,SubMap!$A$2:$A$12,0),0),3),0)) | O3: =IF(OR($A3="",N3=0),"",ROUND(M3/N3*100,1)) | P3: =IF($A3="","",IFERROR(INDEX(Papers!$H$2:$H$12,MATCH($C3,Papers!$A$2:$A$12,0)),"")) | Q3: =IF($A3="","",IFERROR(SUMPRODUCT((INDEX(SubMap!$B$2:$AE$12,MATCH($C3,SubMap!$A$2:$A$12,0),0)=4)*Attempts!$AR3:$BU3),0)) | R3: =IF($A3="","",IFERROR(COUNTIF(INDEX(SubMap!$B$2:$AE$12,MATCH($C3,SubMap!$A$2:$A$12,0),0),4),0)) | S3: =IF(OR($A3="",R3=0),"",ROUND(Q3/R3*100,1)) | T3: =IF($A3="","",IFERROR(INDEX(Papers!$I$2:$I$12,MATCH($C3,Papers!$A$2:$A$12,0)),"")) | U3: =IF($A3="","",IFERROR(SUMPRODUCT((INDEX(SubMap!$B$2:$AE$12,MATCH($C3,SubMap!$A$2:$A$12,0),0)=5)*Attempts!$AR3:$BU3),0)) | V3: =IF($A3="","",IFERROR(COUNTIF(INDEX(SubMap!$B$2:$AE$12,MATCH($C3,SubMap!$A$2:$A$12,0),0),5),0)) | W3: =IF(OR($A3="",V3=0),"",ROUND(U3/V3*100,1)) | X3: =IF($A3="","",IFERROR(INDEX(Papers!$J$2:$J$12,MATCH($C3,Papers!$A$2:$A$12,0)),"")) | Y3: =IF($A3="","",IFERROR(SUMPRODUCT((INDEX(SubMap!$B$2:$AE$12,MATCH($C3,SubMap!$A$2:$A$12,0),0)=6)*Attempts!$AR3:$BU3),0)) | Z3: =IF($A3="","",IFERROR(COUNTIF(INDEX(SubMap!$B$2:$AE$12,MATCH($C3,SubMap!$A$2:$A$12,0),0),6),0)) | AA3: =IF(OR($A3="",Z3=0),"",ROUND(Y3/Z3*100,1)) | AB3: =IF($A3="","",IFERROR(INDEX(CHOOSE({1,2,3,4,5,6},D3,H3,L3,P3,T3,X3),MATCH(MIN(G3,K3,O3,S3,W3,AA3),CHOOSE({1,2,3,4,5,6},G3,K3,O3,S3,W3,AA3),0)),"")) | AC3: =IF($A3="","",IF(COUNT(G3,K3,O3,S3,W3,AA3)=0,"",MIN(G3,K3,O3,S3,W3,AA3))) | AD3: =IF($A3="","",IFERROR(INDEX(CHOOSE({1,2,3,4,5,6},IFERROR(INDEX(Papers!$K$2:$K$12,MATCH($C3,Papers!$A$2:$A$12,0)),""),IFERROR(INDEX(Papers!$L$2:$L$12,MATCH($C3,Papers!$A$2:$A$12,0)),""),IFERROR(INDEX(Papers!$M$2:$M$12,MATCH($C3,Papers!$A$2:$A$12,0)),""),IFERROR(INDEX(Papers!$N$2:$N$12,MATCH($C3,Papers!$A$2:$A$12,0)),""),IFERROR(INDEX(Papers!$O$2:$O$12,MATCH($C3,Papers!$A$2:$A$12,0)),""),IFERROR(INDEX(Papers!$P$2:$P$12,MATCH($C3,Papers!$A$2:$A$12,0)),"")),MATCH(MIN(G3,K3,O3,S3,W3,AA3),CHOOSE({1,2,3,4,5,6},G3,K3,O3,S3,W3,AA3),0)),"")) | AE3: =IF(AC3="","",IF(AC3<50,"Re-teach",IF(AC3<75,"Practice more","Relatively secure")))
A4: =IF(Attempts!A4="","",Attempts!A4) | B4: =IF(Attempts!A4="","",Attempts!B4) | C4: =IF(Attempts!A4="","",Attempts!D4) | D4: =IF($A4="","",IFERROR(INDEX(Papers!$E$2:$E$12,MATCH($C4,Papers!$A$2:$A$12,0)),"")) | E4: =IF($A4="","",IFERROR(SUMPRODUCT((INDEX(SubMap!$B$2:$AE$12,MATCH($C4,SubMap!$A$2:$A$12,0),0)=1)*Attempts!$AR4:$BU4),0)) | F4: =IF($A4="","",IFERROR(COUNTIF(INDEX(SubMap!$B$2:$AE$12,MATCH($C4,SubMap!$A$2:$A$12,0),0),1),0)) | G4: =IF(OR($A4="",F4=0),"",ROUND(E4/F4*100,1)) | H4: =IF($A4="","",IFERROR(INDEX(Papers!$F$2:$F$12,MATCH($C4,Papers!$A$2:$A$12,0)),"")) | I4: =IF($A4="","",IFERROR(SUMPRODUCT((INDEX(SubMap!$B$2:$AE$12,MATCH($C4,SubMap!$A$2:$A$12,0),0)=2)*Attempts!$AR4:$BU4),0)) | J4: =IF($A4="","",IFERROR(COUNTIF(INDEX(SubMap!$B$2:$AE$12,MATCH($C4,SubMap!$A$2:$A$12,0),0),2),0)) | K4: =IF(OR($A4="",J4=0),"",ROUND(I4/J4*100,1)) | L4: =IF($A4="","",IFERROR(INDEX(Papers!$G$2:$G$12,MATCH($C4,Papers!$A$2:$A$12,0)),"")) | M4: =IF($A4="","",IFERROR(SUMPRODUCT((INDEX(SubMap!$B$2:$AE$12,MATCH($C4,SubMap!$A$2:$A$12,0),0)=3)*Attempts!$AR4:$BU4),0)) | N4: =IF($A4="","",IFERROR(COUNTIF(INDEX(SubMap!$B$2:$AE$12,MATCH($C4,SubMap!$A$2:$A$12,0),0),3),0)) | O4: =IF(OR($A4="",N4=0),"",ROUND(M4/N4*100,1)) | P4: =IF($A4="","",IFERROR(INDEX(Papers!$H$2:$H$12,MATCH($C4,Papers!$A$2:$A$12,0)),"")) | Q4: =IF($A4="","",IFERROR(SUMPRODUCT((INDEX(SubMap!$B$2:$AE$12,MATCH($C4,SubMap!$A$2:$A$12,0),0)=4)*Attempts!$AR4:$BU4),0)) | R4: =IF($A4="","",IFERROR(COUNTIF(INDEX(SubMap!$B$2:$AE$12,MATCH($C4,SubMap!$A$2:$A$12,0),0),4),0)) | S4: =IF(OR($A4="",R4=0),"",ROUND(Q4/R4*100,1)) | T4: =IF($A4="","",IFERROR(INDEX(Papers!$I$2:$I$12,MATCH($C4,Papers!$A$2:$A$12,0)),"")) | U4: =IF($A4="","",IFERROR(SUMPRODUCT((INDEX(SubMap!$B$2:$AE$12,MATCH($C4,SubMap!$A$2:$A$12,0),0)=5)*Attempts!$AR4:$BU4),0)) | V4: =IF($A4="","",IFERROR(COUNTIF(INDEX(SubMap!$B$2:$AE$12,MATCH($C4,SubMap!$A$2:$A$12,0),0),5),0)) | W4: =IF(OR($A4="",V4=0),"",ROUND(U4/V4*100,1)) | X4: =IF($A4="","",IFERROR(INDEX(Papers!$J$2:$J$12,MATCH($C4,Papers!$A$2:$A$12,0)),"")) | Y4: =IF($A4="","",IFERROR(SUMPRODUCT((INDEX(SubMap!$B$2:$AE$12,MATCH($C4,SubMap!$A$2:$A$12,0),0)=6)*Attempts!$AR4:$BU4),0)) | Z4: =IF($A4="","",IFERROR(COUNTIF(INDEX(SubMap!$B$2:$AE$12,MATCH($C4,SubMap!$A$2:$A$12,0),0),6),0)) | AA4: =IF(OR($A4="",Z4=0),"",ROUND(Y4/Z4*100,1)) | AB4: =IF($A4="","",IFERROR(INDEX(CHOOSE({1,2,3,4,5,6},D4,H4,L4,P4,T4,X4),MATCH(MIN(G4,K4,O4,S4,W4,AA4),CHOOSE({1,2,3,4,5,6},G4,K4,O4,S4,W4,AA4),0)),"")) | AC4: =IF($A4="","",IF(COUNT(G4,K4,O4,S4,W4,AA4)=0,"",MIN(G4,K4,O4,S4,W4,AA4))) | AD4: =IF($A4="","",IFERROR(INDEX(CHOOSE({1,2,3,4,5,6},IFERROR(INDEX(Papers!$K$2:$K$12,MATCH($C4,Papers!$A$2:$A$12,0)),""),IFERROR(INDEX(Papers!$L$2:$L$12,MATCH($C4,Papers!$A$2:$A$12,0)),""),IFERROR(INDEX(Papers!$M$2:$M$12,MATCH($C4,Papers!$A$2:$A$12,0)),""),IFERROR(INDEX(Papers!$N$2:$N$12,MATCH($C4,Papers!$A$2:$A$12,0)),""),IFERROR(INDEX(Papers!$O$2:$O$12,MATCH($C4,Papers!$A$2:$A$12,0)),""),IFERROR(INDEX(Papers!$P$2:$P$12,MATCH($C4,Papers!$A$2:$A$12,0)),"")),MATCH(MIN(G4,K4,O4,S4,W4,AA4),CHOOSE({1,2,3,4,5,6},G4,K4,O4,S4,W4,AA4),0)),"")) | AE4: =IF(AC4="","",IF(AC4<50,"Re-teach",IF(AC4<75,"Practice more","Relatively secure")))
A5: =IF(Attempts!A5="","",Attempts!A5) | B5: =IF(Attempts!A5="","",Attempts!B5) | C5: =IF(Attempts!A5="","",Attempts!D5) | D5: =IF($A5="","",IFERROR(INDEX(Papers!$E$2:$E$12,MATCH($C5,Papers!$A$2:$A$12,0)),"")) | E5: =IF($A5="","",IFERROR(SUMPRODUCT((INDEX(SubMap!$B$2:$AE$12,MATCH($C5,SubMap!$A$2:$A$12,0),0)=1)*Attempts!$AR5:$BU5),0)) | F5: =IF($A5="","",IFERROR(COUNTIF(INDEX(SubMap!$B$2:$AE$12,MATCH($C5,SubMap!$A$2:$A$12,0),0),1),0)) | G5: =IF(OR($A5="",F5=0),"",ROUND(E5/F5*100,1)) | H5: =IF($A5="","",IFERROR(INDEX(Papers!$F$2:$F$12,MATCH($C5,Papers!$A$2:$A$12,0)),"")) | I5: =IF($A5="","",IFERROR(SUMPRODUCT((INDEX(SubMap!$B$2:$AE$12,MATCH($C5,SubMap!$A$2:$A$12,0),0)=2)*Attempts!$AR5:$BU5),0)) | J5: =IF($A5="","",IFERROR(COUNTIF(INDEX(SubMap!$B$2:$AE$12,MATCH($C5,SubMap!$A$2:$A$12,0),0),2),0)) | K5: =IF(OR($A5="",J5=0),"",ROUND(I5/J5*100,1)) | L5: =IF($A5="","",IFERROR(INDEX(Papers!$G$2:$G$12,MATCH($C5,Papers!$A$2:$A$12,0)),"")) | M5: =IF($A5="","",IFERROR(SUMPRODUCT((INDEX(SubMap!$B$2:$AE$12,MATCH($C5,SubMap!$A$2:$A$12,0),0)=3)*Attempts!$AR5:$BU5),0)) | N5: =IF($A5="","",IFERROR(COUNTIF(INDEX(SubMap!$B$2:$AE$12,MATCH($C5,SubMap!$A$2:$A$12,0),0),3),0)) | O5: =IF(OR($A5="",N5=0),"",ROUND(M5/N5*100,1)) | P5: =IF($A5="","",IFERROR(INDEX(Papers!$H$2:$H$12,MATCH($C5,Papers!$A$2:$A$12,0)),"")) | Q5: =IF($A5="","",IFERROR(SUMPRODUCT((INDEX(SubMap!$B$2:$AE$12,MATCH($C5,SubMap!$A$2:$A$12,0),0)=4)*Attempts!$AR5:$BU5),0)) | R5: =IF($A5="","",IFERROR(COUNTIF(INDEX(SubMap!$B$2:$AE$12,MATCH($C5,SubMap!$A$2:$A$12,0),0),4),0)) | S5: =IF(OR($A5="",R5=0),"",ROUND(Q5/R5*100,1)) | T5: =IF($A5="","",IFERROR(INDEX(Papers!$I$2:$I$12,MATCH($C5,Papers!$A$2:$A$12,0)),"")) | U5: =IF($A5="","",IFERROR(SUMPRODUCT((INDEX(SubMap!$B$2:$AE$12,MATCH($C5,SubMap!$A$2:$A$12,0),0)=5)*Attempts!$AR5:$BU5),0)) | V5: =IF($A5="","",IFERROR(COUNTIF(INDEX(SubMap!$B$2:$AE$12,MATCH($C5,SubMap!$A$2:$A$12,0),0),5),0)) | W5: =IF(OR($A5="",V5=0),"",ROUND(U5/V5*100,1)) | X5: =IF($A5="","",IFERROR(INDEX(Papers!$J$2:$J$12,MATCH($C5,Papers!$A$2:$A$12,0)),"")) | Y5: =IF($A5="","",IFERROR(SUMPRODUCT((INDEX(SubMap!$B$2:$AE$12,MATCH($C5,SubMap!$A$2:$A$12,0),0)=6)*Attempts!$AR5:$BU5),0)) | Z5: =IF($A5="","",IFERROR(COUNTIF(INDEX(SubMap!$B$2:$AE$12,MATCH($C5,SubMap!$A$2:$A$12,0),0),6),0)) | AA5: =IF(OR($A5="",Z5=0),"",ROUND(Y5/Z5*100,1)) | AB5: =IF($A5="","",IFERROR(INDEX(CHOOSE({1,2,3,4,5,6},D5,H5,L5,P5,T5,X5),MATCH(MIN(G5,K5,O5,S5,W5,AA5),CHOOSE({1,2,3,4,5,6},G5,K5,O5,S5,W5,AA5),0)),"")) | AC5: =IF($A5="","",IF(COUNT(G5,K5,O5,S5,W5,AA5)=0,"",MIN(G5,K5,O5,S5,W5,AA5))) | AD5: =IF($A5="","",IFERROR(INDEX(CHOOSE({1,2,3,4,5,6},IFERROR(INDEX(Papers!$K$2:$K$12,MATCH($C5,Papers!$A$2:$A$12,0)),""),IFERROR(INDEX(Papers!$L$2:$L$12,MATCH($C5,Papers!$A$2:$A$12,0)),""),IFERROR(INDEX(Papers!$M$2:$M$12,MATCH($C5,Papers!$A$2:$A$12,0)),""),IFERROR(INDEX(Papers!$N$2:$N$12,MATCH($C5,Papers!$A$2:$A$12,0)),""),IFERROR(INDEX(Papers!$O$2:$O$12,MATCH($C5,Papers!$A$2:$A$12,0)),""),IFERROR(INDEX(Papers!$P$2:$P$12,MATCH($C5,Papers!$A$2:$A$12,0)),"")),MATCH(MIN(G5,K5,O5,S5,W5,AA5),CHOOSE({1,2,3,4,5,6},G5,K5,O5,S5,W5,AA5),0)),"")) | AE5: =IF(AC5="","",IF(AC5<50,"Re-teach",IF(AC5<75,"Practice more","Relatively secure")))
A6: =IF(Attempts!A6="","",Attempts!A6) | B6: =IF(Attempts!A6="","",Attempts!B6) | C6: =IF(Attempts!A6="","",Attempts!D6) | D6: =IF($A6="","",IFERROR(INDEX(Papers!$E$2:$E$12,MATCH($C6,Papers!$A$2:$A$12,0)),"")) | E6: =IF($A6="","",IFERROR(SUMPRODUCT((INDEX(SubMap!$B$2:$AE$12,MATCH($C6,SubMap!$A$2:$A$12,0),0)=1)*Attempts!$AR6:$BU6),0)) | F6: =IF($A6="","",IFERROR(COUNTIF(INDEX(SubMap!$B$2:$AE$12,MATCH($C6,SubMap!$A$2:$A$12,0),0),1),0)) | G6: =IF(OR($A6="",F6=0),"",ROUND(E6/F6*100,1)) | H6: =IF($A6="","",IFERROR(INDEX(Papers!$F$2:$F$12,MATCH($C6,Papers!$A$2:$A$12,0)),"")) | I6: =IF($A6="","",IFERROR(SUMPRODUCT((INDEX(SubMap!$B$2:$AE$12,MATCH($C6,SubMap!$A$2:$A$12,0),0)=2)*Attempts!$AR6:$BU6),0)) | J6: =IF($A6="","",IFERROR(COUNTIF(INDEX(SubMap!$B$2:$AE$12,MATCH($C6,SubMap!$A$2:$A$12,0),0),2),0)) | K6: =IF(OR($A6="",J6=0),"",ROUND(I6/J6*100,1)) | L6: =IF($A6="","",IFERROR(INDEX(Papers!$G$2:$G$12,MATCH($C6,Papers!$A$2:$A$12,0)),"")) | M6: =IF($A6="","",IFERROR(SUMPRODUCT((INDEX(SubMap!$B$2:$AE$12,MATCH($C6,SubMap!$A$2:$A$12,0),0)=3)*Attempts!$AR6:$BU6),0)) | N6: =IF($A6="","",IFERROR(COUNTIF(INDEX(SubMap!$B$2:$AE$12,MATCH($C6,SubMap!$A$2:$A$12,0),0),3),0)) | O6: =IF(OR($A6="",N6=0),"",ROUND(M6/N6*100,1)) | P6: =IF($A6="","",IFERROR(INDEX(Papers!$H$2:$H$12,MATCH($C6,Papers!$A$2:$A$12,0)),"")) | Q6: =IF($A6="","",IFERROR(SUMPRODUCT((INDEX(SubMap!$B$2:$AE$12,MATCH($C6,SubMap!$A$2:$A$12,0),0)=4)*Attempts!$AR6:$BU6),0)) | R6: =IF($A6="","",IFERROR(COUNTIF(INDEX(SubMap!$B$2:$AE$12,MATCH($C6,SubMap!$A$2:$A$12,0),0),4),0)) | S6: =IF(OR($A6="",R6=0),"",ROUND(Q6/R6*100,1)) | T6: =IF($A6="","",IFERROR(INDEX(Papers!$I$2:$I$12,MATCH($C6,Papers!$A$2:$A$12,0)),"")) | U6: =IF($A6="","",IFERROR(SUMPRODUCT((INDEX(SubMap!$B$2:$AE$12,MATCH($C6,SubMap!$A$2:$A$12,0),0)=5)*Attempts!$AR6:$BU6),0)) | V6: =IF($A6="","",IFERROR(COUNTIF(INDEX(SubMap!$B$2:$AE$12,MATCH($C6,SubMap!$A$2:$A$12,0),0),5),0)) | W6: =IF(OR($A6="",V6=0),"",ROUND(U6/V6*100,1)) | X6: =IF($A6="","",IFERROR(INDEX(Papers!$J$2:$J$12,MATCH($C6,Papers!$A$2:$A$12,0)),"")) | Y6: =IF($A6="","",IFERROR(SUMPRODUCT((INDEX(SubMap!$B$2:$AE$12,MATCH($C6,SubMap!$A$2:$A$12,0),0)=6)*Attempts!$AR6:$BU6),0)) | Z6: =IF($A6="","",IFERROR(COUNTIF(INDEX(SubMap!$B$2:$AE$12,MATCH($C6,SubMap!$A$2:$A$12,0),0),6),0)) | AA6: =IF(OR($A6="",Z6=0),"",ROUND(Y6/Z6*100,1)) | AB6: =IF($A6="","",IFERROR(INDEX(CHOOSE({1,2,3,4,5,6},D6,H6,L6,P6,T6,X6),MATCH(MIN(G6,K6,O6,S6,W6,AA6),CHOOSE({1,2,3,4,5,6},G6,K6,O6,S6,W6,AA6),0)),"")) | AC6: =IF($A6="","",IF(COUNT(G6,K6,O6,S6,W6,AA6)=0,"",MIN(G6,K6,O6,S6,W6,AA6))) | AD6: =IF($A6="","",IFERROR(INDEX(CHOOSE({1,2,3,4,5,6},IFERROR(INDEX(Papers!$K$2:$K$12,MATCH($C6,Papers!$A$2:$A$12,0)),""),IFERROR(INDEX(Papers!$L$2:$L$12,MATCH($C6,Papers!$A$2:$A$12,0)),""),IFERROR(INDEX(Papers!$M$2:$M$12,MATCH($C6,Papers!$A$2:$A$12,0)),""),IFERROR(INDEX(Papers!$N$2:$N$12,MATCH($C6,Papers!$A$2:$A$12,0)),""),IFERROR(INDEX(Papers!$O$2:$O$12,MATCH($C6,Papers!$A$2:$A$12,0)),""),IFERROR(INDEX(Papers!$P$2:$P$12,MATCH($C6,Papers!$A$2:$A$12,0)),"")),MATCH(MIN(G6,K6,O6,S6,W6,AA6),CHOOSE({1,2,3,4,5,6},G6,K6,O6,S6,W6,AA6),0)),"")) | AE6: =IF(AC6="","",IF(AC6<50,"Re-teach",IF(AC6<75,"Practice more","Relatively secure")))
A7: =IF(Attempts!A7="","",Attempts!A7) | B7: =IF(Attempts!A7="","",Attempts!B7) | C7: =IF(Attempts!A7="","",Attempts!D7) | D7: =IF($A7="","",IFERROR(INDEX(Papers!$E$2:$E$12,MATCH($C7,Papers!$A$2:$A$12,0)),"")) | E7: =IF($A7="","",IFERROR(SUMPRODUCT((INDEX(SubMap!$B$2:$AE$12,MATCH($C7,SubMap!$A$2:$A$12,0),0)=1)*Attempts!$AR7:$BU7),0)) | F7: =IF($A7="","",IFERROR(COUNTIF(INDEX(SubMap!$B$2:$AE$12,MATCH($C7,SubMap!$A$2:$A$12,0),0),1),0)) | G7: =IF(OR($A7="",F7=0),"",ROUND(E7/F7*100,1)) | H7: =IF($A7="","",IFERROR(INDEX(Papers!$F$2:$F$12,MATCH($C7,Papers!$A$2:$A$12,0)),"")) | I7: =IF($A7="","",IFERROR(SUMPRODUCT((INDEX(SubMap!$B$2:$AE$12,MATCH($C7,SubMap!$A$2:$A$12,0),0)=2)*Attempts!$AR7:$BU7),0)) | J7: =IF($A7="","",IFERROR(COUNTIF(INDEX(SubMap!$B$2:$AE$12,MATCH($C7,SubMap!$A$2:$A$12,0),0),2),0)) | K7: =IF(OR($A7="",J7=0),"",ROUND(I7/J7*100,1)) | L7: =IF($A7="","",IFERROR(INDEX(Papers!$G$2:$G$12,MATCH($C7,Papers!$A$2:$A$12,0)),"")) | M7: =IF($A7="","",IFERROR(SUMPRODUCT((INDEX(SubMap!$B$2:$AE$12,MATCH($C7,SubMap!$A$2:$A$12,0),0)=3)*Attempts!$AR7:$BU7),0)) | N7: =IF($A7="","",IFERROR(COUNTIF(INDEX(SubMap!$B$2:$AE$12,MATCH($C7,SubMap!$A$2:$A$12,0),0),3),0)) | O7: =IF(OR($A7="",N7=0),"",ROUND(M7/N7*100,1)) | P7: =IF($A7="","",IFERROR(INDEX(Papers!$H$2:$H$12,MATCH($C7,Papers!$A$2:$A$12,0)),"")) | Q7: =IF($A7="","",IFERROR(SUMPRODUCT((INDEX(SubMap!$B$2:$AE$12,MATCH($C7,SubMap!$A$2:$A$12,0),0)=4)*Attempts!$AR7:$BU7),0)) | R7: =IF($A7="","",IFERROR(COUNTIF(INDEX(SubMap!$B$2:$AE$12,MATCH($C7,SubMap!$A$2:$A$12,0),0),4),0)) | S7: =IF(OR($A7="",R7=0),"",ROUND(Q7/R7*100,1)) | T7: =IF($A7="","",IFERROR(INDEX(Papers!$I$2:$I$12,MATCH($C7,Papers!$A$2:$A$12,0)),"")) | U7: =IF($A7="","",IFERROR(SUMPRODUCT((INDEX(SubMap!$B$2:$AE$12,MATCH($C7,SubMap!$A$2:$A$12,0),0)=5)*Attempts!$AR7:$BU7),0)) | V7: =IF($A7="","",IFERROR(COUNTIF(INDEX(SubMap!$B$2:$AE$12,MATCH($C7,SubMap!$A$2:$A$12,0),0),5),0)) | W7: =IF(OR($A7="",V7=0),"",ROUND(U7/V7*100,1)) | X7: =IF($A7="","",IFERROR(INDEX(Papers!$J$2:$J$12,MATCH($C7,Papers!$A$2:$A$12,0)),"")) | Y7: =IF($A7="","",IFERROR(SUMPRODUCT((INDEX(SubMap!$B$2:$AE$12,MATCH($C7,SubMap!$A$2:$A$12,0),0)=6)*Attempts!$AR7:$BU7),0)) | Z7: =IF($A7="","",IFERROR(COUNTIF(INDEX(SubMap!$B$2:$AE$12,MATCH($C7,SubMap!$A$2:$A$12,0),0),6),0)) | AA7: =IF(OR($A7="",Z7=0),"",ROUND(Y7/Z7*100,1)) | AB7: =IF($A7="","",IFERROR(INDEX(CHOOSE({1,2,3,4,5,6},D7,H7,L7,P7,T7,X7),MATCH(MIN(G7,K7,O7,S7,W7,AA7),CHOOSE({1,2,3,4,5,6},G7,K7,O7,S7,W7,AA7),0)),"")) | AC7: =IF($A7="","",IF(COUNT(G7,K7,O7,S7,W7,AA7)=0,"",MIN(G7,K7,O7,S7,W7,AA7))) | AD7: =IF($A7="","",IFERROR(INDEX(CHOOSE({1,2,3,4,5,6},IFERROR(INDEX(Papers!$K$2:$K$12,MATCH($C7,Papers!$A$2:$A$12,0)),""),IFERROR(INDEX(Papers!$L$2:$L$12,MATCH($C7,Papers!$A$2:$A$12,0)),""),IFERROR(INDEX(Papers!$M$2:$M$12,MATCH($C7,Papers!$A$2:$A$12,0)),""),IFERROR(INDEX(Papers!$N$2:$N$12,MATCH($C7,Papers!$A$2:$A$12,0)),""),IFERROR(INDEX(Papers!$O$2:$O$12,MATCH($C7,Papers!$A$2:$A$12,0)),""),IFERROR(INDEX(Papers!$P$2:$P$12,MATCH($C7,Papers!$A$2:$A$12,0)),"")),MATCH(MIN(G7,K7,O7,S7,W7,AA7),CHOOSE({1,2,3,4,5,6},G7,K7,O7,S7,W7,AA7),0)),"")) | AE7: =IF(AC7="","",IF(AC7<50,"Re-teach",IF(AC7<75,"Practice more","Relatively secure")))
A8: =IF(Attempts!A8="","",Attempts!A8) | B8: =IF(Attempts!A8="","",Attempts!B8) | C8: =IF(Attempts!A8="","",Attempts!D8) | D8: =IF($A8="","",IFERROR(INDEX(Papers!$E$2:$E$12,MATCH($C8,Papers!$A$2:$A$12,0)),"")) | E8: =IF($A8="","",IFERROR(SUMPRODUCT((INDEX(SubMap!$B$2:$AE$12,MATCH($C8,SubMap!$A$2:$A$12,0),0)=1)*Attempts!$AR8:$BU8),0)) | F8: =IF($A8="","",IFERROR(COUNTIF(INDEX(SubMap!$B$2:$AE$12,MATCH($C8,SubMap!$A$2:$A$12,0),0),1),0)) | G8: =IF(OR($A8="",F8=0),"",ROUND(E8/F8*100,1)) | H8: =IF($A8="","",IFERROR(INDEX(Papers!$F$2:$F$12,MATCH($C8,Papers!$A$2:$A$12,0)),"")) | I8: =IF($A8="","",IFERROR(SUMPRODUCT((INDEX(SubMap!$B$2:$AE$12,MATCH($C8,SubMap!$A$2:$A$12,0),0)=2)*Attempts!$AR8:$BU8),0)) | J8: =IF($A8="","",IFERROR(COUNTIF(INDEX(SubMap!$B$2:$AE$12,MATCH($C8,SubMap!$A$2:$A$12,0),0),2),0)) | K8: =IF(OR($A8="",J8=0),"",ROUND(I8/J8*100,1)) | L8: =IF($A8="","",IFERROR(INDEX(Papers!$G$2:$G$12,MATCH($C8,Papers!$A$2:$A$12,0)),"")) | M8: =IF($A8="","",IFERROR(SUMPRODUCT((INDEX(SubMap!$B$2:$AE$12,MATCH($C8,SubMap!$A$2:$A$12,0),0)=3)*Attempts!$AR8:$BU8),0)) | N8: =IF($A8="","",IFERROR(COUNTIF(INDEX(SubMap!$B$2:$AE$12,MATCH($C8,SubMap!$A$2:$A$12,0),0),3),0)) | O8: =IF(OR($A8="",N8=0),"",ROUND(M8/N8*100,1)) | P8: =IF($A8="","",IFERROR(INDEX(Papers!$H$2:$H$12,MATCH($C8,Papers!$A$2:$A$12,0)),"")) | Q8: =IF($A8="","",IFERROR(SUMPRODUCT((INDEX(SubMap!$B$2:$AE$12,MATCH($C8,SubMap!$A$2:$A$12,0),0)=4)*Attempts!$AR8:$BU8),0)) | R8: =IF($A8="","",IFERROR(COUNTIF(INDEX(SubMap!$B$2:$AE$12,MATCH($C8,SubMap!$A$2:$A$12,0),0),4),0)) | S8: =IF(OR($A8="",R8=0),"",ROUND(Q8/R8*100,1)) | T8: =IF($A8="","",IFERROR(INDEX(Papers!$I$2:$I$12,MATCH($C8,Papers!$A$2:$A$12,0)),"")) | U8: =IF($A8="","",IFERROR(SUMPRODUCT((INDEX(SubMap!$B$2:$AE$12,MATCH($C8,SubMap!$A$2:$A$12,0),0)=5)*Attempts!$AR8:$BU8),0)) | V8: =IF($A8="","",IFERROR(COUNTIF(INDEX(SubMap!$B$2:$AE$12,MATCH($C8,SubMap!$A$2:$A$12,0),0),5),0)) | W8: =IF(OR($A8="",V8=0),"",ROUND(U8/V8*100,1)) | X8: =IF($A8="","",IFERROR(INDEX(Papers!$J$2:$J$12,MATCH($C8,Papers!$A$2:$A$12,0)),"")) | Y8: =IF($A8="","",IFERROR(SUMPRODUCT((INDEX(SubMap!$B$2:$AE$12,MATCH($C8,SubMap!$A$2:$A$12,0),0)=6)*Attempts!$AR8:$BU8),0)) | Z8: =IF($A8="","",IFERROR(COUNTIF(INDEX(SubMap!$B$2:$AE$12,MATCH($C8,SubMap!$A$2:$A$12,0),0),6),0)) | AA8: =IF(OR($A8="",Z8=0),"",ROUND(Y8/Z8*100,1)) | AB8: =IF($A8="","",IFERROR(INDEX(CHOOSE({1,2,3,4,5,6},D8,H8,L8,P8,T8,X8),MATCH(MIN(G8,K8,O8,S8,W8,AA8),CHOOSE({1,2,3,4,5,6},G8,K8,O8,S8,W8,AA8),0)),"")) | AC8: =IF($A8="","",IF(COUNT(G8,K8,O8,S8,W8,AA8)=0,"",MIN(G8,K8,O8,S8,W8,AA8))) | AD8: =IF($A8="","",IFERROR(INDEX(CHOOSE({1,2,3,4,5,6},IFERROR(INDEX(Papers!$K$2:$K$12,MATCH($C8,Papers!$A$2:$A$12,0)),""),IFERROR(INDEX(Papers!$L$2:$L$12,MATCH($C8,Papers!$A$2:$A$12,0)),""),IFERROR(INDEX(Papers!$M$2:$M$12,MATCH($C8,Papers!$A$2:$A$12,0)),""),IFERROR(INDEX(Papers!$N$2:$N$12,MATCH($C8,Papers!$A$2:$A$12,0)),""),IFERROR(INDEX(Papers!$O$2:$O$12,MATCH($C8,Papers!$A$2:$A$12,0)),""),IFERROR(INDEX(Papers!$P$2:$P$12,MATCH($C8,Papers!$A$2:$A$12,0)),"")),MATCH(MIN(G8,K8,O8,S8,W8,AA8),CHOOSE({1,2,3,4,5,6},G8,K8,O8,S8,W8,AA8),0)),"")) | AE8: =IF(AC8="","",IF(AC8<50,"Re-teach",IF(AC8<75,"Practice more","Relatively secure")))
A9: =IF(Attempts!A9="","",Attempts!A9) | B9: =IF(Attempts!A9="","",Attempts!B9) | C9: =IF(Attempts!A9="","",Attempts!D9) | D9: =IF($A9="","",IFERROR(INDEX(Papers!$E$2:$E$12,MATCH($C9,Papers!$A$2:$A$12,0)),"")) | E9: =IF($A9="","",IFERROR(SUMPRODUCT((INDEX(SubMap!$B$2:$AE$12,MATCH($C9,SubMap!$A$2:$A$12,0),0)=1)*Attempts!$AR9:$BU9),0)) | F9: =IF($A9="","",IFERROR(COUNTIF(INDEX(SubMap!$B$2:$AE$12,MATCH($C9,SubMap!$A$2:$A$12,0),0),1),0)) | G9: =IF(OR($A9="",F9=0),"",ROUND(E9/F9*100,1)) | H9: =IF($A9="","",IFERROR(INDEX(Papers!$F$2:$F$12,MATCH($C9,Papers!$A$2:$A$12,0)),"")) | I9: =IF($A9="","",IFERROR(SUMPRODUCT((INDEX(SubMap!$B$2:$AE$12,MATCH($C9,SubMap!$A$2:$A$12,0),0)=2)*Attempts!$AR9:$BU9),0)) | J9: =IF($A9="","",IFERROR(COUNTIF(INDEX(SubMap!$B$2:$AE$12,MATCH($C9,SubMap!$A$2:$A$12,0),0),2),0)) | K9: =IF(OR($A9="",J9=0),"",ROUND(I9/J9*100,1)) | L9: =IF($A9="","",IFERROR(INDEX(Papers!$G$2:$G$12,MATCH($C9,Papers!$A$2:$A$12,0)),"")) | M9: =IF($A9="","",IFERROR(SUMPRODUCT((INDEX(SubMap!$B$2:$AE$12,MATCH($C9,SubMap!$A$2:$A$12,0),0)=3)*Attempts!$AR9:$BU9),0)) | N9: =IF($A9="","",IFERROR(COUNTIF(INDEX(SubMap!$B$2:$AE$12,MATCH($C9,SubMap!$A$2:$A$12,0),0),3),0)) | O9: =IF(OR($A9="",N9=0),"",ROUND(M9/N9*100,1)) | P9: =IF($A9="","",IFERROR(INDEX(Papers!$H$2:$H$12,MATCH($C9,Papers!$A$2:$A$12,0)),"")) | Q9: =IF($A9="","",IFERROR(SUMPRODUCT((INDEX(SubMap!$B$2:$AE$12,MATCH($C9,SubMap!$A$2:$A$12,0),0)=4)*Attempts!$AR9:$BU9),0)) | R9: =IF($A9="","",IFERROR(COUNTIF(INDEX(SubMap!$B$2:$AE$12,MATCH($C9,SubMap!$A$2:$A$12,0),0),4),0)) | S9: =IF(OR($A9="",R9=0),"",ROUND(Q9/R9*100,1)) | T9: =IF($A9="","",IFERROR(INDEX(Papers!$I$2:$I$12,MATCH($C9,Papers!$A$2:$A$12,0)),"")) | U9: =IF($A9="","",IFERROR(SUMPRODUCT((INDEX(SubMap!$B$2:$AE$12,MATCH($C9,SubMap!$A$2:$A$12,0),0)=5)*Attempts!$AR9:$BU9),0)) | V9: =IF($A9="","",IFERROR(COUNTIF(INDEX(SubMap!$B$2:$AE$12,MATCH($C9,SubMap!$A$2:$A$12,0),0),5),0)) | W9: =IF(OR($A9="",V9=0),"",ROUND(U9/V9*100,1)) | X9: =IF($A9="","",IFERROR(INDEX(Papers!$J$2:$J$12,MATCH($C9,Papers!$A$2:$A$12,0)),"")) | Y9: =IF($A9="","",IFERROR(SUMPRODUCT((INDEX(SubMap!$B$2:$AE$12,MATCH($C9,SubMap!$A$2:$A$12,0),0)=6)*Attempts!$AR9:$BU9),0)) | Z9: =IF($A9="","",IFERROR(COUNTIF(INDEX(SubMap!$B$2:$AE$12,MATCH($C9,SubMap!$A$2:$A$12,0),0),6),0)) | AA9: =IF(OR($A9="",Z9=0),"",ROUND(Y9/Z9*100,1)) | AB9: =IF($A9="","",IFERROR(INDEX(CHOOSE({1,2,3,4,5,6},D9,H9,L9,P9,T9,X9),MATCH(MIN(G9,K9,O9,S9,W9,AA9),CHOOSE({1,2,3,4,5,6},G9,K9,O9,S9,W9,AA9),0)),"")) | AC9: =IF($A9="","",IF(COUNT(G9,K9,O9,S9,W9,AA9)=0,"",MIN(G9,K9,O9,S9,W9,AA9))) | AD9: =IF($A9="","",IFERROR(INDEX(CHOOSE({1,2,3,4,5,6},IFERROR(INDEX(Papers!$K$2:$K$12,MATCH($C9,Papers!$A$2:$A$12,0)),""),IFERROR(INDEX(Papers!$L$2:$L$12,MATCH($C9,Papers!$A$2:$A$12,0)),""),IFERROR(INDEX(Papers!$M$2:$M$12,MATCH($C9,Papers!$A$2:$A$12,0)),""),IFERROR(INDEX(Papers!$N$2:$N$12,MATCH($C9,Papers!$A$2:$A$12,0)),""),IFERROR(INDEX(Papers!$O$2:$O$12,MATCH($C9,Papers!$A$2:$A$12,0)),""),IFERROR(INDEX(Papers!$P$2:$P$12,MATCH($C9,Papers!$A$2:$A$12,0)),"")),MATCH(MIN(G9,K9,O9,S9,W9,AA9),CHOOSE({1,2,3,4,5,6},G9,K9,O9,S9,W9,AA9),0)),"")) | AE9: =IF(AC9="","",IF(AC9<50,"Re-teach",IF(AC9<75,"Practice more","Relatively secure")))
A10: =IF(Attempts!A10="","",Attempts!A10) | B10: =IF(Attempts!A10="","",Attempts!B10) | C10: =IF(Attempts!A10="","",Attempts!D10) | D10: =IF($A10="","",IFERROR(INDEX(Papers!$E$2:$E$12,MATCH($C10,Papers!$A$2:$A$12,0)),"")) | E10: =IF($A10="","",IFERROR(SUMPRODUCT((INDEX(SubMap!$B$2:$AE$12,MATCH($C10,SubMap!$A$2:$A$12,0),0)=1)*Attempts!$AR10:$BU10),0)) | F10: =IF($A10="","",IFERROR(COUNTIF(INDEX(SubMap!$B$2:$AE$12,MATCH($C10,SubMap!$A$2:$A$12,0),0),1),0)) | G10: =IF(OR($A10="",F10=0),"",ROUND(E10/F10*100,1)) | H10: =IF($A10="","",IFERROR(INDEX(Papers!$F$2:$F$12,MATCH($C10,Papers!$A$2:$A$12,0)),"")) | I10: =IF($A10="","",IFERROR(SUMPRODUCT((INDEX(SubMap!$B$2:$AE$12,MATCH($C10,SubMap!$A$2:$A$12,0),0)=2)*Attempts!$AR10:$BU10),0)) | J10: =IF($A10="","",IFERROR(COUNTIF(INDEX(SubMap!$B$2:$AE$12,MATCH($C10,SubMap!$A$2:$A$12,0),0),2),0)) | K10: =IF(OR($A10="",J10=0),"",ROUND(I10/J10*100,1)) | L10: =IF($A10="","",IFERROR(INDEX(Papers!$G$2:$G$12,MATCH($C10,Papers!$A$2:$A$12,0)),"")) | M10: =IF($A10="","",IFERROR(SUMPRODUCT((INDEX(SubMap!$B$2:$AE$12,MATCH($C10,SubMap!$A$2:$A$12,0),0)=3)*Attempts!$AR10:$BU10),0)) | N10: =IF($A10="","",IFERROR(COUNTIF(INDEX(SubMap!$B$2:$AE$12,MATCH($C10,SubMap!$A$2:$A$12,0),0),3),0)) | O10: =IF(OR($A10="",N10=0),"",ROUND(M10/N10*100,1)) | P10: =IF($A10="","",IFERROR(INDEX(Papers!$H$2:$H$12,MATCH($C10,Papers!$A$2:$A$12,0)),"")) | Q10: =IF($A10="","",IFERROR(SUMPRODUCT((INDEX(SubMap!$B$2:$AE$12,MATCH($C10,SubMap!$A$2:$A$12,0),0)=4)*Attempts!$AR10:$BU10),0)) | R10: =IF($A10="","",IFERROR(COUNTIF(INDEX(SubMap!$B$2:$AE$12,MATCH($C10,SubMap!$A$2:$A$12,0),0),4),0)) | S10: =IF(OR($A10="",R10=0),"",ROUND(Q10/R10*100,1)) | T10: =IF($A10="","",IFERROR(INDEX(Papers!$I$2:$I$12,MATCH($C10,Papers!$A$2:$A$12,0)),"")) | U10: =IF($A10="","",IFERROR(SUMPRODUCT((INDEX(SubMap!$B$2:$AE$12,MATCH($C10,SubMap!$A$2:$A$12,0),0)=5)*Attempts!$AR10:$BU10),0)) | V10: =IF($A10="","",IFERROR(COUNTIF(INDEX(SubMap!$B$2:$AE$12,MATCH($C10,SubMap!$A$2:$A$12,0),0),5),0)) | W10: =IF(OR($A10="",V10=0),"",ROUND(U10/V10*100,1)) | X10: =IF($A10="","",IFERROR(INDEX(Papers!$J$2:$J$12,MATCH($C10,Papers!$A$2:$A$12,0)),"")) | Y10: =IF($A10="","",IFERROR(SUMPRODUCT((INDEX(SubMap!$B$2:$AE$12,MATCH($C10,SubMap!$A$2:$A$12,0),0)=6)*Attempts!$AR10:$BU10),0)) | Z10: =IF($A10="","",IFERROR(COUNTIF(INDEX(SubMap!$B$2:$AE$12,MATCH($C10,SubMap!$A$2:$A$12,0),0),6),0)) | AA10: =IF(OR($A10="",Z10=0),"",ROUND(Y10/Z10*100,1)) | AB10: =IF($A10="","",IFERROR(INDEX(CHOOSE({1,2,3,4,5,6},D10,H10,L10,P10,T10,X10),MATCH(MIN(G10,K10,O10,S10,W10,AA10),CHOOSE({1,2,3,4,5,6},G10,K10,O10,S10,W10,AA10),0)),"")) | AC10: =IF($A10="","",IF(COUNT(G10,K10,O10,S10,W10,AA10)=0,"",MIN(G10,K10,O10,S10,W10,AA10))) | AD10: =IF($A10="","",IFERROR(INDEX(CHOOSE({1,2,3,4,5,6},IFERROR(INDEX(Papers!$K$2:$K$12,MATCH($C10,Papers!$A$2:$A$12,0)),""),IFERROR(INDEX(Papers!$L$2:$L$12,MATCH($C10,Papers!$A$2:$A$12,0)),""),IFERROR(INDEX(Papers!$M$2:$M$12,MATCH($C10,Papers!$A$2:$A$12,0)),""),IFERROR(INDEX(Papers!$N$2:$N$12,MATCH($C10,Papers!$A$2:$A$12,0)),""),IFERROR(INDEX(Papers!$O$2:$O$12,MATCH($C10,Papers!$A$2:$A$12,0)),""),IFERROR(INDEX(Papers!$P$2:$P$12,MATCH($C10,Papers!$A$2:$A$12,0)),"")),MATCH(MIN(G10,K10,O10,S10,W10,AA10),CHOOSE({1,2,3,4,5,6},G10,K10,O10,S10,W10,AA10),0)),"")) | AE10: =IF(AC10="","",IF(AC10<50,"Re-teach",IF(AC10<75,"Practice more","Relatively secure")))
A11: =IF(Attempts!A11="","",Attempts!A11) | B11: =IF(Attempts!A11="","",Attempts!B11) | C11: =IF(Attempts!A11="","",Attempts!D11) | D11: =IF($A11="","",IFERROR(INDEX(Papers!$E$2:$E$12,MATCH($C11,Papers!$A$2:$A$12,0)),"")) | E11: =IF($A11="","",IFERROR(SUMPRODUCT((INDEX(SubMap!$B$2:$AE$12,MATCH($C11,SubMap!$A$2:$A$12,0),0)=1)*Attempts!$AR11:$BU11),0)) | F11: =IF($A11="","",IFERROR(COUNTIF(INDEX(SubMap!$B$2:$AE$12,MATCH($C11,SubMap!$A$2:$A$12,0),0),1),0)) | G11: =IF(OR($A11="",F11=0),"",ROUND(E11/F11*100,1)) | H11: =IF($A11="","",IFERROR(INDEX(Papers!$F$2:$F$12,MATCH($C11,Papers!$A$2:$A$12,0)),"")) | I11: =IF($A11="","",IFERROR(SUMPRODUCT((INDEX(SubMap!$B$2:$AE$12,MATCH($C11,SubMap!$A$2:$A$12,0),0)=2)*Attempts!$AR11:$BU11),0)) | J11: =IF($A11="","",IFERROR(COUNTIF(INDEX(SubMap!$B$2:$AE$12,MATCH($C11,SubMap!$A$2:$A$12,0),0),2),0)) | K11: =IF(OR($A11="",J11=0),"",ROUND(I11/J11*100,1)) | L11: =IF($A11="","",IFERROR(INDEX(Papers!$G$2:$G$12,MATCH($C11,Papers!$A$2:$A$12,0)),"")) | M11: =IF($A11="","",IFERROR(SUMPRODUCT((INDEX(SubMap!$B$2:$AE$12,MATCH($C11,SubMap!$A$2:$A$12,0),0)=3)*Attempts!$AR11:$BU11),0)) | N11: =IF($A11="","",IFERROR(COUNTIF(INDEX(SubMap!$B$2:$AE$12,MATCH($C11,SubMap!$A$2:$A$12,0),0),3),0)) | O11: =IF(OR($A11="",N11=0),"",ROUND(M11/N11*100,1)) | P11: =IF($A11="","",IFERROR(INDEX(Papers!$H$2:$H$12,MATCH($C11,Papers!$A$2:$A$12,0)),"")) | Q11: =IF($A11="","",IFERROR(SUMPRODUCT((INDEX(SubMap!$B$2:$AE$12,MATCH($C11,SubMap!$A$2:$A$12,0),0)=4)*Attempts!$AR11:$BU11),0)) | R11: =IF($A11="","",IFERROR(COUNTIF(INDEX(SubMap!$B$2:$AE$12,MATCH($C11,SubMap!$A$2:$A$12,0),0),4),0)) | S11: =IF(OR($A11="",R11=0),"",ROUND(Q11/R11*100,1)) | T11: =IF($A11="","",IFERROR(INDEX(Papers!$I$2:$I$12,MATCH($C11,Papers!$A$2:$A$12,0)),"")) | U11: =IF($A11="","",IFERROR(SUMPRODUCT((INDEX(SubMap!$B$2:$AE$12,MATCH($C11,SubMap!$A$2:$A$12,0),0)=5)*Attempts!$AR11:$BU11),0)) | V11: =IF($A11="","",IFERROR(COUNTIF(INDEX(SubMap!$B$2:$AE$12,MATCH($C11,SubMap!$A$2:$A$12,0),0),5),0)) | W11: =IF(OR($A11="",V11=0),"",ROUND(U11/V11*100,1)) | X11: =IF($A11="","",IFERROR(INDEX(Papers!$J$2:$J$12,MATCH($C11,Papers!$A$2:$A$12,0)),"")) | Y11: =IF($A11="","",IFERROR(SUMPRODUCT((INDEX(SubMap!$B$2:$AE$12,MATCH($C11,SubMap!$A$2:$A$12,0),0)=6)*Attempts!$AR11:$BU11),0)) | Z11: =IF($A11="","",IFERROR(COUNTIF(INDEX(SubMap!$B$2:$AE$12,MATCH($C11,SubMap!$A$2:$A$12,0),0),6),0)) | AA11: =IF(OR($A11="",Z11=0),"",ROUND(Y11/Z11*100,1)) | AB11: =IF($A11="","",IFERROR(INDEX(CHOOSE({1,2,3,4,5,6},D11,H11,L11,P11,T11,X11),MATCH(MIN(G11,K11,O11,S11,W11,AA11),CHOOSE({1,2,3,4,5,6},G11,K11,O11,S11,W11,AA11),0)),"")) | AC11: =IF($A11="","",IF(COUNT(G11,K11,O11,S11,W11,AA11)=0,"",MIN(G11,K11,O11,S11,W11,AA11))) | AD11: =IF($A11="","",IFERROR(INDEX(CHOOSE({1,2,3,4,5,6},IFERROR(INDEX(Papers!$K$2:$K$12,MATCH($C11,Papers!$A$2:$A$12,0)),""),IFERROR(INDEX(Papers!$L$2:$L$12,MATCH($C11,Papers!$A$2:$A$12,0)),""),IFERROR(INDEX(Papers!$M$2:$M$12,MATCH($C11,Papers!$A$2:$A$12,0)),""),IFERROR(INDEX(Papers!$N$2:$N$12,MATCH($C11,Papers!$A$2:$A$12,0)),""),IFERROR(INDEX(Papers!$O$2:$O$12,MATCH($C11,Papers!$A$2:$A$12,0)),""),IFERROR(INDEX(Papers!$P$2:$P$12,MATCH($C11,Papers!$A$2:$A$12,0)),"")),MATCH(MIN(G11,K11,O11,S11,W11,AA11),CHOOSE({1,2,3,4,5,6},G11,K11,O11,S11,W11,AA11),0)),"")) | AE11: =IF(AC11="","",IF(AC11<50,"Re-teach",IF(AC11<75,"Practice more","Relatively secure")))
A12: =IF(Attempts!A12="","",Attempts!A12) | B12: =IF(Attempts!A12="","",Attempts!B12) | C12: =IF(Attempts!A12="","",Attempts!D12) | D12: =IF($A12="","",IFERROR(INDEX(Papers!$E$2:$E$12,MATCH($C12,Papers!$A$2:$A$12,0)),"")) | E12: =IF($A12="","",IFERROR(SUMPRODUCT((INDEX(SubMap!$B$2:$AE$12,MATCH($C12,SubMap!$A$2:$A$12,0),0)=1)*Attempts!$AR12:$BU12),0)) | F12: =IF($A12="","",IFERROR(COUNTIF(INDEX(SubMap!$B$2:$AE$12,MATCH($C12,SubMap!$A$2:$A$12,0),0),1),0)) | G12: =IF(OR($A12="",F12=0),"",ROUND(E12/F12*100,1)) | H12: =IF($A12="","",IFERROR(INDEX(Papers!$F$2:$F$12,MATCH($C12,Papers!$A$2:$A$12,0)),"")) | I12: =IF($A12="","",IFERROR(SUMPRODUCT((INDEX(SubMap!$B$2:$AE$12,MATCH($C12,SubMap!$A$2:$A$12,0),0)=2)*Attempts!$AR12:$BU12),0)) | J12: =IF($A12="","",IFERROR(COUNTIF(INDEX(SubMap!$B$2:$AE$12,MATCH($C12,SubMap!$A$2:$A$12,0),0),2),0)) | K12: =IF(OR($A12="",J12=0),"",ROUND(I12/J12*100,1)) | L12: =IF($A12="","",IFERROR(INDEX(Papers!$G$2:$G$12,MATCH($C12,Papers!$A$2:$A$12,0)),"")) | M12: =IF($A12="","",IFERROR(SUMPRODUCT((INDEX(SubMap!$B$2:$AE$12,MATCH($C12,SubMap!$A$2:$A$12,0),0)=3)*Attempts!$AR12:$BU12),0)) | N12: =IF($A12="","",IFERROR(COUNTIF(INDEX(SubMap!$B$2:$AE$12,MATCH($C12,SubMap!$A$2:$A$12,0),0),3),0)) | O12: =IF(OR($A12="",N12=0),"",ROUND(M12/N12*100,1)) | P12: =IF($A12="","",IFERROR(INDEX(Papers!$H$2:$H$12,MATCH($C12,Papers!$A$2:$A$12,0)),"")) | Q12: =IF($A12="","",IFERROR(SUMPRODUCT((INDEX(SubMap!$B$2:$AE$12,MATCH($C12,SubMap!$A$2:$A$12,0),0)=4)*Attempts!$AR12:$BU12),0)) | R12: =IF($A12="","",IFERROR(COUNTIF(INDEX(SubMap!$B$2:$AE$12,MATCH($C12,SubMap!$A$2:$A$12,0),0),4),0)) | S12: =IF(OR($A12="",R12=0),"",ROUND(Q12/R12*100,1)) | T12: =IF($A12="","",IFERROR(INDEX(Papers!$I$2:$I$12,MATCH($C12,Papers!$A$2:$A$12,0)),"")) | U12: =IF($A12="","",IFERROR(SUMPRODUCT((INDEX(SubMap!$B$2:$AE$12,MATCH($C12,SubMap!$A$2:$A$12,0),0)=5)*Attempts!$AR12:$BU12),0)) | V12: =IF($A12="","",IFERROR(COUNTIF(INDEX(SubMap!$B$2:$AE$12,MATCH($C12,SubMap!$A$2:$A$12,0),0),5),0)) | W12: =IF(OR($A12="",V12=0),"",ROUND(U12/V12*100,1)) | X12: =IF($A12="","",IFERROR(INDEX(Papers!$J$2:$J$12,MATCH($C12,Papers!$A$2:$A$12,0)),"")) | Y12: =IF($A12="","",IFERROR(SUMPRODUCT((INDEX(SubMap!$B$2:$AE$12,MATCH($C12,SubMap!$A$2:$A$12,0),0)=6)*Attempts!$AR12:$BU12),0)) | Z12: =IF($A12="","",IFERROR(COUNTIF(INDEX(SubMap!$B$2:$AE$12,MATCH($C12,SubMap!$A$2:$A$12,0),0),6),0)) | AA12: =IF(OR($A12="",Z12=0),"",ROUND(Y12/Z12*100,1)) | AB12: =IF($A12="","",IFERROR(INDEX(CHOOSE({1,2,3,4,5,6},D12,H12,L12,P12,T12,X12),MATCH(MIN(G12,K12,O12,S12,W12,AA12),CHOOSE({1,2,3,4,5,6},G12,K12,O12,S12,W12,AA12),0)),"")) | AC12: =IF($A12="","",IF(COUNT(G12,K12,O12,S12,W12,AA12)=0,"",MIN(G12,K12,O12,S12,W12,AA12))) | AD12: =IF($A12="","",IFERROR(INDEX(CHOOSE({1,2,3,4,5,6},IFERROR(INDEX(Papers!$K$2:$K$12,MATCH($C12,Papers!$A$2:$A$12,0)),""),IFERROR(INDEX(Papers!$L$2:$L$12,MATCH($C12,Papers!$A$2:$A$12,0)),""),IFERROR(INDEX(Papers!$M$2:$M$12,MATCH($C12,Papers!$A$2:$A$12,0)),""),IFERROR(INDEX(Papers!$N$2:$N$12,MATCH($C12,Papers!$A$2:$A$12,0)),""),IFERROR(INDEX(Papers!$O$2:$O$12,MATCH($C12,Papers!$A$2:$A$12,0)),""),IFERROR(INDEX(Papers!$P$2:$P$12,MATCH($C12,Papers!$A$2:$A$12,0)),"")),MATCH(MIN(G12,K12,O12,S12,W12,AA12),CHOOSE({1,2,3,4,5,6},G12,K12,O12,S12,W12,AA12),0)),"")) | AE12: =IF(AC12="","",IF(AC12<50,"Re-teach",IF(AC12<75,"Practice more","Relatively secure")))
A13: =IF(Attempts!A13="","",Attempts!A13) | B13: =IF(Attempts!A13="","",Attempts!B13) | C13: =IF(Attempts!A13="","",Attempts!D13) | D13: =IF($A13="","",IFERROR(INDEX(Papers!$E$2:$E$12,MATCH($C13,Papers!$A$2:$A$12,0)),"")) | E13: =IF($A13="","",IFERROR(SUMPRODUCT((INDEX(SubMap!$B$2:$AE$12,MATCH($C13,SubMap!$A$2:$A$12,0),0)=1)*Attempts!$AR13:$BU13),0)) | F13: =IF($A13="","",IFERROR(COUNTIF(INDEX(SubMap!$B$2:$AE$12,MATCH($C13,SubMap!$A$2:$A$12,0),0),1),0)) | G13: =IF(OR($A13="",F13=0),"",ROUND(E13/F13*100,1)) | H13: =IF($A13="","",IFERROR(INDEX(Papers!$F$2:$F$12,MATCH($C13,Papers!$A$2:$A$12,0)),"")) | I13: =IF($A13="","",IFERROR(SUMPRODUCT((INDEX(SubMap!$B$2:$AE$12,MATCH($C13,SubMap!$A$2:$A$12,0),0)=2)*Attempts!$AR13:$BU13),0)) | J13: =IF($A13="","",IFERROR(COUNTIF(INDEX(SubMap!$B$2:$AE$12,MATCH($C13,SubMap!$A$2:$A$12,0),0),2),0)) | K13: =IF(OR($A13="",J13=0),"",ROUND(I13/J13*100,1)) | L13: =IF($A13="","",IFERROR(INDEX(Papers!$G$2:$G$12,MATCH($C13,Papers!$A$2:$A$12,0)),"")) | M13: =IF($A13="","",IFERROR(SUMPRODUCT((INDEX(SubMap!$B$2:$AE$12,MATCH($C13,SubMap!$A$2:$A$12,0),0)=3)*Attempts!$AR13:$BU13),0)) | N13: =IF($A13="","",IFERROR(COUNTIF(INDEX(SubMap!$B$2:$AE$12,MATCH($C13,SubMap!$A$2:$A$12,0),0),3),0)) | O13: =IF(OR($A13="",N13=0),"",ROUND(M13/N13*100,1)) | P13: =IF($A13="","",IFERROR(INDEX(Papers!$H$2:$H$12,MATCH($C13,Papers!$A$2:$A$12,0)),"")) | Q13: =IF($A13="","",IFERROR(SUMPRODUCT((INDEX(SubMap!$B$2:$AE$12,MATCH($C13,SubMap!$A$2:$A$12,0),0)=4)*Attempts!$AR13:$BU13),0)) | R13: =IF($A13="","",IFERROR(COUNTIF(INDEX(SubMap!$B$2:$AE$12,MATCH($C13,SubMap!$A$2:$A$12,0),0),4),0)) | S13: =IF(OR($A13="",R13=0),"",ROUND(Q13/R13*100,1)) | T13: =IF($A13="","",IFERROR(INDEX(Papers!$I$2:$I$12,MATCH($C13,Papers!$A$2:$A$12,0)),"")) | U13: =IF($A13="","",IFERROR(SUMPRODUCT((INDEX(SubMap!$B$2:$AE$12,MATCH($C13,SubMap!$A$2:$A$12,0),0)=5)*Attempts!$AR13:$BU13),0)) | V13: =IF($A13="","",IFERROR(COUNTIF(INDEX(SubMap!$B$2:$AE$12,MATCH($C13,SubMap!$A$2:$A$12,0),0),5),0)) | W13: =IF(OR($A13="",V13=0),"",ROUND(U13/V13*100,1)) | X13: =IF($A13="","",IFERROR(INDEX(Papers!$J$2:$J$12,MATCH($C13,Papers!$A$2:$A$12,0)),"")) | Y13: =IF($A13="","",IFERROR(SUMPRODUCT((INDEX(SubMap!$B$2:$AE$12,MATCH($C13,SubMap!$A$2:$A$12,0),0)=6)*Attempts!$AR13:$BU13),0)) | Z13: =IF($A13="","",IFERROR(COUNTIF(INDEX(SubMap!$B$2:$AE$12,MATCH($C13,SubMap!$A$2:$A$12,0),0),6),0)) | AA13: =IF(OR($A13="",Z13=0),"",ROUND(Y13/Z13*100,1)) | AB13: =IF($A13="","",IFERROR(INDEX(CHOOSE({1,2,3,4,5,6},D13,H13,L13,P13,T13,X13),MATCH(MIN(G13,K13,O13,S13,W13,AA13),CHOOSE({1,2,3,4,5,6},G13,K13,O13,S13,W13,AA13),0)),"")) | AC13: =IF($A13="","",IF(COUNT(G13,K13,O13,S13,W13,AA13)=0,"",MIN(G13,K13,O13,S13,W13,AA13))) | AD13: =IF($A13="","",IFERROR(INDEX(CHOOSE({1,2,3,4,5,6},IFERROR(INDEX(Papers!$K$2:$K$12,MATCH($C13,Papers!$A$2:$A$12,0)),""),IFERROR(INDEX(Papers!$L$2:$L$12,MATCH($C13,Papers!$A$2:$A$12,0)),""),IFERROR(INDEX(Papers!$M$2:$M$12,MATCH($C13,Papers!$A$2:$A$12,0)),""),IFERROR(INDEX(Papers!$N$2:$N$12,MATCH($C13,Papers!$A$2:$A$12,0)),""),IFERROR(INDEX(Papers!$O$2:$O$12,MATCH($C13,Papers!$A$2:$A$12,0)),""),IFERROR(INDEX(Papers!$P$2:$P$12,MATCH($C13,Papers!$A$2:$A$12,0)),"")),MATCH(MIN(G13,K13,O13,S13,W13,AA13),CHOOSE({1,2,3,4,5,6},G13,K13,O13,S13,W13,AA13),0)),"")) | AE13: =IF(AC13="","",IF(AC13<50,"Re-teach",IF(AC13<75,"Practice more","Relatively secure")))
... A200: =IF(Attempts!A200="","",Attempts!A200) | B200: =IF(Attempts!A200="","",Attempts!B200) | C200: =IF(Attempts!A200="","",Attempts!D200) | D200: =IF($A200="","",IFERROR(INDEX(Papers!$E$2:$E$12,MATCH($C200,Papers!$A$2:$A$12,0)),"")) | E200: =IF($A200="","",IFERROR(SUMPRODUCT((INDEX(SubMap!$B$2:$AE$12,MATCH($C200,SubMap!$A$2:$A$12,0),0)=1)*Attempts!$AR200:$BU200),0)) | F200: =IF($A200="","",IFERROR(COUNTIF(INDEX(SubMap!$B$2:$AE$12,MATCH($C200,SubMap!$A$2:$A$12,0),0),1),0)) | G200: =IF(OR($A200="",F200=0),"",ROUND(E200/F200*100,1)) | H200: =IF($A200="","",IFERROR(INDEX(Papers!$F$2:$F$12,MATCH($C200,Papers!$A$2:$A$12,0)),"")) | I200: =IF($A200="","",IFERROR(SUMPRODUCT((INDEX(SubMap!$B$2:$AE$12,MATCH($C200,SubMap!$A$2:$A$12,0),0)=2)*Attempts!$AR200:$BU200),0)) | J200: =IF($A200="","",IFERROR(COUNTIF(INDEX(SubMap!$B$2:$AE$12,MATCH($C200,SubMap!$A$2:$A$12,0),0),2),0)) | K200: =IF(OR($A200="",J200=0),"",ROUND(I200/J200*100,1)) | L200: =IF($A200="","",IFERROR(INDEX(Papers!$G$2:$G$12,MATCH($C200,Papers!$A$2:$A$12,0)),"")) | M200: =IF($A200="","",IFERROR(SUMPRODUCT((INDEX(SubMap!$B$2:$AE$12,MATCH($C200,SubMap!$A$2:$A$12,0),0)=3)*Attempts!$AR200:$BU200),0)) | N200: =IF($A200="","",IFERROR(COUNTIF(INDEX(SubMap!$B$2:$AE$12,MATCH($C200,SubMap!$A$2:$A$12,0),0),3),0)) | O200: =IF(OR($A200="",N200=0),"",ROUND(M200/N200*100,1)) | P200: =IF($A200="","",IFERROR(INDEX(Papers!$H$2:$H$12,MATCH($C200,Papers!$A$2:$A$12,0)),"")) | Q200: =IF($A200="","",IFERROR(SUMPRODUCT((INDEX(SubMap!$B$2:$AE$12,MATCH($C200,SubMap!$A$2:$A$12,0),0)=4)*Attempts!$AR200:$BU200),0)) | R200: =IF($A200="","",IFERROR(COUNTIF(INDEX(SubMap!$B$2:$AE$12,MATCH($C200,SubMap!$A$2:$A$12,0),0),4),0)) | S200: =IF(OR($A200="",R200=0),"",ROUND(Q200/R200*100,1)) | T200: =IF($A200="","",IFERROR(INDEX(Papers!$I$2:$I$12,MATCH($C200,Papers!$A$2:$A$12,0)),"")) | U200: =IF($A200="","",IFERROR(SUMPRODUCT((INDEX(SubMap!$B$2:$AE$12,MATCH($C200,SubMap!$A$2:$A$12,0),0)=5)*Attempts!$AR200:$BU200),0)) | V200: =IF($A200="","",IFERROR(COUNTIF(INDEX(SubMap!$B$2:$AE$12,MATCH($C200,SubMap!$A$2:$A$12,0),0),5),0)) | W200: =IF(OR($A200="",V200=0),"",ROUND(U200/V200*100,1)) | X200: =IF($A200="","",IFERROR(INDEX(Papers!$J$2:$J$12,MATCH($C200,Papers!$A$2:$A$12,0)),"")) | Y200: =IF($A200="","",IFERROR(SUMPRODUCT((INDEX(SubMap!$B$2:$AE$12,MATCH($C200,SubMap!$A$2:$A$12,0),0)=6)*Attempts!$AR200:$BU200),0)) | Z200: =IF($A200="","",IFERROR(COUNTIF(INDEX(SubMap!$B$2:$AE$12,MATCH($C200,SubMap!$A$2:$A$12,0),0),6),0)) | AA200: =IF(OR($A200="",Z200=0),"",ROUND(Y200/Z200*100,1)) | AB200: =IF($A200="","",IFERROR(INDEX(CHOOSE({1,2,3,4,5,6},D200,H200,L200,P200,T200,X200),MATCH(MIN(G200,K200,O200,S200,W200,AA200),CHOOSE({1,2,3,4,5,6},G200,K200,O200,S200,W200,AA200),0)),"")) | AC200: =IF($A200="","",IF(COUNT(G200,K200,O200,S200,W200,AA200)=0,"",MIN(G200,K200,O200,S200,W200,AA200))) | AD200: =IF($A200="","",IFERROR(INDEX(CHOOSE({1,2,3,4,5,6},IFERROR(INDEX(Papers!$K$2:$K$12,MATCH($C200,Papers!$A$2:$A$12,0)),""),IFERROR(INDEX(Papers!$L$2:$L$12,MATCH($C200,Papers!$A$2:$A$12,0)),""),IFERROR(INDEX(Papers!$M$2:$M$12,MATCH($C200,Papers!$A$2:$A$12,0)),""),IFERROR(INDEX(Papers!$N$2:$N$12,MATCH($C200,Papers!$A$2:$A$12,0)),""),IFERROR(INDEX(Papers!$O$2:$O$12,MATCH($C200,Papers!$A$2:$A$12,0)),""),IFERROR(INDEX(Papers!$P$2:$P$12,MATCH($C200,Papers!$A$2:$A$12,0)),"")),MATCH(MIN(G200,K200,O200,S200,W200,AA200),CHOOSE({1,2,3,4,5,6},G200,K200,O200,S200,W200,AA200),0)),"")) | AE200: =IF(AC200="","",IF(AC200<50,"Re-teach",IF(AC200<75,"Practice more","Relatively secure")))

Sheet Error_Log
A1: Attempt ID | B1: Q No | C1: Paper | D1: Candidate answer | E1: Correct answer | F1: Subtopic | G1: Error category | H1: Recommended remedial lesson | I1: Tutor note | J1: Remedial lesson done? (Y/N)
C2: =IF(A2="","",IFERROR(INDEX(Attempts!$D$2:$D$200,MATCH(A2,Attempts!$A$2:$A$200,0)),"?")) | D2: =IF(OR(A2="",B2=""),"",IFERROR(INDEX(Attempts!$M$2:$AP$200,MATCH(A2,Attempts!$A$2:$A$200,0),B2),"")) | E2: =IF(OR(C2="",B2=""),"",IFERROR(INDEX(Key!$C$2:$C$263,MATCH(C2*100+B2,Key!$G$2:$G$263,0)),"")) | F2: =IF(OR(C2="",B2=""),"",IFERROR(INDEX(Key!$E$2:$E$263,MATCH(C2*100+B2,Key!$G$2:$G$263,0)),"")) | H2: =IF(OR(C2="",B2=""),"",IFERROR(INDEX(Papers!$K$2:$P$12,MATCH(C2,Papers!$A$2:$A$12,0),INDEX(Key!$D$2:$D$263,MATCH(C2*100+B2,Key!$G$2:$G$263,0))),""))
C3: =IF(A3="","",IFERROR(INDEX(Attempts!$D$2:$D$200,MATCH(A3,Attempts!$A$2:$A$200,0)),"?")) | D3: =IF(OR(A3="",B3=""),"",IFERROR(INDEX(Attempts!$M$2:$AP$200,MATCH(A3,Attempts!$A$2:$A$200,0),B3),"")) | E3: =IF(OR(C3="",B3=""),"",IFERROR(INDEX(Key!$C$2:$C$263,MATCH(C3*100+B3,Key!$G$2:$G$263,0)),"")) | F3: =IF(OR(C3="",B3=""),"",IFERROR(INDEX(Key!$E$2:$E$263,MATCH(C3*100+B3,Key!$G$2:$G$263,0)),"")) | H3: =IF(OR(C3="",B3=""),"",IFERROR(INDEX(Papers!$K$2:$P$12,MATCH(C3,Papers!$A$2:$A$12,0),INDEX(Key!$D$2:$D$263,MATCH(C3*100+B3,Key!$G$2:$G$263,0))),""))
C4: =IF(A4="","",IFERROR(INDEX(Attempts!$D$2:$D$200,MATCH(A4,Attempts!$A$2:$A$200,0)),"?")) | D4: =IF(OR(A4="",B4=""),"",IFERROR(INDEX(Attempts!$M$2:$AP$200,MATCH(A4,Attempts!$A$2:$A$200,0),B4),"")) | E4: =IF(OR(C4="",B4=""),"",IFERROR(INDEX(Key!$C$2:$C$263,MATCH(C4*100+B4,Key!$G$2:$G$263,0)),"")) | F4: =IF(OR(C4="",B4=""),"",IFERROR(INDEX(Key!$E$2:$E$263,MATCH(C4*100+B4,Key!$G$2:$G$263,0)),"")) | H4: =IF(OR(C4="",B4=""),"",IFERROR(INDEX(Papers!$K$2:$P$12,MATCH(C4,Papers!$A$2:$A$12,0),INDEX(Key!$D$2:$D$263,MATCH(C4*100+B4,Key!$G$2:$G$263,0))),""))
C5: =IF(A5="","",IFERROR(INDEX(Attempts!$D$2:$D$200,MATCH(A5,Attempts!$A$2:$A$200,0)),"?")) | D5: =IF(OR(A5="",B5=""),"",IFERROR(INDEX(Attempts!$M$2:$AP$200,MATCH(A5,Attempts!$A$2:$A$200,0),B5),"")) | E5: =IF(OR(C5="",B5=""),"",IFERROR(INDEX(Key!$C$2:$C$263,MATCH(C5*100+B5,Key!$G$2:$G$263,0)),"")) | F5: =IF(OR(C5="",B5=""),"",IFERROR(INDEX(Key!$E$2:$E$263,MATCH(C5*100+B5,Key!$G$2:$G$263,0)),"")) | H5: =IF(OR(C5="",B5=""),"",IFERROR(INDEX(Papers!$K$2:$P$12,MATCH(C5,Papers!$A$2:$A$12,0),INDEX(Key!$D$2:$D$263,MATCH(C5*100+B5,Key!$G$2:$G$263,0))),""))
C6: =IF(A6="","",IFERROR(INDEX(Attempts!$D$2:$D$200,MATCH(A6,Attempts!$A$2:$A$200,0)),"?")) | D6: =IF(OR(A6="",B6=""),"",IFERROR(INDEX(Attempts!$M$2:$AP$200,MATCH(A6,Attempts!$A$2:$A$200,0),B6),"")) | E6: =IF(OR(C6="",B6=""),"",IFERROR(INDEX(Key!$C$2:$C$263,MATCH(C6*100+B6,Key!$G$2:$G$263,0)),"")) | F6: =IF(OR(C6="",B6=""),"",IFERROR(INDEX(Key!$E$2:$E$263,MATCH(C6*100+B6,Key!$G$2:$G$263,0)),"")) | H6: =IF(OR(C6="",B6=""),"",IFERROR(INDEX(Papers!$K$2:$P$12,MATCH(C6,Papers!$A$2:$A$12,0),INDEX(Key!$D$2:$D$263,MATCH(C6*100+B6,Key!$G$2:$G$263,0))),""))
C7: =IF(A7="","",IFERROR(INDEX(Attempts!$D$2:$D$200,MATCH(A7,Attempts!$A$2:$A$200,0)),"?")) | D7: =IF(OR(A7="",B7=""),"",IFERROR(INDEX(Attempts!$M$2:$AP$200,MATCH(A7,Attempts!$A$2:$A$200,0),B7),"")) | E7: =IF(OR(C7="",B7=""),"",IFERROR(INDEX(Key!$C$2:$C$263,MATCH(C7*100+B7,Key!$G$2:$G$263,0)),"")) | F7: =IF(OR(C7="",B7=""),"",IFERROR(INDEX(Key!$E$2:$E$263,MATCH(C7*100+B7,Key!$G$2:$G$263,0)),"")) | H7: =IF(OR(C7="",B7=""),"",IFERROR(INDEX(Papers!$K$2:$P$12,MATCH(C7,Papers!$A$2:$A$12,0),INDEX(Key!$D$2:$D$263,MATCH(C7*100+B7,Key!$G$2:$G$263,0))),""))
C8: =IF(A8="","",IFERROR(INDEX(Attempts!$D$2:$D$200,MATCH(A8,Attempts!$A$2:$A$200,0)),"?")) | D8: =IF(OR(A8="",B8=""),"",IFERROR(INDEX(Attempts!$M$2:$AP$200,MATCH(A8,Attempts!$A$2:$A$200,0),B8),"")) | E8: =IF(OR(C8="",B8=""),"",IFERROR(INDEX(Key!$C$2:$C$263,MATCH(C8*100+B8,Key!$G$2:$G$263,0)),"")) | F8: =IF(OR(C8="",B8=""),"",IFERROR(INDEX(Key!$E$2:$E$263,MATCH(C8*100+B8,Key!$G$2:$G$263,0)),"")) | H8: =IF(OR(C8="",B8=""),"",IFERROR(INDEX(Papers!$K$2:$P$12,MATCH(C8,Papers!$A$2:$A$12,0),INDEX(Key!$D$2:$D$263,MATCH(C8*100+B8,Key!$G$2:$G$263,0))),""))
C9: =IF(A9="","",IFERROR(INDEX(Attempts!$D$2:$D$200,MATCH(A9,Attempts!$A$2:$A$200,0)),"?")) | D9: =IF(OR(A9="",B9=""),"",IFERROR(INDEX(Attempts!$M$2:$AP$200,MATCH(A9,Attempts!$A$2:$A$200,0),B9),"")) | E9: =IF(OR(C9="",B9=""),"",IFERROR(INDEX(Key!$C$2:$C$263,MATCH(C9*100+B9,Key!$G$2:$G$263,0)),"")) | F9: =IF(OR(C9="",B9=""),"",IFERROR(INDEX(Key!$E$2:$E$263,MATCH(C9*100+B9,Key!$G$2:$G$263,0)),"")) | H9: =IF(OR(C9="",B9=""),"",IFERROR(INDEX(Papers!$K$2:$P$12,MATCH(C9,Papers!$A$2:$A$12,0),INDEX(Key!$D$2:$D$263,MATCH(C9*100+B9,Key!$G$2:$G$263,0))),""))
C10: =IF(A10="","",IFERROR(INDEX(Attempts!$D$2:$D$200,MATCH(A10,Attempts!$A$2:$A$200,0)),"?")) | D10: =IF(OR(A10="",B10=""),"",IFERROR(INDEX(Attempts!$M$2:$AP$200,MATCH(A10,Attempts!$A$2:$A$200,0),B10),"")) | E10: =IF(OR(C10="",B10=""),"",IFERROR(INDEX(Key!$C$2:$C$263,MATCH(C10*100+B10,Key!$G$2:$G$263,0)),"")) | F10: =IF(OR(C10="",B10=""),"",IFERROR(INDEX(Key!$E$2:$E$263,MATCH(C10*100+B10,Key!$G$2:$G$263,0)),"")) | H10: =IF(OR(C10="",B10=""),"",IFERROR(INDEX(Papers!$K$2:$P$12,MATCH(C10,Papers!$A$2:$A$12,0),INDEX(Key!$D$2:$D$263,MATCH(C10*100+B10,Key!$G$2:$G$263,0))),""))
C11: =IF(A11="","",IFERROR(INDEX(Attempts!$D$2:$D$200,MATCH(A11,Attempts!$A$2:$A$200,0)),"?")) | D11: =IF(OR(A11="",B11=""),"",IFERROR(INDEX(Attempts!$M$2:$AP$200,MATCH(A11,Attempts!$A$2:$A$200,0),B11),"")) | E11: =IF(OR(C11="",B11=""),"",IFERROR(INDEX(Key!$C$2:$C$263,MATCH(C11*100+B11,Key!$G$2:$G$263,0)),"")) | F11: =IF(OR(C11="",B11=""),"",IFERROR(INDEX(Key!$E$2:$E$263,MATCH(C11*100+B11,Key!$G$2:$G$263,0)),"")) | H11: =IF(OR(C11="",B11=""),"",IFERROR(INDEX(Papers!$K$2:$P$12,MATCH(C11,Papers!$A$2:$A$12,0),INDEX(Key!$D$2:$D$263,MATCH(C11*100+B11,Key!$G$2:$G$263,0))),""))
C12: =IF(A12="","",IFERROR(INDEX(Attempts!$D$2:$D$200,MATCH(A12,Attempts!$A$2:$A$200,0)),"?")) | D12: =IF(OR(A12="",B12=""),"",IFERROR(INDEX(Attempts!$M$2:$AP$200,MATCH(A12,Attempts!$A$2:$A$200,0),B12),"")) | E12: =IF(OR(C12="",B12=""),"",IFERROR(INDEX(Key!$C$2:$C$263,MATCH(C12*100+B12,Key!$G$2:$G$263,0)),"")) | F12: =IF(OR(C12="",B12=""),"",IFERROR(INDEX(Key!$E$2:$E$263,MATCH(C12*100+B12,Key!$G$2:$G$263,0)),"")) | H12: =IF(OR(C12="",B12=""),"",IFERROR(INDEX(Papers!$K$2:$P$12,MATCH(C12,Papers!$A$2:$A$12,0),INDEX(Key!$D$2:$D$263,MATCH(C12*100+B12,Key!$G$2:$G$263,0))),""))
C13: =IF(A13="","",IFERROR(INDEX(Attempts!$D$2:$D$200,MATCH(A13,Attempts!$A$2:$A$200,0)),"?")) | D13: =IF(OR(A13="",B13=""),"",IFERROR(INDEX(Attempts!$M$2:$AP$200,MATCH(A13,Attempts!$A$2:$A$200,0),B13),"")) | E13: =IF(OR(C13="",B13=""),"",IFERROR(INDEX(Key!$C$2:$C$263,MATCH(C13*100+B13,Key!$G$2:$G$263,0)),"")) | F13: =IF(OR(C13="",B13=""),"",IFERROR(INDEX(Key!$E$2:$E$263,MATCH(C13*100+B13,Key!$G$2:$G$263,0)),"")) | H13: =IF(OR(C13="",B13=""),"",IFERROR(INDEX(Papers!$K$2:$P$12,MATCH(C13,Papers!$A$2:$A$12,0),INDEX(Key!$D$2:$D$263,MATCH(C13*100+B13,Key!$G$2:$G$263,0))),""))
... C500: =IF(A500="","",IFERROR(INDEX(Attempts!$D$2:$D$200,MATCH(A500,Attempts!$A$2:$A$200,0)),"?")) | D500: =IF(OR(A500="",B500=""),"",IFERROR(INDEX(Attempts!$M$2:$AP$200,MATCH(A500,Attempts!$A$2:$A$200,0),B500),"")) | E500: =IF(OR(C500="",B500=""),"",IFERROR(INDEX(Key!$C$2:$C$263,MATCH(C500*100+B500,Key!$G$2:$G$263,0)),"")) | F500: =IF(OR(C500="",B500=""),"",IFERROR(INDEX(Key!$E$2:$E$263,MATCH(C500*100+B500,Key!$G$2:$G$263,0)),"")) | H500: =IF(OR(C500="",B500=""),"",IFERROR(INDEX(Papers!$K$2:$P$12,MATCH(C500,Papers!$A$2:$A$12,0),INDEX(Key!$D$2:$D$263,MATCH(C500*100+B500,Key!$G$2:$G$263,0))),""))

Sheet Retest
A1: Original Attempt ID | B1: Retest Attempt ID | C1: Candidate | D1: Paper (orig) | E1: Original % | F1: Retest % | G1: Improvement (percentage points) | H1: Retest paper | I1: Note
C2: =IF(A2="","",IFERROR(INDEX(Attempts!$B$2:$B$200,MATCH(A2,Attempts!$A$2:$A$200,0)),"?")) | D2: =IF(A2="","",IFERROR(INDEX(Attempts!$D$2:$D$200,MATCH(A2,Attempts!$A$2:$A$200,0)),"?")) | E2: =IF(A2="","",IFERROR(INDEX(Attempts!$L$2:$L$200,MATCH(A2,Attempts!$A$2:$A$200,0)),"")) | F2: =IF(B2="","",IFERROR(INDEX(Attempts!$L$2:$L$200,MATCH(B2,Attempts!$A$2:$A$200,0)),"")) | G2: =IF(OR(E2="",F2=""),"",F2-E2) | H2: =IF(B2="","",IFERROR(INDEX(Attempts!$D$2:$D$200,MATCH(B2,Attempts!$A$2:$A$200,0)),"?"))
C3: =IF(A3="","",IFERROR(INDEX(Attempts!$B$2:$B$200,MATCH(A3,Attempts!$A$2:$A$200,0)),"?")) | D3: =IF(A3="","",IFERROR(INDEX(Attempts!$D$2:$D$200,MATCH(A3,Attempts!$A$2:$A$200,0)),"?")) | E3: =IF(A3="","",IFERROR(INDEX(Attempts!$L$2:$L$200,MATCH(A3,Attempts!$A$2:$A$200,0)),"")) | F3: =IF(B3="","",IFERROR(INDEX(Attempts!$L$2:$L$200,MATCH(B3,Attempts!$A$2:$A$200,0)),"")) | G3: =IF(OR(E3="",F3=""),"",F3-E3) | H3: =IF(B3="","",IFERROR(INDEX(Attempts!$D$2:$D$200,MATCH(B3,Attempts!$A$2:$A$200,0)),"?"))
C4: =IF(A4="","",IFERROR(INDEX(Attempts!$B$2:$B$200,MATCH(A4,Attempts!$A$2:$A$200,0)),"?")) | D4: =IF(A4="","",IFERROR(INDEX(Attempts!$D$2:$D$200,MATCH(A4,Attempts!$A$2:$A$200,0)),"?")) | E4: =IF(A4="","",IFERROR(INDEX(Attempts!$L$2:$L$200,MATCH(A4,Attempts!$A$2:$A$200,0)),"")) | F4: =IF(B4="","",IFERROR(INDEX(Attempts!$L$2:$L$200,MATCH(B4,Attempts!$A$2:$A$200,0)),"")) | G4: =IF(OR(E4="",F4=""),"",F4-E4) | H4: =IF(B4="","",IFERROR(INDEX(Attempts!$D$2:$D$200,MATCH(B4,Attempts!$A$2:$A$200,0)),"?"))
C5: =IF(A5="","",IFERROR(INDEX(Attempts!$B$2:$B$200,MATCH(A5,Attempts!$A$2:$A$200,0)),"?")) | D5: =IF(A5="","",IFERROR(INDEX(Attempts!$D$2:$D$200,MATCH(A5,Attempts!$A$2:$A$200,0)),"?")) | E5: =IF(A5="","",IFERROR(INDEX(Attempts!$L$2:$L$200,MATCH(A5,Attempts!$A$2:$A$200,0)),"")) | F5: =IF(B5="","",IFERROR(INDEX(Attempts!$L$2:$L$200,MATCH(B5,Attempts!$A$2:$A$200,0)),"")) | G5: =IF(OR(E5="",F5=""),"",F5-E5) | H5: =IF(B5="","",IFERROR(INDEX(Attempts!$D$2:$D$200,MATCH(B5,Attempts!$A$2:$A$200,0)),"?"))
C6: =IF(A6="","",IFERROR(INDEX(Attempts!$B$2:$B$200,MATCH(A6,Attempts!$A$2:$A$200,0)),"?")) | D6: =IF(A6="","",IFERROR(INDEX(Attempts!$D$2:$D$200,MATCH(A6,Attempts!$A$2:$A$200,0)),"?")) | E6: =IF(A6="","",IFERROR(INDEX(Attempts!$L$2:$L$200,MATCH(A6,Attempts!$A$2:$A$200,0)),"")) | F6: =IF(B6="","",IFERROR(INDEX(Attempts!$L$2:$L$200,MATCH(B6,Attempts!$A$2:$A$200,0)),"")) | G6: =IF(OR(E6="",F6=""),"",F6-E6) | H6: =IF(B6="","",IFERROR(INDEX(Attempts!$D$2:$D$200,MATCH(B6,Attempts!$A$2:$A$200,0)),"?"))
C7: =IF(A7="","",IFERROR(INDEX(Attempts!$B$2:$B$200,MATCH(A7,Attempts!$A$2:$A$200,0)),"?")) | D7: =IF(A7="","",IFERROR(INDEX(Attempts!$D$2:$D$200,MATCH(A7,Attempts!$A$2:$A$200,0)),"?")) | E7: =IF(A7="","",IFERROR(INDEX(Attempts!$L$2:$L$200,MATCH(A7,Attempts!$A$2:$A$200,0)),"")) | F7: =IF(B7="","",IFERROR(INDEX(Attempts!$L$2:$L$200,MATCH(B7,Attempts!$A$2:$A$200,0)),"")) | G7: =IF(OR(E7="",F7=""),"",F7-E7) | H7: =IF(B7="","",IFERROR(INDEX(Attempts!$D$2:$D$200,MATCH(B7,Attempts!$A$2:$A$200,0)),"?"))
C8: =IF(A8="","",IFERROR(INDEX(Attempts!$B$2:$B$200,MATCH(A8,Attempts!$A$2:$A$200,0)),"?")) | D8: =IF(A8="","",IFERROR(INDEX(Attempts!$D$2:$D$200,MATCH(A8,Attempts!$A$2:$A$200,0)),"?")) | E8: =IF(A8="","",IFERROR(INDEX(Attempts!$L$2:$L$200,MATCH(A8,Attempts!$A$2:$A$200,0)),"")) | F8: =IF(B8="","",IFERROR(INDEX(Attempts!$L$2:$L$200,MATCH(B8,Attempts!$A$2:$A$200,0)),"")) | G8: =IF(OR(E8="",F8=""),"",F8-E8) | H8: =IF(B8="","",IFERROR(INDEX(Attempts!$D$2:$D$200,MATCH(B8,Attempts!$A$2:$A$200,0)),"?"))
C9: =IF(A9="","",IFERROR(INDEX(Attempts!$B$2:$B$200,MATCH(A9,Attempts!$A$2:$A$200,0)),"?")) | D9: =IF(A9="","",IFERROR(INDEX(Attempts!$D$2:$D$200,MATCH(A9,Attempts!$A$2:$A$200,0)),"?")) | E9: =IF(A9="","",IFERROR(INDEX(Attempts!$L$2:$L$200,MATCH(A9,Attempts!$A$2:$A$200,0)),"")) | F9: =IF(B9="","",IFERROR(INDEX(Attempts!$L$2:$L$200,MATCH(B9,Attempts!$A$2:$A$200,0)),"")) | G9: =IF(OR(E9="",F9=""),"",F9-E9) | H9: =IF(B9="","",IFERROR(INDEX(Attempts!$D$2:$D$200,MATCH(B9,Attempts!$A$2:$A$200,0)),"?"))
C10: =IF(A10="","",IFERROR(INDEX(Attempts!$B$2:$B$200,MATCH(A10,Attempts!$A$2:$A$200,0)),"?")) | D10: =IF(A10="","",IFERROR(INDEX(Attempts!$D$2:$D$200,MATCH(A10,Attempts!$A$2:$A$200,0)),"?")) | E10: =IF(A10="","",IFERROR(INDEX(Attempts!$L$2:$L$200,MATCH(A10,Attempts!$A$2:$A$200,0)),"")) | F10: =IF(B10="","",IFERROR(INDEX(Attempts!$L$2:$L$200,MATCH(B10,Attempts!$A$2:$A$200,0)),"")) | G10: =IF(OR(E10="",F10=""),"",F10-E10) | H10: =IF(B10="","",IFERROR(INDEX(Attempts!$D$2:$D$200,MATCH(B10,Attempts!$A$2:$A$200,0)),"?"))
C11: =IF(A11="","",IFERROR(INDEX(Attempts!$B$2:$B$200,MATCH(A11,Attempts!$A$2:$A$200,0)),"?")) | D11: =IF(A11="","",IFERROR(INDEX(Attempts!$D$2:$D$200,MATCH(A11,Attempts!$A$2:$A$200,0)),"?")) | E11: =IF(A11="","",IFERROR(INDEX(Attempts!$L$2:$L$200,MATCH(A11,Attempts!$A$2:$A$200,0)),"")) | F11: =IF(B11="","",IFERROR(INDEX(Attempts!$L$2:$L$200,MATCH(B11,Attempts!$A$2:$A$200,0)),"")) | G11: =IF(OR(E11="",F11=""),"",F11-E11) | H11: =IF(B11="","",IFERROR(INDEX(Attempts!$D$2:$D$200,MATCH(B11,Attempts!$A$2:$A$200,0)),"?"))
C12: =IF(A12="","",IFERROR(INDEX(Attempts!$B$2:$B$200,MATCH(A12,Attempts!$A$2:$A$200,0)),"?")) | D12: =IF(A12="","",IFERROR(INDEX(Attempts!$D$2:$D$200,MATCH(A12,Attempts!$A$2:$A$200,0)),"?")) | E12: =IF(A12="","",IFERROR(INDEX(Attempts!$L$2:$L$200,MATCH(A12,Attempts!$A$2:$A$200,0)),"")) | F12: =IF(B12="","",IFERROR(INDEX(Attempts!$L$2:$L$200,MATCH(B12,Attempts!$A$2:$A$200,0)),"")) | G12: =IF(OR(E12="",F12=""),"",F12-E12) | H12: =IF(B12="","",IFERROR(INDEX(Attempts!$D$2:$D$200,MATCH(B12,Attempts!$A$2:$A$200,0)),"?"))
C13: =IF(A13="","",IFERROR(INDEX(Attempts!$B$2:$B$200,MATCH(A13,Attempts!$A$2:$A$200,0)),"?")) | D13: =IF(A13="","",IFERROR(INDEX(Attempts!$D$2:$D$200,MATCH(A13,Attempts!$A$2:$A$200,0)),"?")) | E13: =IF(A13="","",IFERROR(INDEX(Attempts!$L$2:$L$200,MATCH(A13,Attempts!$A$2:$A$200,0)),"")) | F13: =IF(B13="","",IFERROR(INDEX(Attempts!$L$2:$L$200,MATCH(B13,Attempts!$A$2:$A$200,0)),"")) | G13: =IF(OR(E13="",F13=""),"",F13-E13) | H13: =IF(B13="","",IFERROR(INDEX(Attempts!$D$2:$D$200,MATCH(B13,Attempts!$A$2:$A$200,0)),"?"))
... C201: =IF(A201="","",IFERROR(INDEX(Attempts!$B$2:$B$200,MATCH(A201,Attempts!$A$2:$A$200,0)),"?")) | D201: =IF(A201="","",IFERROR(INDEX(Attempts!$D$2:$D$200,MATCH(A201,Attempts!$A$2:$A$200,0)),"?")) | E201: =IF(A201="","",IFERROR(INDEX(Attempts!$L$2:$L$200,MATCH(A201,Attempts!$A$2:$A$200,0)),"")) | F201: =IF(B201="","",IFERROR(INDEX(Attempts!$L$2:$L$200,MATCH(B201,Attempts!$A$2:$A$200,0)),"")) | G201: =IF(OR(E201="",F201=""),"",F201-E201) | H201: =IF(B201="","",IFERROR(INDEX(Attempts!$D$2:$D$200,MATCH(B201,Attempts!$A$2:$A$200,0)),"?"))

Sheet Baseline_40
A1: Candidate
A2: Date
A4: Q | B4: Section # | C4: Correct answer | D4: Candidate answer | E4: Correct (1/0) | G4: Section | H4: Questions | I4: Correct | J4: % | K4: Guide (not official) | L4: Next papers
A5: 1 | B5: 1 | C5: A | E5: =IF(D5="",0,IF(UPPER(TRIM(D5))=C5,1,0)) | G5: A Bookkeeping & Basic Accounting | H5: 12 | I5: =SUMIF($B$5:$B$44,1,$E$5:$E$44) | J5: =ROUND(I5/H5*100,1) | K5: =IF(COUNTA($D$5:$D$44)=0,"",IF(J5<50,"Needs re-teaching",IF(J5<75,"Developing","Relatively strong"))) | L5: Papers 2-5
A6: 2 | B6: 1 | C6: B | E6: =IF(D6="",0,IF(UPPER(TRIM(D6))=C6,1,0)) | G6: B Taxation | H6: 6 | I6: =SUMIF($B$5:$B$44,2,$E$5:$E$44) | J6: =ROUND(I6/H6*100,1) | K6: =IF(COUNTA($D$5:$D$44)=0,"",IF(J6<50,"Needs re-teaching",IF(J6<75,"Developing","Relatively strong"))) | L6: Paper 6
A7: 3 | B7: 1 | C7: A | E7: =IF(D7="",0,IF(UPPER(TRIM(D7))=C7,1,0)) | G7: C Budget & Financial Discipline | H7: 5 | I7: =SUMIF($B$5:$B$44,3,$E$5:$E$44) | J7: =ROUND(I7/H7*100,1) | K7: =IF(COUNTA($D$5:$D$44)=0,"",IF(J7<50,"Needs re-teaching",IF(J7<75,"Developing","Relatively strong"))) | L7: Paper 7 (+5 BRS)
A8: 4 | B8: 1 | C8: B | E8: =IF(D8="",0,IF(UPPER(TRIM(D8))=C8,1,0)) | G8: D Banking | H8: 6 | I8: =SUMIF($B$5:$B$44,4,$E$5:$E$44) | J8: =ROUND(I8/H8*100,1) | K8: =IF(COUNTA($D$5:$D$44)=0,"",IF(J8<50,"Needs re-teaching",IF(J8<75,"Developing","Relatively strong"))) | L8: Paper 8
A9: 5 | B9: 1 | C9: B | E9: =IF(D9="",0,IF(UPPER(TRIM(D9))=C9,1,0)) | G9: E Computer & Modern Tools | H9: 6 | I9: =SUMIF($B$5:$B$44,5,$E$5:$E$44) | J9: =ROUND(I9/H9*100,1) | K9: =IF(COUNTA($D$5:$D$44)=0,"",IF(J9<50,"Needs re-teaching",IF(J9<75,"Developing","Relatively strong"))) | L9: Paper 9
A10: 6 | B10: 1 | C10: A | E10: =IF(D10="",0,IF(UPPER(TRIM(D10))=C10,1,0)) | G10: F Current Affairs / GA | H10: 5 | I10: =SUMIF($B$5:$B$44,6,$E$5:$E$44) | J10: =ROUND(I10/H10*100,1) | K10: =IF(COUNTA($D$5:$D$44)=0,"",IF(J10<50,"Needs re-teaching",IF(J10<75,"Developing","Relatively strong"))) | L10: Paper 10
A11: 7 | B11: 1 | C11: B | E11: =IF(D11="",0,IF(UPPER(TRIM(D11))=C11,1,0))
A12: 8 | B12: 1 | C12: B | E12: =IF(D12="",0,IF(UPPER(TRIM(D12))=C12,1,0)) | G12: TOTAL | H12: =SUM(H5:H10) | I12: =SUM(I5:I10) | J12: =ROUND(I12/H12*100,1)
A13: 9 | B13: 1 | C13: C | E13: =IF(D13="",0,IF(UPPER(TRIM(D13))=C13,1,0))
A14: 10 | B14: 1 | C14: B | E14: =IF(D14="",0,IF(UPPER(TRIM(D14))=C14,1,0)) | G14: Baseline key = the supplied Teacher Answer Key (Quick Scoring). Diagnostic only; no official cutoff. Decide teaching from section/question evidence, not the total.
A15: 11 | B15: 1 | C15: B | E15: =IF(D15="",0,IF(UPPER(TRIM(D15))=C15,1,0))
A16: 12 | B16: 1 | C16: C | E16: =IF(D16="",0,IF(UPPER(TRIM(D16))=C16,1,0))
A17: 13 | B17: 2 | C17: B | E17: =IF(D17="",0,IF(UPPER(TRIM(D17))=C17,1,0))
A18: 14 | B18: 2 | C18: B | E18: =IF(D18="",0,IF(UPPER(TRIM(D18))=C18,1,0))
A19: 15 | B19: 2 | C19: C | E19: =IF(D19="",0,IF(UPPER(TRIM(D19))=C19,1,0))
A20: 16 | B20: 2 | C20: B | E20: =IF(D20="",0,IF(UPPER(TRIM(D20))=C20,1,0))
A21: 17 | B21: 2 | C21: B | E21: =IF(D21="",0,IF(UPPER(TRIM(D21))=C21,1,0))
A22: 18 | B22: 2 | C22: A | E22: =IF(D22="",0,IF(UPPER(TRIM(D22))=C22,1,0))
A23: 19 | B23: 3 | C23: B | E23: =IF(D23="",0,IF(UPPER(TRIM(D23))=C23,1,0))
A24: 20 | B24: 3 | C24: A | E24: =IF(D24="",0,IF(UPPER(TRIM(D24))=C24,1,0))
A25: 21 | B25: 3 | C25: A | E25: =IF(D25="",0,IF(UPPER(TRIM(D25))=C25,1,0))
A26: 22 | B26: 3 | C26: B | E26: =IF(D26="",0,IF(UPPER(TRIM(D26))=C26,1,0))
... A44: 40 | B44: 6 | C44: C | E44: =IF(D44="",0,IF(UPPER(TRIM(D44))=C44,1,0))
